Workbook

Sheet 00_README
A1: NACS 数据收集模板 v1.0
A3: 用途
A4: 本模板用于收集香港 IPO 基石投资量化模型 (NACS) 的回测原始数据。
A5: 覆盖范围: 2022-01-01 至 2026-04-30 期间在 HKEX 主板上市的全部新股 (~250只)。
A7: 工作流
A8: 步骤 1: 在 sheet [01_ipo_master] 用 Wind WSET 函数批量拉出该期间所有 IPO 的代码列表。
A9: 步骤 2: 用 Wind WSS 函数为每只 IPO 拉横截面字段 (发行价/募资额/认购倍数等)。
A10: 步骤 3: 在 sheet [02_ipo_cornerstones] 手填或半自动填写每只IPO的基石明细 (招股书原文+ticket size)。
A11: 步骤 4: 在 sheet [03_company_fundamentals] 填写公司基本面 (招股书披露的3年财务)。
A12: 步骤 5: 在 sheet [04_ccass_unlocks] 填CCASS解禁日前后的持仓变动。
A13: 步骤 6: sheet [05_hsi_macro] 用 Wind WSD 拉恒指日频; sheet [06_price_index] 列出每只IPO要拉的价格区间, 价格数据保存到独立CSV文件。
A14: 步骤 7: 全部填好后, 把整份 xlsx 发给我, 我来跑 loader 灌库 + 回测。
... A56: → 全部就位,可以发我做 loader+回测。

Sheet 01_ipo_master
A1: stock_code | B1: company_name_zh | C1: listing_date | D1: pricing_date | E1: listing_chapter | F1: is_a_h | G1: a_share_code | H1: gics_l2 | I1: offer_price_hkd | J1: offer_price_low | K1: offer_price_high | L1: offering_size_hkd | M1: intl_oversub | N1: public_oversub | O1: clawback_triggered | P1: greenshoe_pct | Q1: sponsor_primary | R1: joint_sponsor_count | S1: sponsor_tier | T1: auditor_tier | U1: pe_at_offer | V1: pe_peer_median | W1: last_round_premium | X1: lockup_months | Y1: is_delisted | Z1: delisting_date | AA1: data_quality_notes | AB1: wind_code_clean | AC1: close_day1_hkd | AD1: open_day1_hkd | AE1: high_day1_hkd | AF1: low_day1_hkd | AG1: listing_board | AH1: h_stock_class | AI1: _orig_chapter | AJ1: is_18a_dual_listing
A2: Wind代码 ★必填 | B2: 证券中文简称 ★必填 | C2: ipo_listdate yyyy-mm-dd ★必填 | D2: ipo_setdate yyyy-mm-dd ★必填 | E2: (枚举) ★必填 | F2: AH双重上市 0/1 ★必填 | G2: 对应A股代码 ○选填 | H2: 行业GICSL2 ★必填 | I2: ipo_price HKD ★必填 | J2: ipo_offerprice_low HKD ○选填 | K2: ipo_offerprice_high HKD ○选填 | L2: ipo_amount HKD ★必填 | M2: ipo_intoversub 倍 ★必填 | N2: ipo_puboversub 倍 ★必填 | O2: (派生) 0/1 ★必填 | P2: ipo_oversinl_pct 比例 ○选填 | Q2: ipo_underwriter ★必填 | R2: (派生:计数+号) 整数 ○选填 | S2: (枚举1/2/3) 1/2/3 ★必填 | T2: (枚举1/2/3) 1/2/3 ○选填 | U2: ipo_pe 倍 ○选填 | V2: (代偿:同GICSL2同PE平均) 倍 ○选填 ⚠偏态分布,极值>100例多为生医医药,谨慎使用 | W2: (招股书:Pre-IPO最后一轮) 比例 ○选填 | X2: 招股书锁定期 月 ○选填 | Y2: 退市状态 0/1 ★必填 | Z2: 退市日期 yyyy-mm-dd ○选填 | AA2: (备注) ○选填 | AB2: Wind代码(去前导0) 仅供公式引用 | AC2: 上市首日收盘价 HKD | AD2: 上市首日开盘价 HKD | AE2: 上市首日最高 HKD | AF2: 上市首日最低 HKD | AG2: 上市板 (主板/创业板) | AH2: H股/红筹股 (首发明细) | AI2: 原E列备份(派生用) | AJ2: 18A 同时为 A+H 双重上市 1=是, 0=否 (派生:ch_18a AND is_a_h=1)
A3: 03296.HK | B3: 华勤技术 | C3: 2026-04-23 | D3: =IFERROR(IF(ISNUMBER($C3),$C3-2,DATEVALUE($C3)-2),"") -> 46133 | E3: a_plus_h | F3: 1 | G3: 603296.SH | H3: TECH_HARDWARE | I3: 77.7 | J3: 70 | K3: 77.7 | L3: 4549000000 | M3: 8 | N3: 531.33 | O3: 0 | P3: 0.15 | Q3: 中金公司+美银证券 | R3: 2 | S3: 1 | T3: 1 | U3: 12.2 | V3: =IFERROR((SUMIFS($U$3:$U$392,$H$3:$H$392,$H3,$U$3:$U$392,">0")-IF(IFERROR($U3,0)>0,$U3,0))/(COUNTIFS($H$3:$H$392,$H3,$U$3:$U$392,">0")-IF(IFERROR($U3,0)>0,1,0)),"") | W3: -0.28 | X3: 6 | Y3: 0 | AA3: ticket_size estimated | AC3: 推荐做法(更稳): | AI3: a_plus_h | AJ3: 0
A4: 3750.HK | B4: 宁德时代 | C4: 45797 | D4: =IFERROR(IF(ISNUMBER($C4),$C4-2,DATEVALUE($C4)-2),"") -> 45795 | E4: a_plus_h | F4: =IF(AND(G4<>"",G4<>0),1,0) -> 1 | G4: 300750.SZ | H4: 工业(HS)-工业工程(HS)-能源储存装置(HS) | I4: 263 | K4: 263 | L4: 41005723900 | M4: 15.17 | N4: 151.15 | O4: =IF(IFERROR(N4*1,0)>=15,1,0) -> 1 | P4: 53.053 | Q4: 法国巴黎证券(亚洲)有限公司,国泰君安证券(香港)有限公司,高盛(亚洲)有限责任公司,摩根士丹利亚洲有限公司,UBS AG Hong Kong Branch,中国国际金融香港证券有限公司,中信建投(国际)融资有限公司,J.P. Morgan Securities (Asia Pacific) Limited,Merrill Lynch (Asia Pacific) Limited | R4: =IF(Q4="",0,LEN(Q4)-LEN(SUBSTITUTE(Q4,",",""))+1) -> 9 | U4: 21.245432 | V4: =IFERROR((SUMIFS($U$3:$U$392,$H$3:$H$392,$H4,$U$3:$U$392,">0")-IF(IFERROR($U4,0)>0,$U4,0))/(COUNTIFS($H$3:$H$392,$H4,$U$3:$U$392,">0")-IF(IFERROR($U4,0)>0,1,0)),"") -> 167.7774 | X4: 6 | Y4: =WSS(AB4,"sec_status") | AB4: =IF(LEFT(A4,1)="0",MID(A4,2,99),A4) -> 3750.HK | AC4: 306.2 | AD4: 296 | AE4: 311.4 | AF4: 291 | AG4: 主板 | AH4: H股 | AI4: 主板 | AJ4: 0
A5: 0300.HK | B5: 美的集团 | C5: 45552 | D5: =IFERROR(IF(ISNUMBER($C5),$C5-2,DATEVALUE($C5)-2),"") -> 45550 | E5: a_plus_h | F5: =IF(AND(G5<>"",G5<>0),1,0) -> 1 | G5: 000333.SZ | H5: 非必需性消费(HS)-家庭电器及用品(HS)-家庭电器(HS) | I5: 54.8 | J5: 52 | K5: 54.8 | L5: 35666497800 | M5: 8.06 | N5: 5.31 | O5: =IF(IFERROR(N5*1,0)>=15,1,0) -> 0 | P5: 46.145 | Q5: 中国国际金融香港证券有限公司,Merrill Lynch (Asia Pacific) Limited,UBS AG Hong Kong Branch,中信里昂证券有限公司,高盛(亚洲)有限责任公司,华泰金融控股(香港)有限公司,广发证券(香港)经纪有限公司,招银国际融资有限公司,法国巴黎证券(亚洲)有限公司,富途证券国际(香港)有限公司 | R5: =IF(Q5="",0,LEN(Q5)-LEN(SUBSTITUTE(Q5,",",""))+1) -> 10 | U5: 11.134372 | V5: =IFERROR((SUMIFS($U$3:$U$392,$H$3:$H$392,$H5,$U$3:$U$392,">0")-IF(IFERROR($U5,0)>0,$U5,0))/(COUNTIFS($H$3:$H$392,$H5,$U$3:$U$392,">0")-IF(IFERROR($U5,0)>0,1,0)),"") -> 6.9752519 | X5: 6 | Y5: =[1]!wss(AB5,"sec_status","cols=1;rows=1") | AB5: =IF(LEFT(A5,1)="0",MID(A5,2,99),A5) -> 300.HK | AC5: 59.1 | AD5: 59.2 | AE5: 60 | AF5: 58 | AG5: 主板 | AH5: H股 | AI5: 主板 | AJ5: 0
A6: 6936.HK | B6: 顺丰控股 | C6: 45623 | D6: =IFERROR(IF(ISNUMBER($C6),$C6-2,DATEVALUE($C6)-2),"") -> 45621 | E6: a_plus_h | F6: =IF(AND(G6<>"",G6<>0),1,0) -> 1 | G6: 002352.SZ | H6: 工业(HS)-工用运输(HS)-航空货运及物流(HS) | I6: 34.3 | J6: 32.3 | K6: 36.3 | L6: 5831000000 | M6: 10.1 | N6: 79.07 | O6: =IF(IFERROR(N6*1,0)>=15,1,0) -> 1 | P6: 0 | Q6: 高盛(亚洲)有限责任公司,华泰金融控股(香港)有限公司,J.P. Morgan Securities (Asia Pacific) Limited,中国国际金融香港证券有限公司,UBS AG Hong Kong Branch,农银国际证券有限公司,中银国际亚洲有限公司,招银国际融资有限公司,星展亚洲融资有限公司,广发证券(香港)经纪有限公司,工银国际证券有限公司 | R6: =IF(Q6="",0,LEN(Q6)-LEN(SUBSTITUTE(Q6,",",""))+1) -> 11 | U6: 18.821727 | V6: =IFERROR((SUMIFS($U$3:$U$392,$H$3:$H$392,$H6,$U$3:$U$392,">0")-IF(IFERROR($U6,0)>0,$U6,0))/(COUNTIFS($H$3:$H$392,$H6,$U$3:$U$392,">0")-IF(IFERROR($U6,0)>0,1,0)),"") -> 16.263307 | X6: 6 | Y6: =[1]!wss(AB6,"sec_status","cols=1;rows=1") -> L | AB6: =IF(LEFT(A6,1)="0",MID(A6,2,99),A6) -> 6936.HK | AC6: 34.3 | AD6: 34.3 | AE6: 35.5 | AF6: 34.3 | AG6: 主板 | AH6: H股 | AI6: 主板 | AJ6: 0
A7: 9973.HK | B7: 奇瑞汽车 | C7: 45925 | D7: =IFERROR(IF(ISNUMBER($C7),$C7-2,DATEVALUE($C7)-2),"") -> 45923 | E7: main_board_profitable | F7: =IF(AND(G7<>"",G7<>0),1,0) -> 0 | H7: 非必需性消费(HS)-汽车(HS)-汽车Ⅲ(HS) | I7: 30.75 | J7: 27.75 | K7: 30.75 | L7: 10417266675 | M7: 11.61 | N7: 308.18 | O7: =IF(IFERROR(N7*1,0)>=15,1,0) -> 1 | P7: 12.493 | Q7: 中国国际金融香港证券有限公司,华泰金融控股(香港)有限公司,广发证券(香港)经纪有限公司,中信里昂证券有限公司,中银国际亚洲有限公司,招银国际融资有限公司,农银国际证券有限公司,富途证券国际(香港)有限公司 | R7: =IF(Q7="",0,LEN(Q7)-LEN(SUBSTITUTE(Q7,",",""))+1) -> 8 | U7: 11.618397 | V7: =IFERROR((SUMIFS($U$3:$U$392,$H$3:$H$392,$H7,$U$3:$U$392,">0")-IF(IFERROR($U7,0)>0,$U7,0))/(COUNTIFS($H$3:$H$392,$H7,$U$3:$U$392,">0")-IF(IFERROR($U7,0)>0,1,0)),"") -> 18.637358 | X7: 6 | Y7: =[1]!wss(AB7,"sec_status","cols=1;rows=1") -> L | AB7: =IF(LEFT(A7,1)="0",MID(A7,2,99),A7) -> 9973.HK | AC7: 31.92 | AD7: 34.2 | AE7: 34.98 | AF7: 31.72 | AG7: 主板 | AH7: H股 | AI7: 主板 | AJ7: 0
A8: 2714.HK | B8: 牧原股份 | C8: 46059 | D8: =IFERROR(IF(ISNUMBER($C8),$C8-2,DATEVALUE($C8)-2),"") -> 46057 | E8: a_plus_h | F8: =IF(AND(G8<>"",G8<>0),1,0) -> 1 | G8: 002714.SZ | H8: 必需性消费(HS)-农业产品(HS)-禽畜肉类(HS) | I8: 39 | K8: 39 | L8: 12098700900 | M8: 8.62 | N8: 5.88 | O8: =IF(IFERROR(N8*1,0)>=15,1,0) -> 0 | P8: 13.95 | Q8: 摩根士丹利亚洲有限公司,中信里昂证券有限公司,高盛(亚洲)有限责任公司,中国国际金融香港证券有限公司,Merrill Lynch (Asia Pacific) Limited,招银国际融资有限公司,招商证券(香港)有限公司,农银国际证券有限公司,中银国际亚洲有限公司,交银国际证券有限公司,建银国际金融有限公司,长江证券经纪(香港)有限公司,中国银河国际证券(香港)有限公司,中国光大证券(香港)有限公司,富途证券国际(香港)有限公司,农银国际融资有限公司 | R8: =IF(Q8="",0,LEN(Q8)-LEN(SUBSTITUTE(Q8,",",""))+1) -> 16 | U8: 11.586709 | V8: =IFERROR((SUMIFS($U$3:$U$392,$H$3:$H$392,$H8,$U$3:$U$392,">0")-IF(IFERROR($U8,0)>0,$U8,0))/(COUNTIFS($H$3:$H$392,$H8,$U$3:$U$392,">0")-IF(IFERROR($U8,0)>0,1,0)),"") -> 12.927582 | X8: 6 | Y8: =[1]!wss(AB8,"sec_status","cols=1;rows=1") -> L | AB8: =IF(LEFT(A8,1)="0",MID(A8,2,99),A8) -> 2714.HK | AC8: 40.52 | AD8: 39 | AE8: 41.72 | AF8: 38.98 | AG8: 主板 | AH8: H股 | AI8: 主板 | AJ8: 0
A9: 3296.HK | B9: 华勤技术 | C9: 46135 | D9: =IFERROR(IF(ISNUMBER($C9),$C9-2,DATEVALUE($C9)-2),"") -> 46133 | E9: a_plus_h | F9: =IF(AND(G9<>"",G9<>0),1,0) -> 1 | G9: 603296.SH | H9: 资讯科技业(HS)-资讯科技器材(HS)-消费性电讯设备(HS) | I9: 77.7 | K9: 77.7 | L9: 4549195140 | M9: 13.34 | N9: 531.33 | O9: =IF(IFERROR(N9*1,0)>=15,1,0) -> 1 | P9: 0 | Q9: 中国国际金融香港证券有限公司,Merrill Lynch (Asia Pacific) Limited,高盛(亚洲)有限责任公司,中信里昂证券有限公司,农银国际证券有限公司,富途证券国际(香港)有限公司,老虎证券(香港)环球有限公司,农银国际融资有限公司 | R9: =IF(Q9="",0,LEN(Q9)-LEN(SUBSTITUTE(Q9,",",""))+1) -> 8 | U9: 18.472672 | V9: =IFERROR((SUMIFS($U$3:$U$392,$H$3:$H$392,$H9,$U$3:$U$392,">0")-IF(IFERROR($U9,0)>0,$U9,0))/(COUNTIFS($H$3:$H$392,$H9,$U$3:$U$392,">0")-IF(IFERROR($U9,0)>0,1,0)),"") -> 44.735767 | X9: 6 | Y9: =[1]!wss(AB9,"sec_status","cols=1;rows=1") -> L | AB9: =IF(LEFT(A9,1)="0",MID(A9,2,99),A9) -> 3296.HK | AC9: 88 | AD9: 87.55 | AE9: 90.95 | AF9: 85 | AG9: 主板 | AH9: H股 | AI9: 主板 | AJ9: 0
A10: 9878.HK | B10: 汇通达网络 | C10: 44610 | D10: =IFERROR(IF(ISNUMBER($C10),$C10-2,DATEVALUE($C10)-2),"") -> 44608 | E10: main_board_profitable | F10: =IF(AND(G10<>"",G10<>0),1,0) -> 0 | H10: 非必需性消费(HS)-专业零售(HS)-线上零售商(HS) | I10: 43 | J10: 43 | K10: 48 | L10: 2318207400 | M10: 2.0497 | N10: 1.67 | O10: =IF(IFERROR(N10*1,0)>=15,1,0) -> 0 | P10: 0.9566 | Q10: 中国国际金融香港证券有限公司,花旗环球金融亚洲有限公司,Citigroup Global Markets Limited,华兴证券(香港)有限公司,香港上海汇丰银行有限公司,海通国际证券有限公司,浦银国际融资有限公司,招银国际融资有限公司,交银国际证券有限公司,中银国际亚洲有限公司,建银国际金融有限公司,农银国际证券有限公司,富途证券国际(香港)有限公司,联合证券有限公司 | R10: =IF(Q10="",0,LEN(Q10)-LEN(SUBSTITUTE(Q10,",",""))+1) -> 14 | U10: -50.029372 | V10: =IFERROR((SUMIFS($U$3:$U$392,$H$3:$H$392,$H10,$U$3:$U$392,">0")-IF(IFERROR($U10,0)>0,$U10,0))/(COUNTIFS($H$3:$H$392,$H10,$U$3:$U$392,">0")-IF(IFERROR($U10,0)>0,1,0)),"") -> 28.634596 | X10: 6 | Y10: =[1]!wss(AB10,"sec_status","cols=1;rows=1") -> L | AB10: =IF(LEFT(A10,1)="0",MID(A10,2,99),A10) -> 9878.HK | AC10: 45.1 | AD10: 43.55 | AE10: 45.5 | AF10: 43 | AG10: 主板 | AH10: H股 | AI10: 主板 | AJ10: 0
A11: 6963.HK | B11: 阳光保险 | C11: 44904 | D11: =IFERROR(IF(ISNUMBER($C11),$C11-2,DATEVALUE($C11)-2),"") -> 44902 | E11: main_board_profitable | F11: =IF(AND(G11<>"",G11<>0),1,0) -> 0 | H11: 金融业(HS)-保险(HS)-保险Ⅲ(HS) | I11: 5.83 | J11: 5.83 | K11: 6.45 | L11: 6705389075 | M11: 1.34 | N11: 0.13 | O11: =IF(IFERROR(N11*1,0)>=15,1,0) -> 0 | P11: 0 | Q11: 华泰金融控股(香港)有限公司,中国国际金融香港证券有限公司,UBS AG Hong Kong Branch,建银国际金融有限公司,法国巴黎证券(亚洲)有限公司,交银国际证券有限公司,工银国际证券有限公司,招银国际融资有限公司,中信里昂证券有限公司,农银国际证券有限公司,招商证券(香港)有限公司,申万宏源证券(香港)有限公司,东吴证券国际经纪有限公司 | R11: =IF(Q11="",0,LEN(Q11)-LEN(SUBSTITUTE(Q11,",",""))+1) -> 13 | U11: 9.3189273 | V11: =IFERROR((SUMIFS($U$3:$U$392,$H$3:$H$392,$H11,$U$3:$U$392,">0")-IF(IFERROR($U11,0)>0,$U11,0))/(COUNTIFS($H$3:$H$392,$H11,$U$3:$U$392,">0")-IF(IFERROR($U11,0)>0,1,0)),"") -> 140.71723 | Y11: =[1]!wss(AB11,"sec_status","cols=1;rows=1") -> L | AB11: =IF(LEFT(A11,1)="0",MID(A11,2,99),A11) -> 6963.HK | AC11: 5.83 | AD11: 5.83 | AE11: 5.83 | AF11: 5.51 | AG11: 主板 | AH11: H股 | AI11: 主板 | AJ11: 0
A12: 2423.HK | B12: 贝壳-W | C12: 44692 | D12: =IFERROR(IF(ISNUMBER($C12),$C12-2,DATEVALUE($C12)-2),"") -> 44690 | E12: 18a | F12: =IF(AND(G12<>"",G12<>0),1,0) -> 0 | H12: 地产建筑业(HS)-地产(HS)-地产代理(HS) | L12: 0 | M12: 0 | N12: 0 | O12: =IF(IFERROR(N12*1,0)>=15,1,0) -> 0 | P12: 0 | Q12: 0 | R12: =IF(Q12="",0,LEN(Q12)-LEN(SUBSTITUTE(Q12,",",""))+1) -> 1 | U12: 0 | V12: =IFERROR((SUMIFS($U$3:$U$392,$H$3:$H$392,$H12,$U$3:$U$392,">0")-IF(IFERROR($U12,0)>0,$U12,0))/(COUNTIFS($H$3:$H$392,$H12,$U$3:$U$392,">0")-IF(IFERROR($U12,0)>0,1,0)),"") | Y12: =[1]!wss(AB12,"sec_status","cols=1;rows=1") -> L | AB12: =IF(LEFT(A12,1)="0",MID(A12,2,99),A12) -> 2423.HK | AC12: 30.75 | AD12: 30 | AE12: 32.45 | AF12: 30 | AG12: 主板 | AI12: 主板 | AJ12: 0
A13: 6031.HK | B13: 三一重工 | C13: 45958 | D13: =IFERROR(IF(ISNUMBER($C13),$C13-2,DATEVALUE($C13)-2),"") -> 45956 | E13: a_plus_h | F13: =IF(AND(G13<>"",G13<>0),1,0) -> 1 | G13: 600031.SH | H13: 工业(HS)-工业工程(HS)-重型机械(HS) | I13: 21.3 | J13: 20.3 | K13: 21.3 | L13: 15349086720 | M13: 13.96 | N13: 52.93 | O13: =IF(IFERROR(N13*1,0)>=15,1,0) -> 1 | P13: 18.824 | Q13: 中信里昂证券有限公司,中国国际金融香港证券有限公司,中银国际亚洲有限公司,招商证券(香港)有限公司,农银国际证券有限公司,工银国际证券有限公司,农银国际融资有限公司 | R13: =IF(Q13="",0,LEN(Q13)-LEN(SUBSTITUTE(Q13,",",""))+1) -> 7 | U13: 30.058394 | V13: =IFERROR((SUMIFS($U$3:$U$392,$H$3:$H$392,$H13,$U$3:$U$392,">0")-IF(IFERROR($U13,0)>0,$U13,0))/(COUNTIFS($H$3:$H$392,$H13,$U$3:$U$392,">0")-IF(IFERROR($U13,0)>0,1,0)),"") -> 19.366735 | X13: 6 | Y13: =[1]!wss(AB13,"sec_status","cols=1;rows=1") -> L | AB13: =IF(LEFT(A13,1)="0",MID(A13,2,99),A13) -> 6031.HK | AC13: 21.9 | AD13: 21.3 | AE13: 22.3 | AF13: 21.3 | AG13: 主板 | AH13: H股 | AI13: 主板 | AJ13: 0
A14: 1880.HK | B14: 中国中免 | C14: 44798 | D14: =IFERROR(IF(ISNUMBER($C14),$C14-2,DATEVALUE($C14)-2),"") -> 44796 | E14: a_plus_h | F14: =IF(AND(G14<>"",G14<>0),1,0) -> 1 | G14: 601888.SH | H14: 非必需性消费(HS)-旅游及消闲设施(HS)-旅游及观光(HS) | I14: 158 | J14: 143.5 | K14: 165.5 | L14: 18388593000 | M14: 4.7 | N14: 1.06 | O14: =IF(IFERROR(N14*1,0)>=15,1,0) -> 0 | P14: 21.198 | Q14: 中国国际金融香港证券有限公司,UBS AG Hong Kong Branch,建银国际金融有限公司,中信里昂证券有限公司,海通国际证券有限公司,农银国际证券有限公司,中银国际亚洲有限公司,交银国际证券有限公司,招银国际融资有限公司,中信建投(国际)融资有限公司,星展亚洲融资有限公司,国泰君安证券(香港)有限公司,工银国际证券有限公司,中国银河国际证券(香港)有限公司,东吴证券国际经纪有限公司 | R14: =IF(Q14="",0,LEN(Q14)-LEN(SUBSTITUTE(Q14,",",""))+1) -> 15 | U14: 27.296115 | V14: =IFERROR((SUMIFS($U$3:$U$392,$H$3:$H$392,$H14,$U$3:$U$392,">0")-IF(IFERROR($U14,0)>0,$U14,0))/(COUNTIFS($H$3:$H$392,$H14,$U$3:$U$392,">0")-IF(IFERROR($U14,0)>0,1,0)),"") | X14: 6 | Y14: =[1]!wss(AB14,"sec_status","cols=1;rows=1") -> L | AB14: =IF(LEFT(A14,1)="0",MID(A14,2,99),A14) -> 1880.HK | AC14: 158 | AD14: 120 | AE14: 159.3 | AF14: 120 | AG14: 主板 | AH14: H股 | AI14: 主板 | AJ14: 0
A15: 1519.HK | B15: 极兔速递-W | C15: 45226 | D15: =IFERROR(IF(ISNUMBER($C15),$C15-2,DATEVALUE($C15)-2),"") -> 45224 | E15: 18a | F15: =IF(AND(G15<>"",G15<>0),1,0) -> 0 | H15: 工业(HS)-工用运输(HS)-航空货运及物流(HS) | I15: 12 | J15: 12 | K15: 12 | L15: 3918604800 | M15: 1.91 | N15: 1.36 | O15: =IF(IFERROR(N15*1,0)>=15,1,0) -> 0 | P15: 0 | Q15: 国泰君安证券(香港)有限公司,星展亚洲融资有限公司,中国银河国际证券(香港)有限公司,富途证券国际(香港)有限公司,老虎证券(香港)环球有限公司,华盛资本证券有限公司,富明证券有限公司,复星国际证券有限公司,摩根士丹利亚洲有限公司,Merrill Lynch (Asia Pacific) Limited,中国国际金融香港证券有限公司,UBS AG Hong Kong Branch,建银国际金融有限公司,招银国际融资有限公司,华泰金融控股(香港)有限公司,中银国际亚洲有限公司,农银国际证券有限公司,交银国际证券有限公司,工银国际证券有限公司,德意志银行香港分行,大和资本市场香港有限公司 | R15: =IF(Q15="",0,LEN(Q15)-LEN(SUBSTITUTE(Q15,",",""))+1) -> 21 | U15: 8.1892873 | V15: =IFERROR((SUMIFS($U$3:$U$392,$H$3:$H$392,$H15,$U$3:$U$392,">0")-IF(IFERROR($U15,0)>0,$U15,0))/(COUNTIFS($H$3:$H$392,$H15,$U$3:$U$392,">0")-IF(IFERROR($U15,0)>0,1,0)),"") -> 21.579526 | X15: 6 | Y15: =[1]!wss(AB15,"sec_status","cols=1;rows=1") -> L | AB15: =IF(LEFT(A15,1)="0",MID(A15,2,99),A15) -> 1519.HK | AC15: 12 | AD15: 12 | AE15: 12.2 | AF15: 11.8 | AG15: 主板 | AI15: 主板 | AJ15: 0
A16: 0699.HK | B16: 均胜电子 | C16: 45967 | D16: =IFERROR(IF(ISNUMBER($C16),$C16-2,DATEVALUE($C16)-2),"") -> 45965 | E16: a_plus_h | F16: =IF(AND(G16<>"",G16<>0),1,0) -> 1 | G16: 600699.SH | H16: 非必需性消费(HS)-汽车(HS)-汽车零件(HS) | I16: 22 | K16: 23.6 | L16: 3412200000 | M16: 9.78 | N16: 147.67 | O16: =IF(IFERROR(N16*1,0)>=15,1,0) -> 1 | P16: 0 | Q16: 中国国际金融香港证券有限公司,UBS AG Hong Kong Branch,广发证券(香港)经纪有限公司,农银国际证券有限公司,华兴证券(香港)有限公司,招银国际融资有限公司,UBS Securities Hong Kong Limited,农银国际融资有限公司 | R16: =IF(Q16="",0,LEN(Q16)-LEN(SUBSTITUTE(Q16,",",""))+1) -> 8 | U16: 32.893961 | V16: =IFERROR((SUMIFS($U$3:$U$392,$H$3:$H$392,$H16,$U$3:$U$392,">0")-IF(IFERROR($U16,0)>0,$U16,0))/(COUNTIFS($H$3:$H$392,$H16,$U$3:$U$392,">0")-IF(IFERROR($U16,0)>0,1,0)),"") -> 10.854154 | X16: 6 | Y16: =[1]!wss(AB16,"sec_status","cols=1;rows=1") | AB16: =IF(LEFT(A16,1)="0",MID(A16,2,99),A16) -> 699.HK | AC16: 20.24 | AD16: 21.5 | AE16: 21.5 | AF16: 19.85 | AG16: 主板 | AH16: H股 | AI16: 主板 | AJ16: 0
A17: 9866.HK | B17: 蔚来-SW | C17: 44630 | D17: =IFERROR(IF(ISNUMBER($C17),$C17-2,DATEVALUE($C17)-2),"") -> 44628 | E17: secondary | F17: =IF(AND(G17<>"",G17<>0),1,0) -> 0 | H17: 非必需性消费(HS)-汽车(HS)-汽车Ⅲ(HS) | L17: 0 | M17: 0 | N17: 0 | O17: =IF(IFERROR(N17*1,0)>=15,1,0) -> 0 | P17: 0 | Q17: 0 | R17: =IF(Q17="",0,LEN(Q17)-LEN(SUBSTITUTE(Q17,",",""))+1) -> 1 | U17: 0 | V17: =IFERROR((SUMIFS($U$3:$U$392,$H$3:$H$392,$H17,$U$3:$U$392,">0")-IF(IFERROR($U17,0)>0,$U17,0))/(COUNTIFS($H$3:$H$392,$H17,$U$3:$U$392,">0")-IF(IFERROR($U17,0)>0,1,0)),"") -> 16.882618 | Y17: =[1]!wss(AB17,"sec_status","cols=1;rows=1") -> L | AB17: =IF(LEFT(A17,1)="0",MID(A17,2,99),A17) -> 9866.HK | AC17: 158.9 | AD17: 160 | AE17: 169.5 | AF17: 158.8 | AG17: 主板 | AI17: 主板 | AJ17: 0
A18: 6613.HK | B18: 蓝思科技 | C18: 45847 | D18: =IFERROR(IF(ISNUMBER($C18),$C18-2,DATEVALUE($C18)-2),"") -> 45845 | E18: a_plus_h | F18: =IF(AND(G18<>"",G18<>0),1,0) -> 1 | G18: 300433.SZ | H18: 工业(HS)-工业工程(HS)-电子零件(HS) | I18: 18.18 | J18: 17.38 | K18: 18.18 | L18: 5483000736 | M18: 16.68 | N18: 462.76 | O18: =IF(IFERROR(N18*1,0)>=15,1,0) -> 1 | P18: 7.108 | Q18: 中信里昂证券有限公司,Merrill Lynch (Asia Pacific) Limited,农银国际证券有限公司,中银国际亚洲有限公司,富途证券国际(香港)有限公司,中航资信环球资产管理有限公司,农银国际融资有限公司 | R18: =IF(Q18="",0,LEN(Q18)-LEN(SUBSTITUTE(Q18,",",""))+1) -> 7 | U18: 24.366614 | V18: =IFERROR((SUMIFS($U$3:$U$392,$H$3:$H$392,$H18,$U$3:$U$392,">0")-IF(IFERROR($U18,0)>0,$U18,0))/(COUNTIFS($H$3:$H$392,$H18,$U$3:$U$392,">0")-IF(IFERROR($U18,0)>0,1,0)),"") -> 35.876825 | X18: 6 | Y18: =[1]!wss(AB18,"sec_status","cols=1;rows=1") -> L | AB18: =IF(LEFT(A18,1)="0",MID(A18,2,99),A18) -> 6613.HK | AC18: 19.84 | AD18: 18.88 | AE18: 19.98 | AF18: 18.54 | AG18: 主板 | AH18: H股 | AI18: 主板 | AJ18: 0
A19: 9696.HK | B19: 天齐锂业 | C19: 44755 | D19: =IFERROR(IF(ISNUMBER($C19),$C19-2,DATEVALUE($C19)-2),"") -> 44753 | E19: a_plus_h | F19: =IF(AND(G19<>"",G19<>0),1,0) -> 1 | G19: 002466.SZ | H19: 原材料业(HS)-一般金属及矿石(HS)-其他金属及矿物(HS) | I19: 82 | J19: 69 | K19: 82 | L19: 13458020400 | M19: 5.2 | N19: 9.3 | O19: =IF(IFERROR(N19*1,0)>=15,1,0) -> 0 | P19: 0 | Q19: 摩根士丹利亚洲有限公司,中国国际金融香港证券有限公司,招银国际融资有限公司,法国巴黎证券(亚洲)有限公司,瑞士信贷(香港)有限公司,Banco BTG Pactual S.A.-Cayman Branch,中国银河国际证券(香港)有限公司,富途证券国际(香港)有限公司,华泰金融控股(香港)有限公司 | R19: =IF(Q19="",0,LEN(Q19)-LEN(SUBSTITUTE(Q19,",",""))+1) -> 9 | U19: 30.152691 | V19: =IFERROR((SUMIFS($U$3:$U$392,$H$3:$H$392,$H19,$U$3:$U$392,">0")-IF(IFERROR($U19,0)>0,$U19,0))/(COUNTIFS($H$3:$H$392,$H19,$U$3:$U$392,">0")-IF(IFERROR($U19,0)>0,1,0)),"") -> 34.494409 | X19: 6 | Y19: =[1]!wss(AB19,"sec_status","cols=1;rows=1") -> L | AB19: =IF(LEFT(A19,1)="0",MID(A19,2,99),A19) -> 9696.HK | AC19: 82 | AD19: 74.5 | AE19: 82 | AF19: 72.65 | AG19: 主板 | AH19: H股 | AI19: 主板 | AJ19: 0
A20: 9927.HK | B20: 赛力斯 | C20: 45966 | D20: =IFERROR(IF(ISNUMBER($C20),$C20-2,DATEVALUE($C20)-2),"") -> 45964 | E20: a_plus_h | F20: =IF(AND(G20<>"",G20<>0),1,0) -> 1 | G20: 601127.SH | H20: 非必需性消费(HS)-汽车(HS)-汽车Ⅲ(HS) | I20: 131.5 | K20: 131.5 | L20: 14283398500 | M20: 8.61 | N20: 132.68 | O20: =IF(IFERROR(N20*1,0)>=15,1,0) -> 1 | P20: 0 | Q20: 中国国际金融香港证券有限公司,中国银河国际证券(香港)有限公司,华泰金融控股(香港)有限公司 | R20: =IF(Q20="",0,LEN(Q20)-LEN(SUBSTITUTE(Q20,",",""))+1) -> 3 | U20: 35.676237 | V20: =IFERROR((SUMIFS($U$3:$U$392,$H$3:$H$392,$H20,$U$3:$U$392,">0")-IF(IFERROR($U20,0)>0,$U20,0))/(COUNTIFS($H$3:$H$392,$H20,$U$3:$U$392,">0")-IF(IFERROR($U20,0)>0,1,0)),"") -> 10.618078 | X20: 6 | Y20: =[1]!wss(AB20,"sec_status","cols=1;rows=1") -> L | AB20: =IF(LEFT(A20,1)="0",MID(A20,2,99),A20) -> 9927.HK | AC20: 131.5 | AD20: 128.9 | AE20: 131.5 | AF20: 118 | AG20: 主板 | AH20: H股 | AI20: 主板 | AJ20: 0
A21: 2579.HK | B21: 中伟新材 | C21: 45978 | D21: =IFERROR(IF(ISNUMBER($C21),$C21-2,DATEVALUE($C21)-2),"") -> 45976 | E21: a_plus_h | F21: =IF(AND(G21<>"",G21<>0),1,0) -> 1 | G21: 300919.SZ | H21: 原材料业(HS)-原材料(HS)-特殊化工用品(HS) | I21: 34 | J21: 34 | K21: 37.8 | L21: 3543663600 | M21: 4.08 | N21: 27.9 | O21: =IF(IFERROR(N21*1,0)>=15,1,0) -> 1 | P21: 0 | Q21: 摩根士丹利亚洲有限公司,华泰金融控股(香港)有限公司,中国国际金融香港证券有限公司,法国巴黎证券(亚洲)有限公司,农银国际融资有限公司,农银国际证券有限公司,中银国际亚洲有限公司,工银国际证券有限公司,建银国际金融有限公司,瑞穗证券亚洲有限公司,老虎证券(香港)环球有限公司,第一上海证券有限公司 | R21: =IF(Q21="",0,LEN(Q21)-LEN(SUBSTITUTE(Q21,",",""))+1) -> 12 | U21: 22.365868 | V21: =IFERROR((SUMIFS($U$3:$U$392,$H$3:$H$392,$H21,$U$3:$U$392,">0")-IF(IFERROR($U21,0)>0,$U21,0))/(COUNTIFS($H$3:$H$392,$H21,$U$3:$U$392,">0")-IF(IFERROR($U21,0)>0,1,0)),"") -> 10.481443 | X21: 6 | Y21: =[1]!wss(AB21,"sec_status","cols=1;rows=1") -> L | AB21: =IF(LEFT(A21,1)="0",MID(A21,2,99),A21) -> 2579.HK | AC21: 33.96 | AD21: 34 | AE21: 34 | AF21: 32 | AG21: 主板 | AH21: H股 | AI21: 主板 | AJ21: 0
A22: 6655.HK | B22: 华新建材 | C22: 44648 | D22: =IFERROR(IF(ISNUMBER($C22),$C22-2,DATEVALUE($C22)-2),"") -> 44646 | E22: a_plus_h | F22: =IF(AND(G22<>"",G22<>0),1,0) -> 1 | G22: 600801.SH | H22: 地产建筑业(HS)-建筑(HS)-建筑材料(HS) | L22: 0 | M22: 0 | N22: 0 | O22: =IF(IFERROR(N22*1,0)>=15,1,0) -> 0 | P22: 0 | Q22: 0 | R22: =IF(Q22="",0,LEN(Q22)-LEN(SUBSTITUTE(Q22,",",""))+1) -> 1 | U22: 0 | V22: =IFERROR((SUMIFS($U$3:$U$392,$H$3:$H$392,$H22,$U$3:$U$392,">0")-IF(IFERROR($U22,0)>0,$U22,0))/(COUNTIFS($H$3:$H$392,$H22,$U$3:$U$392,">0")-IF(IFERROR($U22,0)>0,1,0)),"") -> 10.989343 | Y22: =[1]!wss(AB22,"sec_status","cols=1;rows=1") -> L | AB22: =IF(LEFT(A22,1)="0",MID(A22,2,99),A22) -> 6655.HK | AC22: 13.8 | AD22: 14.74 | AE22: 14.74 | AF22: 11.2 | AG22: 主板 | AH22: H股 | AI22: 主板 | AJ22: 0
A23: 2602.HK | B23: 万物云 | C23: 44833 | D23: =IFERROR(IF(ISNUMBER($C23),$C23-2,DATEVALUE($C23)-2),"") -> 44831 | E23: main_board_profitable | F23: =IF(AND(G23<>"",G23<>0),1,0) -> 0 | H23: 地产建筑业(HS)-地产(HS)-物业服务及管理(HS) | I23: 49.35 | J23: 47.1 | K23: 52.7 | L23: 6319203345 | M23: 3.3 | N23: 0.82 | O23: =IF(IFERROR(N23*1,0)>=15,1,0) -> 0 | P23: 5.551 | Q23: 高盛(亚洲)有限责任公司,招银国际融资有限公司,中银国际亚洲有限公司,建银国际金融有限公司,国信证券(香港)融资有限公司,工银国际证券有限公司,农银国际证券有限公司,中信里昂证券有限公司,花旗环球金融亚洲有限公司,Citigroup Global Markets Limited,工银国际融资有限公司 | R23: =IF(Q23="",0,LEN(Q23)-LEN(SUBSTITUTE(Q23,",",""))+1) -> 11 | U23: 28.23878 | V23: =IFERROR((SUMIFS($U$3:$U$392,$H$3:$H$392,$H23,$U$3:$U$392,">0")-IF(IFERROR($U23,0)>0,$U23,0))/(COUNTIFS($H$3:$H$392,$H23,$U$3:$U$392,">0")-IF(IFERROR($U23,0)>0,1,0)),"") -> 18.089727 | X23: 6 | Y23: =[1]!wss(AB23,"sec_status","cols=1;rows=1") -> L | AB23: =IF(LEFT(A23,1)="0",MID(A23,2,99),A23) -> 2602.HK | AC23: 46 | AD23: 45.6 | AE23: 47.45 | AF23: 42.05 | AG23: 主板 | AH23: H股 | AI23: 主板 | AJ23: 0
A24: 1698.HK | B24: 腾讯音乐-SW | C24: 44825 | D24: =IFERROR(IF(ISNUMBER($C24),$C24-2,DATEVALUE($C24)-2),"") -> 44823 | E24: secondary | F24: =IF(AND(G24<>"",G24<>0),1,0) -> 0 | H24: 非必需性消费(HS)-媒体及娱乐(HS)-影视娱乐(HS) | L24: 0 | M24: 0 | N24: 0 | O24: =IF(IFERROR(N24*1,0)>=15,1,0) -> 0 | P24: 0 | Q24: 0 | R24: =IF(Q24="",0,LEN(Q24)-LEN(SUBSTITUTE(Q24,",",""))+1) -> 1 | U24: 0 | V24: =IFERROR((SUMIFS($U$3:$U$392,$H$3:$H$392,$H24,$U$3:$U$392,">0")-IF(IFERROR($U24,0)>0,$U24,0))/(COUNTIFS($H$3:$H$392,$H24,$U$3:$U$392,">0")-IF(IFERROR($U24,0)>0,1,0)),"") -> 71.440653 | Y24: =[1]!wss(AB24,"sec_status","cols=1;rows=1") -> L | AB24: =IF(LEFT(A24,1)="0",MID(A24,2,99),A24) -> 1698.HK | AC24: 18.22 | AD24: 18 | AE24: 18.3 | AF24: 18 | AG24: 主板 | AI24: 主板 | AJ24: 0
A25: 9611.HK | B25: 龙旗科技 | C25: 46044 | D25: =IFERROR(IF(ISNUMBER($C25),$C25-2,DATEVALUE($C25)-2),"") -> 46042 | E25: a_plus_h | F25: =IF(AND(G25<>"",G25<>0),1,0) -> 1 | G25: 603341.SH | H25: 资讯科技业(HS)-资讯科技器材(HS)-消费性电讯设备(HS) | I25: 31 | K25: 31 | L25: 1620032100 | M25: 9.02 | N25: 1149.76 | O25: =IF(IFERROR(N25*1,0)>=15,1,0) -> 1 | P25: 0 | Q25: 花旗环球金融亚洲有限公司,Citigroup Global Markets Limited,海通国际证券有限公司,国泰君安证券(香港)有限公司,华泰金融控股(香港)有限公司,农银国际证券有限公司,富途证券国际(香港)有限公司,老虎证券(香港)环球有限公司,农银国际融资有限公司 | R25: =IF(Q25="",0,LEN(Q25)-LEN(SUBSTITUTE(Q25,",",""))+1) -> 9 | U25: 29.936494 | V25: =IFERROR((SUMIFS($U$3:$U$392,$H$3:$H$392,$H25,$U$3:$U$392,">0")-IF(IFERROR($U25,0)>0,$U25,0))/(COUNTIFS($H$3:$H$392,$H25,$U$3:$U$392,">0")-IF(IFERROR($U25,0)>0,1,0)),"") -> 39.003856 | X25: 6 | Y25: =[1]!wss(AB25,"sec_status","cols=1;rows=1") -> L | AB25: =IF(LEFT(A25,1)="0",MID(A25,2,99),A25) -> 9611.HK | AC25: 32.1 | AD25: 35 | AE25: 36.86 | AF25: 31.22 | AG25: 主板 | AH25: H股 | AI25: 主板 | AJ25: 0
A26: 3931.HK | B26: 中创新航 | C26: 44840 | D26: =IFERROR(IF(ISNUMBER($C26),$C26-2,DATEVALUE($C26)-2),"") -> 44838 | E26: main_board_profitable | F26: =IF(AND(G26<>"",G26<>0),1,0) -> 0 | H26: 工业(HS)-工业工程(HS)-能源储存装置(HS) | I26: 38 | J26: 38 | K26: 51 | L26: 10102121400 | M26: 2.11 | N26: 0.21 | O26: =IF(IFERROR(N26*1,0)>=15,1,0) -> 0 | P26: 0 | Q26: 华泰金融控股(香港)有限公司,J.P. Morgan Securities (Asia Pacific) Limited,J.P. Morgan Securities plc,花旗环球金融亚洲有限公司,Citigroup Global Markets Limited,瑞士信贷(香港)有限公司 | R26: =IF(Q26="",0,LEN(Q26)-LEN(SUBSTITUTE(Q26,",",""))+1) -> 6 | U26: 393.22777 | V26: =IFERROR((SUMIFS($U$3:$U$392,$H$3:$H$392,$H26,$U$3:$U$392,">0")-IF(IFERROR($U26,0)>0,$U26,0))/(COUNTIFS($H$3:$H$392,$H26,$U$3:$U$392,">0")-IF(IFERROR($U26,0)>0,1,0)),"") -> 93.380932 | X26: 6 | Y26: =[1]!wss(AB26,"sec_status","cols=1;rows=1") -> L | AB26: =IF(LEFT(A26,1)="0",MID(A26,2,99),A26) -> 3931.HK | AC26: 38 | AD26: 38 | AE26: 38.45 | AF26: 37.15 | AG26: 主板 | AH26: H股 | AI26: 主板 | AJ26: 0
A27: 2580.HK | B27: 奥克斯电气 | C27: 45902 | D27: =IFERROR(IF(ISNUMBER($C27),$C27-2,DATEVALUE($C27)-2),"") -> 45900 | E27: main_board_profitable | F27: =IF(AND(G27<>"",G27<>0),1,0) -> 0 | H27: 非必需性消费(HS)-家庭电器及用品(HS)-家庭电器(HS) | I27: 17.42 | J27: 16 | K27: 17.42 | L27: 4150057184 | M27: 8.3 | N27: 557.2 | O27: =IF(IFERROR(N27*1,0)>=15,1,0) -> 1 | P27: 0 | Q27: 中国国际金融香港证券有限公司,东方证券(香港)有限公司,农银国际证券有限公司,工银国际证券有限公司,富途证券国际(香港)有限公司,农银国际融资有限公司 | R27: =IF(Q27="",0,LEN(Q27)-LEN(SUBSTITUTE(Q27,",",""))+1) -> 6 | U27: 8.8038818 | V27: =IFERROR((SUMIFS($U$3:$U$392,$H$3:$H$392,$H27,$U$3:$U$392,">0")-IF(IFERROR($U27,0)>0,$U27,0))/(COUNTIFS($H$3:$H$392,$H27,$U$3:$U$392,">0")-IF(IFERROR($U27,0)>0,1,0)),"") -> 8.1404968 | X27: 6 | Y27: =[1]!wss(AB27,"sec_status","cols=1;rows=1") -> L | AB27: =IF(LEFT(A27,1)="0",MID(A27,2,99),A27) -> 2580.HK | AC27: 16.48 | AD27: 16.1 | AE27: 16.79 | AF27: 15.68 | AG27: 主板 | AI27: 主板 | AJ27: 0
A28: 3288.HK | B28: 海天味业 | C28: 45827 | D28: =IFERROR(IF(ISNUMBER($C28),$C28-2,DATEVALUE($C28)-2),"") -> 45825 | E28: a_plus_h | F28: =IF(AND(G28<>"",G28<>0),1,0) -> 1 | G28: 603288.SH | H28: 必需性消费(HS)-食物饮品(HS)-食品添加剂(HS) | I28: 36.3 | J28: 35 | K28: 36.3 | L28: 10571445720 | M28: 22.93 | N28: 918.15 | O28: =IF(IFERROR(N28*1,0)>=15,1,0) -> 1 | P28: 4.3686 | Q28: 中国国际金融香港证券有限公司,高盛(亚洲)有限责任公司,摩根士丹利亚洲有限公司,中银国际亚洲有限公司,工银国际证券有限公司,交银国际证券有限公司,招银国际融资有限公司,农银国际融资有限公司,农银国际证券有限公司,建银国际金融有限公司,香港上海汇丰银行有限公司,华泰金融控股(香港)有限公司,中信里昂证券有限公司,富途证券国际(香港)有限公司,广发证券(香港)经纪有限公司,中国银河国际证券(香港)有限公司 | R28: =IF(Q28="",0,LEN(Q28)-LEN(SUBSTITUTE(Q28,",",""))+1) -> 16 | U28: 30.94212 | V28: =IFERROR((SUMIFS($U$3:$U$392,$H$3:$H$392,$H28,$U$3:$U$392,">0")-IF(IFERROR($U28,0)>0,$U28,0))/(COUNTIFS($H$3:$H$392,$H28,$U$3:$U$392,">0")-IF(IFERROR($U28,0)>0,1,0)),"") -> 38.802333 | X28: 6 | Y28: =[1]!wss(AB28,"sec_status","cols=1;rows=1") -> L | AB28: =IF(LEFT(A28,1)="0",MID(A28,2,99),A28) -> 3288.HK | AC28: 36.5 | AD28: 37.5 | AE28: 38 | AF28: 36.05 | AG28: 主板 | AH28: H股 | AI28: 主板 | AJ28: 0
A29: 2050.HK | B29: 三花智控 | C29: 45831 | D29: =IFERROR(IF(ISNUMBER($C29),$C29-2,DATEVALUE($C29)-2),"") -> 45829 | E29: a_plus_h | F29: =IF(AND(G29<>"",G29<>0),1,0) -> 1 | G29: 002050.SZ | H29: 工业(HS)-工业工程(HS)-工业零件及器材(HS) | I29: 22.53 | J29: 21.21 | K29: 22.53 | L29: 10736365092 | M29: 23.57 | N29: 747.92 | O29: =IF(IFERROR(N29*1,0)>=15,1,0) -> 1 | P29: 13.9 | Q29: 中国国际金融香港证券有限公司,华泰金融控股(香港)有限公司,农银国际证券有限公司,中银国际亚洲有限公司,财通国际证券有限公司,广发证券(香港)经纪有限公司,浙商国际金融控股有限公司 | R29: =IF(Q29="",0,LEN(Q29)-LEN(SUBSTITUTE(Q29,",",""))+1) -> 7 | U29: 27.916186 | V29: =IFERROR((SUMIFS($U$3:$U$392,$H$3:$H$392,$H29,$U$3:$U$392,">0")-IF(IFERROR($U29,0)>0,$U29,0))/(COUNTIFS($H$3:$H$392,$H29,$U$3:$U$392,">0")-IF(IFERROR($U29,0)>0,1,0)),"") -> 88.140923 | X29: 6 | Y29: =[1]!wss(AB29,"sec_status","cols=1;rows=1") -> L | AB29: =IF(LEFT(A29,1)="0",MID(A29,2,99),A29) -> 2050.HK | AC29: 22.5 | AD29: 20.95 | AE29: 22.55 | AF29: 20.7 | AG29: 主板 | AH29: H股 | AI29: 主板 | AJ29: 0
A30: 1276.HK | B30: 恒瑞医药 | C30: 45800 | D30: =IFERROR(IF(ISNUMBER($C30),$C30-2,DATEVALUE($C30)-2),"") -> 45798 | E30: a_plus_h | F30: =IF(AND(G30<>"",G30<>0),1,0) -> 1 | G30: 600276.SH | H30: 医疗保健业(HS)-药品及生物科技(HS)-药品(HS) | I30: 44.05 | J30: 41.45 | K30: 44.05 | L30: 11373604280 | M30: 17.09 | N30: 454.85 | O30: =IF(IFERROR(N30*1,0)>=15,1,0) -> 1 | P30: 14.715 | Q30: 摩根士丹利亚洲有限公司,花旗环球金融亚洲有限公司,Citigroup Global Markets Limited,华泰金融控股(香港)有限公司,UBS AG Hong Kong Branch,中银国际亚洲有限公司,中信里昂证券有限公司,广发证券(香港)经纪有限公司 | R30: =IF(Q30="",0,LEN(Q30)-LEN(SUBSTITUTE(Q30,",",""))+1) -> 8 | U30: 42.510871 | V30: =IFERROR((SUMIFS($U$3:$U$392,$H$3:$H$392,$H30,$U$3:$U$392,">0")-IF(IFERROR($U30,0)>0,$U30,0))/(COUNTIFS($H$3:$H$392,$H30,$U$3:$U$392,">0")-IF(IFERROR($U30,0)>0,1,0)),"") -> 101.02218 | X30: 6 | Y30: =[1]!wss(AB30,"sec_status","cols=1;rows=1") -> L | AB30: =IF(LEFT(A30,1)="0",MID(A30,2,99),A30) -> 1276.HK | AC30: 55.15 | AD30: 57 | AE30: 60.5 | AF30: 55.15 | AG30: 主板 | AH30: H股 | AI30: 主板 | AJ30: 0
A31: 6623.HK | B31: 陆控 | C31: 45030 | D31: =IFERROR(IF(ISNUMBER($C31),$C31-2,DATEVALUE($C31)-2),"") -> 45028 | E31: main_board_profitable | F31: =IF(AND(G31<>"",G31<>0),1,0) -> 0 | H31: 金融业(HS)-其他金融(HS)-信贷(HS) | L31: 0 | M31: 0 | N31: 0 | O31: =IF(IFERROR(N31*1,0)>=15,1,0) -> 0 | P31: 0 | Q31: 0 | R31: =IF(Q31="",0,LEN(Q31)-LEN(SUBSTITUTE(Q31,",",""))+1) -> 1 | U31: 0 | V31: =IFERROR((SUMIFS($U$3:$U$392,$H$3:$H$392,$H31,$U$3:$U$392,">0")-IF(IFERROR($U31,0)>0,$U31,0))/(COUNTIFS($H$3:$H$392,$H31,$U$3:$U$392,">0")-IF(IFERROR($U31,0)>0,1,0)),"") -> 7.7662206 | Y31: =[1]!wss(AB31,"sec_status","cols=1;rows=1") -> L | AB31: =IF(LEFT(A31,1)="0",MID(A31,2,99),A31) -> 6623.HK | AC31: 34.75 | AD31: 33.5 | AE31: 36.5 | AF31: 33.4 | AG31: 主板 | AI31: 主板 | AJ31: 0
A32: 2245.HK | B32: 力勤资源 | C32: 44896 | D32: =IFERROR(IF(ISNUMBER($C32),$C32-2,DATEVALUE($C32)-2),"") -> 44894 | E32: main_board_profitable | F32: =IF(AND(G32<>"",G32<>0),1,0) -> 0 | H32: 原材料业(HS)-一般金属及矿石(HS)-其他金属及矿物(HS) | I32: 15.8 | J32: 15.6 | K32: 19.96 | L32: 3762969080 | M32: 1.4 | N32: 1.47 | O32: =IF(IFERROR(N32*1,0)>=15,1,0) -> 0 | P32: 0.853 | Q32: 中国国际金融香港证券有限公司,招银国际融资有限公司,中银国际亚洲有限公司,星展亚洲融资有限公司,农银国际证券有限公司,法国巴黎证券(亚洲)有限公司,元库证券有限公司,中国国际金融香港证券有限公司(香港) | R32: =IF(Q32="",0,LEN(Q32)-LEN(SUBSTITUTE(Q32,",",""))+1) -> 8 | U32: 18.214611 | V32: =IFERROR((SUMIFS($U$3:$U$392,$H$3:$H$392,$H32,$U$3:$U$392,">0")-IF(IFERROR($U32,0)>0,$U32,0))/(COUNTIFS($H$3:$H$392,$H32,$U$3:$U$392,">0")-IF(IFERROR($U32,0)>0,1,0)),"") -> 36.882025 | X32: 6 | Y32: =[1]!wss(AB32,"sec_status","cols=1;rows=1") -> L | AB32: =IF(LEFT(A32,1)="0",MID(A32,2,99),A32) -> 2245.HK | AC32: 15.8 | AD32: 15.8 | AE32: 16.02 | AF32: 15.8 | AG32: 主板 | AH32: H股 | AI32: 主板 | AJ32: 0
A33: 0501.HK | B33: 豪威集团 | C33: 46034 | D33: =IFERROR(IF(ISNUMBER($C33),$C33-2,DATEVALUE($C33)-2),"") -> 46032 | E33: a_plus_h | F33: =IF(AND(G33<>"",G33<>0),1,0) -> 1 | G33: 603501.SH | H33: 资讯科技业(HS)-半导体(HS)-半导体Ⅲ(HS) | I33: 104.8 | K33: 104.8 | L33: 5317667280 | M33: 9.73 | N33: 9.28 | O33: =IF(IFERROR(N33*1,0)>=15,1,0) -> 0 | P33: 5.112 | Q33: UBS AG Hong Kong Branch,中国国际金融香港证券有限公司,平安证券(香港)有限公司,广发证券(香港)经纪有限公司,海通国际证券有限公司,中信里昂证券有限公司,淘金者证券(香港)有限公司 | R33: =IF(Q33="",0,LEN(Q33)-LEN(SUBSTITUTE(Q33,",",""))+1) -> 7 | U33: 36.733359 | V33: =IFERROR((SUMIFS($U$3:$U$392,$H$3:$H$392,$H33,$U$3:$U$392,">0")-IF(IFERROR($U33,0)>0,$U33,0))/(COUNTIFS($H$3:$H$392,$H33,$U$3:$U$392,">0")-IF(IFERROR($U33,0)>0,1,0)),"") -> 62.754445 | X33: 6 | Y33: =[1]!wss(AB33,"sec_status","cols=1;rows=1") | AB33: =IF(LEFT(A33,1)="0",MID(A33,2,99),A33) -> 501.HK | AC33: 121.8 | AD33: 108 | AE33: 121.8 | AF33: 108 | AG33: 主板 | AH33: H股 | AI33: 主板 | AJ33: 0
A34: 2097.HK | B34: 蜜雪集团 | C34: 45719 | D34: =IFERROR(IF(ISNUMBER($C34),$C34-2,DATEVALUE($C34)-2),"") -> 45717 | E34: main_board_profitable | F34: =IF(AND(G34<>"",G34<>0),1,0) -> 0 | H34: 必需性消费(HS)-食物饮品(HS)-非酒精饮料(HS) | I34: 202.5 | J34: 202.5 | K34: 202.5 | L34: 3972807000 | M34: 35.23 | N34: 5258.21 | O34: =IF(IFERROR(N34*1,0)>=15,1,0) -> 1 | P34: 5.0776966 | Q34: 招银国际融资有限公司,广发证券(香港)经纪有限公司,工银国际证券有限公司,华泰金融控股(香港)有限公司,中国国际金融香港证券有限公司,UBS AG Hong Kong Branch,高盛(亚洲)有限责任公司,Merrill Lynch (Asia Pacific) Limited | R34: =IF(Q34="",0,LEN(Q34)-LEN(SUBSTITUTE(Q34,",",""))+1) -> 8 | U34: 22.055012 | V34: =IFERROR((SUMIFS($U$3:$U$392,$H$3:$H$392,$H34,$U$3:$U$392,">0")-IF(IFERROR($U34,0)>0,$U34,0))/(COUNTIFS($H$3:$H$392,$H34,$U$3:$U$392,">0")-IF(IFERROR($U34,0)>0,1,0)),"") -> 27.018666 | X34: 6 | Y34: =[1]!wss(AB34,"sec_status","cols=1;rows=1") -> L | AB34: =IF(LEFT(A34,1)="0",MID(A34,2,99),A34) -> 2097.HK | AC34: 290 | AD34: 262 | AE34: 298 | AF34: 256 | AG34: 主板 | AH34: H股 | AI34: 主板 | AJ34: 0
A35: 2585.HK | B35: 梦金园 | C35: 45625 | D35: =IFERROR(IF(ISNUMBER($C35),$C35-2,DATEVALUE($C35)-2),"") -> 45623 | E35: main_board_profitable | F35: =IF(AND(G35<>"",G35<>0),1,0) -> 0 | H35: 非必需性消费(HS)-专业零售(HS)-其他零售商(HS) | I35: 12 | J35: 12 | K35: 14.4 | L35: 527481600 | M35: 0.98 | N35: 20.58 | O35: =IF(IFERROR(N35*1,0)>=15,1,0) -> 1 | P35: 0 | Q35: 农银国际证券有限公司,中国光大证券(香港)有限公司,富途证券国际(香港)有限公司,工银国际证券有限公司,TradeGo Markets Limited,中信里昂证券有限公司 | R35: =IF(Q35="",0,LEN(Q35)-LEN(SUBSTITUTE(Q35,",",""))+1) -> 6 | U35: 12.887822 | V35: =IFERROR((SUMIFS($U$3:$U$392,$H$3:$H$392,$H35,$U$3:$U$392,">0")-IF(IFERROR($U35,0)>0,$U35,0))/(COUNTIFS($H$3:$H$392,$H35,$U$3:$U$392,">0")-IF(IFERROR($U35,0)>0,1,0)),"") -> 13.610448 | X35: 6 | Y35: =[1]!wss(AB35,"sec_status","cols=1;rows=1") -> L | AB35: =IF(LEFT(A35,1)="0",MID(A35,2,99),A35) -> 2585.HK | AC35: 12.9 | AD35: 12.5 | AE35: 13.2 | AF35: 11.2 | AG35: 主板 | AH35: H股 | AI35: 主板 | AJ35: 0
A36: 1828.HK | B36: 富卫集团 | C36: 45845 | D36: =IFERROR(IF(ISNUMBER($C36),$C36-2,DATEVALUE($C36)-2),"") -> 45843 | E36: main_board_profitable | F36: =IF(AND(G36<>"",G36<>0),1,0) -> 0 | H36: 金融业(HS)-保险(HS)-保险Ⅲ(HS) | I36: 38 | J36: 38 | K36: 38 | L36: 3661053000 | M36: 2.32 | N36: 37.13 | O36: =IF(IFERROR(N36*1,0)>=15,1,0) -> 1 | P36: 1.723 | Q36: 摩根士丹利亚洲有限公司,香港上海汇丰银行有限公司,招银国际融资有限公司,高盛(亚洲)有限责任公司,交银国际证券有限公司,建银国际金融有限公司,华泰金融控股(香港)有限公司,工银国际证券有限公司,瑞穗证券亚洲有限公司,日兴证券(香港)有限公司,星展亚洲融资有限公司,华侨银行有限公司,大华继显(香港)有限公司 | R36: =IF(Q36="",0,LEN(Q36)-LEN(SUBSTITUTE(Q36,",",""))+1) -> 13 | U36: 259.24879 | V36: =IFERROR((SUMIFS($U$3:$U$392,$H$3:$H$392,$H36,$U$3:$U$392,">0")-IF(IFERROR($U36,0)>0,$U36,0))/(COUNTIFS($H$3:$H$392,$H36,$U$3:$U$392,">0")-IF(IFERROR($U36,0)>0,1,0)),"") -> 15.752299 | X36: 6 | Y36: =[1]!wss(AB36,"sec_status","cols=1;rows=1") -> L | AB36: =IF(LEFT(A36,1)="0",MID(A36,2,99),A36) -> 1828.HK | AC36: 38.4 | AD36: 38 | AE36: 38.8 | AF36: 37.05 | AG36: 主板 | AI36: 主板 | AJ36: 0
A37: 2865.HK | B37: 钧达股份 | C37: 45785 | D37: =IFERROR(IF(ISNUMBER($C37),$C37-2,DATEVALUE($C37)-2),"") -> 45783 | E37: a_plus_h | F37: =IF(AND(G37<>"",G37<>0),1,0) -> 1 | G37: 002865.SZ | H37: 工业(HS)-工业工程(HS)-新能源物料(HS) | I37: 22.15 | J37: 20.4 | K37: 28.6 | L37: 1405025445 | M37: 1.08 | N37: 3.5 | O37: =IF(IFERROR(N37*1,0)>=15,1,0) -> 0 | P37: 0 | Q37: TradeGo Markets Limited,富强证券有限公司,工银国际证券有限公司,建银国际金融有限公司,中银国际亚洲有限公司,复星国际证券有限公司,富途证券国际(香港)有限公司,广发证券(香港)经纪有限公司,百惠证券有限公司,国证国际证券(香港)有限公司,中国国际金融香港证券有限公司,中信里昂证券有限公司,德意志银行(香港分行),招银国际融资有限公司,华泰金融控股(香港)有限公司,元宇宙(国际)证券有限公司,星河证券有限公司,艾德证券期货有限公司 | R37: =IF(Q37="",0,LEN(Q37)-LEN(SUBSTITUTE(Q37,",",""))+1) -> 18 | U37: -10.152748 | V37: =IFERROR((SUMIFS($U$3:$U$392,$H$3:$H$392,$H37,$U$3:$U$392,">0")-IF(IFERROR($U37,0)>0,$U37,0))/(COUNTIFS($H$3:$H$392,$H37,$U$3:$U$392,">0")-IF(IFERROR($U37,0)>0,1,0)),"") | X37: 6 | Y37: =[1]!wss(AB37,"sec_status","cols=1;rows=1") -> L | AB37: =IF(LEFT(A37,1)="0",MID(A37,2,99),A37) -> 2865.HK | AC37: 26.6 | AD37: 22.2 | AE37: 27.5 | AF37: 22.1 | AG37: 主板 | AH37: H股 | AI37: 主板 | AJ37: 0
A38: 2768.HK | B38: 国恩科技 | C38: 46057 | D38: =IFERROR(IF(ISNUMBER($C38),$C38-2,DATEVALUE($C38)-2),"") -> 46055 | E38: a_plus_h | F38: =IF(AND(G38<>"",G38<>0),1,0) -> 1 | G38: 002768.SZ | H38: 原材料业(HS)-原材料(HS)-特殊化工用品(HS) | I38: 36 | J38: 34 | K38: 42 | L38: 1080000000 | M38: 10.03 | N38: 2251.85 | O38: =IF(IFERROR(N38*1,0)>=15,1,0) -> 1 | P38: 0 | Q38: 招商证券(香港)有限公司,中信里昂证券有限公司,中国国际金融香港证券有限公司,招银国际融资有限公司,老虎证券(香港)环球有限公司,利弗莫尔证券有限公司 | R38: =IF(Q38="",0,LEN(Q38)-LEN(SUBSTITUTE(Q38,",",""))+1) -> 6 | U38: 14.65621 | V38: =IFERROR((SUMIFS($U$3:$U$392,$H$3:$H$392,$H38,$U$3:$U$392,">0")-IF(IFERROR($U38,0)>0,$U38,0))/(COUNTIFS($H$3:$H$392,$H38,$U$3:$U$392,">0")-IF(IFERROR($U38,0)>0,1,0)),"") -> 12.408857 | X38: 6 | Y38: =[1]!wss(AB38,"sec_status","cols=1;rows=1") -> L | AB38: =IF(LEFT(A38,1)="0",MID(A38,2,99),A38) -> 2768.HK | AC38: 40.16 | AD38: 45 | AE38: 50.8 | AF38: 39.8 | AG38: 主板 | AH38: H股 | AI38: 主板 | AJ38: 0
A39: 7618.HK | B39: 京东工业 | C39: 46002 | D39: =IFERROR(IF(ISNUMBER($C39),$C39-2,DATEVALUE($C39)-2),"") -> 46000 | E39: main_board_profitable | F39: =IF(AND(G39<>"",G39<>0),1,0) -> 0 | H39: 工业(HS)-工用支援(HS)-采购及供应链管理(HS) | I39: 14.1 | J39: 12.7 | K39: 15.5 | L39: 3033843420 | M39: 7.88 | N39: 60.52 | O39: =IF(IFERROR(N39*1,0)>=15,1,0) -> 1 | P39: 0.547 | Q39: Merrill Lynch (Asia Pacific) Limited,东方证券(香港)有限公司,工银国际证券有限公司,香港上海汇丰银行有限公司,富途证券国际(香港)有限公司,中银国际亚洲有限公司,农银国际证券有限公司,华泰金融控股(香港)有限公司,海通国际证券有限公司,UBS AG Hong Kong Branch,高盛(亚洲)有限责任公司,民银证券有限公司,中信里昂证券有限公司,摩根士丹利(亚太)有限公司,瑞银集团香港分行,农银国际融资有限公司 | R39: =IF(Q39="",0,LEN(Q39)-LEN(SUBSTITUTE(Q39,",",""))+1) -> 16 | U39: 46.076256 | V39: =IFERROR((SUMIFS($U$3:$U$392,$H$3:$H$392,$H39,$U$3:$U$392,">0")-IF(IFERROR($U39,0)>0,$U39,0))/(COUNTIFS($H$3:$H$392,$H39,$U$3:$U$392,">0")-IF(IFERROR($U39,0)>0,1,0)),"") -> 10.954967 | X39: 6 | Y39: =[1]!wss(AB39,"sec_status","cols=1;rows=1") -> L | AB39: =IF(LEFT(A39,1)="0",MID(A39,2,99),A39) -> 7618.HK | AC39: 14.1 | AD39: 13 | AE39: 14.15 | AF39: 12.66 | AG39: 主板 | AI39: 主板 | AJ39: 0
A40: 9885.HK | B40: 药师帮 | C40: 45105 | D40: =IFERROR(IF(ISNUMBER($C40),$C40-2,DATEVALUE($C40)-2),"") -> 45103 | E40: main_board_profitable | F40: =IF(AND(G40<>"",G40<>0),1,0) -> 0 | H40: 医疗保健业(HS)-药品及生物科技(HS)-药品分销(HS) | I40: 20 | J40: 19 | K40: 23 | L40: 344708000 | M40: 2.08 | N40: 5.6 | O40: =IF(IFERROR(N40*1,0)>=15,1,0) -> 0 | P40: 0.272 | Q40: 中国国际金融香港证券有限公司,招银国际融资有限公司,工银国际证券有限公司,农银国际证券有限公司,复星国际证券有限公司,富途证券国际(香港)有限公司,老虎证券(香港)环球有限公司,华盛资本证券有限公司 | R40: =IF(Q40="",0,LEN(Q40)-LEN(SUBSTITUTE(Q40,",",""))+1) -> 8 | U40: -7.5886866 | V40: =IFERROR((SUMIFS($U$3:$U$392,$H$3:$H$392,$H40,$U$3:$U$392,">0")-IF(IFERROR($U40,0)>0,$U40,0))/(COUNTIFS($H$3:$H$392,$H40,$U$3:$U$392,">0")-IF(IFERROR($U40,0)>0,1,0)),"") | X40: 6 | Y40: =[1]!wss(AB40,"sec_status","cols=1;rows=1") -> L | AB40: =IF(LEFT(A40,1)="0",MID(A40,2,99),A40) -> 9885.HK | AC40: 21.1 | AD40: 23.05 | AE40: 23.3 | AF40: 20.55 | AG40: 主板 | AI40: 主板 | AJ40: 0
A41: 9863.HK | B41: 零跑汽车 | C41: 44833 | D41: =IFERROR(IF(ISNUMBER($C41),$C41-2,DATEVALUE($C41)-2),"") -> 44831 | E41: main_board_profitable | F41: =IF(AND(G41<>"",G41<>0),1,0) -> 0 | H41: 非必需性消费(HS)-汽车(HS)-汽车Ⅲ(HS) | I41: 48 | J41: 48 | K41: 62 | L41: 6279316800 | M41: 2.33 | N41: 0.16 | O41: =IF(IFERROR(N41*1,0)>=15,1,0) -> 0 | P41: 0 | Q41: J.P. Morgan Securities (Asia Pacific) Limited,J.P. Morgan Securities plc,中国国际金融香港证券有限公司,花旗环球金融亚洲有限公司,Citigroup Global Markets Limited,建银国际金融有限公司,中信里昂证券有限公司,中信建投(国际)融资有限公司,华泰金融控股(香港)有限公司,农银国际证券有限公司,富途证券国际(香港)有限公司,老虎证券(香港)环球有限公司,J.P. Morgan Securities (Far East) Limited | R41: =IF(Q41="",0,LEN(Q41)-LEN(SUBSTITUTE(Q41,",",""))+1) -> 13 | U41: -15.758555 | V41: =IFERROR((SUMIFS($U$3:$U$392,$H$3:$H$392,$H41,$U$3:$U$392,">0")-IF(IFERROR($U41,0)>0,$U41,0))/(COUNTIFS($H$3:$H$392,$H41,$U$3:$U$392,">0")-IF(IFERROR($U41,0)>0,1,0)),"") -> 16.882618 | X41: 6 | Y41: =[1]!wss(AB41,"sec_status","cols=1;rows=1") -> L | AB41: =IF(LEFT(A41,1)="0",MID(A41,2,99),A41) -> 9863.HK | AC41: 31.9 | AD41: 41 | AE41: 41 | AF41: 28.05 | AG41: 主板 | AH41: H股 | AI41: 主板 | AJ41: 0
A42: 0470.HK | B42: 先导智能 | C42: 46064 | D42: =IFERROR(IF(ISNUMBER($C42),$C42-2,DATEVALUE($C42)-2),"") -> 46062 | E42: a_plus_h | F42: =IF(AND(G42<>"",G42<>0),1,0) -> 1 | G42: 300450.SZ | H42: 工业(HS)-工业工程(HS)-工业零件及器材(HS) | I42: 45.8 | K42: 45.8 | L42: 4949074720 | M42: 10.47 | N42: 79.54 | O42: =IF(IFERROR(N42*1,0)>=15,1,0) -> 1 | P42: 0.18 | Q42: 工银国际证券有限公司,中信里昂证券有限公司,J.P. Morgan Securities (Asia Pacific) Limited,华泰金融控股(香港)有限公司,中银国际亚洲有限公司,招银国际融资有限公司,浦银国际融资有限公司,农银国际融资有限公司,农银国际证券有限公司 | R42: =IF(Q42="",0,LEN(Q42)-LEN(SUBSTITUTE(Q42,",",""))+1) -> 9 | U42: 248.13412 | V42: =IFERROR((SUMIFS($U$3:$U$392,$H$3:$H$392,$H42,$U$3:$U$392,">0")-IF(IFERROR($U42,0)>0,$U42,0))/(COUNTIFS($H$3:$H$392,$H42,$U$3:$U$392,">0")-IF(IFERROR($U42,0)>0,1,0)),"") -> 60.613681 | X42: 6 | Y42: =[1]!wss(AB42,"sec_status","cols=1;rows=1") | AB42: =IF(LEFT(A42,1)="0",MID(A42,2,99),A42) -> 470.HK | AC42: 45.8 | AD42: 46.26 | AE42: 46.54 | AF42: 45.04 | AG42: 主板 | AH42: H股 | AI42: 主板 | AJ42: 0
A43: 2419.HK | B43: 德康农牧 | C43: 45266 | D43: =IFERROR(IF(ISNUMBER($C43),$C43-2,DATEVALUE($C43)-2),"") -> 45264 | E43: main_board_profitable | F43: =IF(AND(G43<>"",G43<>0),1,0) -> 0 | H43: 必需性消费(HS)-农业产品(HS)-禽畜肉类(HS) | I43: 36.95 | J43: 30.35 | K43: 36.95 | L43: 994398400 | M43: 1.13 | N43: 1.88 | O43: =IF(IFERROR(N43*1,0)>=15,1,0) -> 0 | P43: 0 | Q43: 民银证券有限公司,华盛资本证券有限公司,鉅诚证券有限公司,招银国际融资有限公司,工银国际证券有限公司,中国国际金融香港证券有限公司,中国银河国际证券(香港)有限公司,农银国际证券有限公司,中银国际亚洲有限公司,中国光大证券(香港)有限公司,Citigroup Global Markets Limited,花旗环球金融亚洲有限公司 | R43: =IF(Q43="",0,LEN(Q43)-LEN(SUBSTITUTE(Q43,",",""))+1) -> 12 | U43: 12.927582 | V43: =IFERROR((SUMIFS($U$3:$U$392,$H$3:$H$392,$H43,$U$3:$U$392,">0")-IF(IFERROR($U43,0)>0,$U43,0))/(COUNTIFS($H$3:$H$392,$H43,$U$3:$U$392,">0")-IF(IFERROR($U43,0)>0,1,0)),"") -> 11.586709 | X43: 6 | Y43: =[1]!wss(AB43,"sec_status","cols=1;rows=1") -> L | AB43: =IF(LEFT(A43,1)="0",MID(A43,2,99),A43) -> 2419.HK | AC43: 37.5 | AD43: 36.95 | AE43: 38 | AF43: 36.95 | AG43: 主板 | AH43: H股 | AI43: 主板 | AJ43: 0
A44: 2259.HK | B44: 紫金黄金国际 | C44: 45930 | D44: =IFERROR(IF(ISNUMBER($C44),$C44-2,DATEVALUE($C44)-2),"") -> 45928 | E44: main_board_profitable | F44: =IF(AND(G44<>"",G44<>0),1,0) -> 0 | H44: 原材料业(HS)-黄金及贵金属(HS)-黄金及贵金属Ⅲ(HS) | I44: 71.59 | J44: 71.59 | K44: 71.59 | L44: 28731880487 | M44: 20.38 | N44: 240.74 | O44: =IF(IFERROR(N44*1,0)>=15,1,0) -> 1 | P44: 37.023 | Q44: 摩根士丹利亚洲有限公司,Morgan Stanley & Co. International plc,中信里昂证券有限公司,广发证券(香港)经纪有限公司,华泰金融控股(香港)有限公司,麦格理资本股份有限公司,兴证国际融资有限公司 | R44: =IF(Q44="",0,LEN(Q44)-LEN(SUBSTITUTE(Q44,",",""))+1) -> 7 | U44: 50.272704 | V44: =IFERROR((SUMIFS($U$3:$U$392,$H$3:$H$392,$H44,$U$3:$U$392,">0")-IF(IFERROR($U44,0)>0,$U44,0))/(COUNTIFS($H$3:$H$392,$H44,$U$3:$U$392,">0")-IF(IFERROR($U44,0)>0,1,0)),"") -> 20.351365 | X44: 6 | Y44: =[1]!wss(AB44,"sec_status","cols=1;rows=1") -> L | AB44: =IF(LEFT(A44,1)="0",MID(A44,2,99),A44) -> 2259.HK | AC44: 120.6 | AD44: 111.5 | AE44: 123 | AF44: 111 | AG44: 主板 | AI44: 主板 | AJ44: 0
A45: 3660.HK | B45: 奇富科技-S | C45: 44894 | D45: =IFERROR(IF(ISNUMBER($C45),$C45-2,DATEVALUE($C45)-2),"") -> 44892 | E45: secondary | F45: =IF(AND(G45<>"",G45<>0),1,0) -> 0 | H45: 金融业(HS)-其他金融(HS)-信贷(HS) | I45: 50.03 | J45: 50.03 | K45: 88.8 | L45: 318691100 | M45: 5.3 | N45: 2.46 | O45: =IF(IFERROR(N45*1,0)>=15,1,0) -> 0 | P45: 0.377 | Q45: 花旗环球金融亚洲有限公司,Citigroup Global Markets Limited,中国国际金融香港证券有限公司,建银国际金融有限公司,富途证券国际(香港)有限公司,老虎证券(香港)环球有限公司,利弗莫尔证券有限公司 | R45: =IF(Q45="",0,LEN(Q45)-LEN(SUBSTITUTE(Q45,",",""))+1) -> 7 | U45: 2.2708188 | V45: =IFERROR((SUMIFS($U$3:$U$392,$H$3:$H$392,$H45,$U$3:$U$392,">0")-IF(IFERROR($U45,0)>0,$U45,0))/(COUNTIFS($H$3:$H$392,$H45,$U$3:$U$392,">0")-IF(IFERROR($U45,0)>0,1,0)),"") -> 13.261622 | Y45: =[1]!wss(AB45,"sec_status","cols=1;rows=1") -> L | AB45: =IF(LEFT(A45,1)="0",MID(A45,2,99),A45) -> 3660.HK | AC45: 51.75 | AD45: 50.6 | AE45: 51.95 | AF45: 50 | AG45: 主板 | AI45: 主板 | AJ45: 0
A46: 2648.HK | B46: 安井食品 | C46: 45842 | D46: =IFERROR(IF(ISNUMBER($C46),$C46-2,DATEVALUE($C46)-2),"") -> 45840 | E46: a_plus_h | F46: =IF(AND(G46<>"",G46<>0),1,0) -> 1 | G46: 603345.SH | H46: 必需性消费(HS)-食物饮品(HS)-包装食品(HS) | I46: 60 | K46: 66 | L46: 2399682000 | M46: 5.85 | N46: 44.2 | O46: =IF(IFERROR(N46*1,0)>=15,1,0) -> 1 | P46: 0 | Q46: 平安证券(香港)有限公司,招银国际融资有限公司,中信建投(国际)融资有限公司,华泰金融控股(香港)有限公司,中国银河国际证券(香港)有限公司,大华继显(香港)有限公司,广发证券(香港)经纪有限公司,建银国际金融有限公司,兴证国际融资有限公司,高盛(亚洲)有限责任公司 | R46: =IF(Q46="",0,LEN(Q46)-LEN(SUBSTITUTE(Q46,",",""))+1) -> 10 | U46: 12.471677 | V46: =IFERROR((SUMIFS($U$3:$U$392,$H$3:$H$392,$H46,$U$3:$U$392,">0")-IF(IFERROR($U46,0)>0,$U46,0))/(COUNTIFS($H$3:$H$392,$H46,$U$3:$U$392,">0")-IF(IFERROR($U46,0)>0,1,0)),"") -> 31.243203 | X46: 6 | Y46: =[1]!wss(AB46,"sec_status","cols=1;rows=1") -> L | AB46: =IF(LEFT(A46,1)="0",MID(A46,2,99),A46) -> 2648.HK | AC46: 57 | AD46: 60 | AE46: 60.1 | AF46: 57 | AG46: 主板 | AH46: H股 | AI46: 主板 | AJ46: 0
A47: 2788.HK | B47: 创新实业 | C47: 45985 | D47: =IFERROR(IF(ISNUMBER($C47),$C47-2,DATEVALUE($C47)-2),"") -> 45983 | E47: main_board_profitable | F47: =IF(AND(G47<>"",G47<>0),1,0) -> 0 | H47: 原材料业(HS)-一般金属及矿石(HS)-铝(HS) | I47: 10.99 | J47: 10.18 | K47: 10.99 | L47: 6319250000 | M47: 19.85 | N47: 447.2 | O47: =IF(IFERROR(N47*1,0)>=15,1,0) -> 1 | P47: 8.118 | Q47: 利弗莫尔证券有限公司,老虎证券(香港)环球有限公司,富途证券国际(香港)有限公司,南华证券投资有限公司,中航资信环球资产管理有限公司,中银国际亚洲有限公司,招银国际融资有限公司,华泰金融控股(香港)有限公司,中国国际金融香港证券有限公司,大华继显(香港)有限公司 | R47: =IF(Q47="",0,LEN(Q47)-LEN(SUBSTITUTE(Q47,",",""))+1) -> 10 | U47: 9.8988872 | V47: =IFERROR((SUMIFS($U$3:$U$392,$H$3:$H$392,$H47,$U$3:$U$392,">0")-IF(IFERROR($U47,0)>0,$U47,0))/(COUNTIFS($H$3:$H$392,$H47,$U$3:$U$392,">0")-IF(IFERROR($U47,0)>0,1,0)),"") -> 5.0165752 | X47: 6 | Y47: =[1]!wss(AB47,"sec_status","cols=1;rows=1") -> L | AB47: =IF(LEFT(A47,1)="0",MID(A47,2,99),A47) -> 2788.HK | AC47: 14.59 | AD47: 15.2 | AE47: 15.8 | AF47: 14.18 | AG47: 主板 | AI47: 主板 | AJ47: 0
A48: 0666.HK | B48: 瑞浦兰钧 | C48: 45278 | D48: =IFERROR(IF(ISNUMBER($C48),$C48-2,DATEVALUE($C48)-2),"") -> 45276 | E48: main_board_profitable | F48: =IF(AND(G48<>"",G48<>0),1,0) -> 0 | H48: 工业(HS)-工业工程(HS)-能源储存装置(HS) | I48: 18.3 | J48: 18.2 | K48: 20.6 | L48: 2124084660 | M48: 1.21 | N48: 1.27 | O48: =IF(IFERROR(N48*1,0)>=15,1,0) -> 0 | P48: 0 | Q48: 摩根士丹利亚洲有限公司,星展亚洲融资有限公司,中国银河国际证券(香港)有限公司,香港上海汇丰银行有限公司,中信里昂证券有限公司,中国国际金融香港证券有限公司,华盛资本证券有限公司,富途证券国际(香港)有限公司,老虎证券(香港)环球有限公司,农银国际证券有限公司,中银国际亚洲有限公司,招银国际融资有限公司,国泰君安证券(香港)有限公司 | R48: =IF(Q48="",0,LEN(Q48)-LEN(SUBSTITUTE(Q48,",",""))+1) -> 13 | U48: -105.10446 | V48: =IFERROR((SUMIFS($U$3:$U$392,$H$3:$H$392,$H48,$U$3:$U$392,">0")-IF(IFERROR($U48,0)>0,$U48,0))/(COUNTIFS($H$3:$H$392,$H48,$U$3:$U$392,">0")-IF(IFERROR($U48,0)>0,1,0)),"") -> 143.35541 | Y48: =[1]!wss(AB48,"sec_status","cols=1;rows=1") | AB48: =IF(LEFT(A48,1)="0",MID(A48,2,99),A48) -> 666.HK | AC48: 18.78 | AD48: 18.6 | AE48: 19.66 | AF48: 18.56 | AG48: 主板 | AH48: H股 | AI48: 主板 | AJ48: 0
A49: 9690.HK | B49: 途虎-W | C49: 45195 | D49: =IFERROR(IF(ISNUMBER($C49),$C49-2,DATEVALUE($C49)-2),"") -> 45193 | E49: 18a | F49: =IF(AND(G49<>"",G49<>0),1,0) -> 0 | H49: 非必需性消费(HS)-专业零售(HS)-汽车零售商(HS) | I49: 28 | J49: 28 | K49: 31 | L49: 1315042400 | M49: 2.3 | N49: 2.67 | O49: =IF(IFERROR(N49*1,0)>=15,1,0) -> 0 | P49: 1.228 | Q49: 高盛(亚洲)有限责任公司,中国国际金融香港证券有限公司,UBS AG Hong Kong Branch,Merrill Lynch (Asia Pacific) Limited,招银国际融资有限公司,交银国际证券有限公司,工银国际证券有限公司,农银国际证券有限公司,富途证券国际(香港)有限公司 | R49: =IF(Q49="",0,LEN(Q49)-LEN(SUBSTITUTE(Q49,",",""))+1) -> 9 | U49: -9.535136 | V49: =IFERROR((SUMIFS($U$3:$U$392,$H$3:$H$392,$H49,$U$3:$U$392,">0")-IF(IFERROR($U49,0)>0,$U49,0))/(COUNTIFS($H$3:$H$392,$H49,$U$3:$U$392,">0")-IF(IFERROR($U49,0)>0,1,0)),"") | X49: 6 | Y49: =[1]!wss(AB49,"sec_status","cols=1;rows=1") -> L | AB49: =IF(LEFT(A49,1)="0",MID(A49,2,99),A49) -> 9690.HK | AC49: 29.5 | AD49: 28 | AE49: 29.8 | AF49: 28 | AG49: 主板 | AI49: 主板 | AJ49: 0
A50: 2460.HK | B50: 华润饮料 | C50: 45588 | D50: =IFERROR(IF(ISNUMBER($C50),$C50-2,DATEVALUE($C50)-2),"") -> 45586 | E50: main_board_profitable | F50: =IF(AND(G50<>"",G50<>0),1,0) -> 0 | H50: 必需性消费(HS)-食物饮品(HS)-非酒精饮料(HS) | I50: 14.5 | J50: 13.5 | K50: 14.5 | L50: 5773850700 | M50: 24.47 | N50: 234.49 | O50: =IF(IFERROR(N50*1,0)>=15,1,0) -> 1 | P50: 7.186 | Q50: UBS AG Hong Kong Branch,中银国际亚洲有限公司,中信里昂证券有限公司,Merrill Lynch (Asia Pacific) Limited,中国国际金融香港证券有限公司,招银国际融资有限公司,香港上海汇丰银行有限公司,华泰金融控股(香港)有限公司,农银国际证券有限公司,建银国际金融有限公司 | R50: =IF(Q50="",0,LEN(Q50)-LEN(SUBSTITUTE(Q50,",",""))+1) -> 10 | U50: 23.207651 | V50: =IFERROR((SUMIFS($U$3:$U$392,$H$3:$H$392,$H50,$U$3:$U$392,">0")-IF(IFERROR($U50,0)>0,$U50,0))/(COUNTIFS($H$3:$H$392,$H50,$U$3:$U$392,">0")-IF(IFERROR($U50,0)>0,1,0)),"") -> 26.890595 | X50: 6 | Y50: =[1]!wss(AB50,"sec_status","cols=1;rows=1") -> L | AB50: =IF(LEFT(A50,1)="0",MID(A50,2,99),A50) -> 2460.HK | AC50: 16.68 | AD50: 16.46 | AE50: 16.78 | AF50: 15.72 | AG50: 主板 | AH50: 红筹股 | AI50: 主板 | AJ50: 0
A51: 7489.HK | B51: 岚图汽车 | C51: 46100 | D51: =IFERROR(IF(ISNUMBER($C51),$C51-2,DATEVALUE($C51)-2),"") -> 46098 | E51: main_board_profitable | F51: =IF(AND(G51<>"",G51<>0),1,0) -> 0 | H51: 非必需性消费(HS)-汽车(HS)-汽车Ⅲ(HS) | L51: 0 | M51: 0 | N51: 0 | O51: =IF(IFERROR(N51*1,0)>=15,1,0) -> 0 | P51: 0 | Q51: 0 | R51: =IF(Q51="",0,LEN(Q51)-LEN(SUBSTITUTE(Q51,",",""))+1) -> 1 | U51: 0 | V51: =IFERROR((SUMIFS($U$3:$U$392,$H$3:$H$392,$H51,$U$3:$U$392,">0")-IF(IFERROR($U51,0)>0,$U51,0))/(COUNTIFS($H$3:$H$392,$H51,$U$3:$U$392,">0")-IF(IFERROR($U51,0)>0,1,0)),"") -> 16.882618 | Y51: =[1]!wss(AB51,"sec_status","cols=1;rows=1") -> L | AB51: =IF(LEFT(A51,1)="0",MID(A51,2,99),A51) -> 7489.HK | AC51: 6.51 | AD51: 7.5 | AE51: 7.5 | AF51: 6.25 | AG51: 主板 | AH51: H股 | AI51: 主板 | AJ51: 0
A52: 9896.HK | B52: 名创优品 | C52: 44755 | D52: =IFERROR(IF(ISNUMBER($C52),$C52-2,DATEVALUE($C52)-2),"") -> 44753 | E52: main_board_profitable | F52: =IF(AND(G52<>"",G52<>0),1,0) -> 0 | H52: 非必需性消费(HS)-专业零售(HS)-多元化零售商(HS) | I52: 13.8 | K52: 22.1 | L52: 573889560 | M52: 4.84 | N52: 1.4 | O52: =IF(IFERROR(N52*1,0)>=15,1,0) -> 0 | P52: 0.064 | Q52: Merrill Lynch (Asia Pacific) Limited,海通国际证券有限公司,UBS AG Hong Kong Branch,UBS Securities LLC,富途证券国际(香港)有限公司,广发证券(香港)经纪有限公司 | R52: =IF(Q52="",0,LEN(Q52)-LEN(SUBSTITUTE(Q52,",",""))+1) -> 6 | U52: -10.278906 | V52: =IFERROR((SUMIFS($U$3:$U$392,$H$3:$H$392,$H52,$U$3:$U$392,">0")-IF(IFERROR($U52,0)>0,$U52,0))/(COUNTIFS($H$3:$H$392,$H52,$U$3:$U$392,">0")-IF(IFERROR($U52,0)>0,1,0)),"") | Y52: =[1]!wss(AB52,"sec_status","cols=1;rows=1") -> L | AB52: =IF(LEFT(A52,1)="0",MID(A52,2,99),A52) -> 9896.HK | AC52: 13.38 | AD52: 13.2 | AE52: 13.66 | AF52: 13.12 | AG52: 主板 | AI52: 主板 | AJ52: 0
A53: 2411.HK | B53: 百果园集团 | C53: 44942 | D53: =IFERROR(IF(ISNUMBER($C53),$C53-2,DATEVALUE($C53)-2),"") -> 44940 | E53: main_board_profitable | F53: =IF(AND(G53<>"",G53<>0),1,0) -> 0 | H53: 必需性消费(HS)-食物饮品(HS)-包装食品(HS) | I53: 5.6 | J53: 5 | K53: 6.2 | L53: 495846400 | M53: 2.8 | N53: 12.2 | O53: =IF(IFERROR(N53*1,0)>=15,1,0) -> 0 | P53: 0.516 | Q53: 摩根士丹利亚洲有限公司,招银国际融资有限公司,复星恒利证券有限公司,第一上海证券有限公司,富途证券国际(香港)有限公司,老虎证券(香港)环球有限公司 | R53: =IF(Q53="",0,LEN(Q53)-LEN(SUBSTITUTE(Q53,",",""))+1) -> 6 | U53: 31.384688 | V53: =IFERROR((SUMIFS($U$3:$U$392,$H$3:$H$392,$H53,$U$3:$U$392,">0")-IF(IFERROR($U53,0)>0,$U53,0))/(COUNTIFS($H$3:$H$392,$H53,$U$3:$U$392,">0")-IF(IFERROR($U53,0)>0,1,0)),"") -> 28.541345 | X53: 6 | Y53: =[1]!wss(AB53,"sec_status","cols=1;rows=1") -> L | AB53: =IF(LEFT(A53,1)="0",MID(A53,2,99),A53) -> 2411.HK | AC53: 6 | AD53: 6.52 | AE53: 7.12 | AF53: 6 | AG53: 主板 | AH53: H股 | AI53: 主板 | AJ53: 0
A54: 9980.HK | B54: 东鹏饮料 | C54: 46056 | D54: =IFERROR(IF(ISNUMBER($C54),$C54-2,DATEVALUE($C54)-2),"") -> 46054 | E54: a_plus_h | F54: =IF(AND(G54<>"",G54<>0),1,0) -> 1 | G54: 605499.SH | H54: 必需性消费(HS)-食物饮品(HS)-非酒精饮料(HS) | I54: 248 | K54: 248 | L54: 11099413600 | M54: 15.6 | N54: 57.46 | O54: =IF(IFERROR(N54*1,0)>=15,1,0) -> 1 | P54: 9.4905 | Q54: 华泰金融控股(香港)有限公司,摩根士丹利亚洲有限公司,UBS AG Hong Kong Branch | R54: =IF(Q54="",0,LEN(Q54)-LEN(SUBSTITUTE(Q54,",",""))+1) -> 3 | U54: 38.721678 | V54: =IFERROR((SUMIFS($U$3:$U$392,$H$3:$H$392,$H54,$U$3:$U$392,">0")-IF(IFERROR($U54,0)>0,$U54,0))/(COUNTIFS($H$3:$H$392,$H54,$U$3:$U$392,">0")-IF(IFERROR($U54,0)>0,1,0)),"") -> 25.166814 | X54: 6 | Y54: =[1]!wss(AB54,"sec_status","cols=1;rows=1") -> L | AB54: =IF(LEFT(A54,1)="0",MID(A54,2,99),A54) -> 9980.HK | AC54: 251.8 | AD54: 248 | AE54: 251.8 | AF54: 245.6 | AG54: 主板 | AH54: H股 | AI54: 主板 | AJ54: 0
A55: 2520.HK | B55: 山西安装 | C55: 45252 | D55: =IFERROR(IF(ISNUMBER($C55),$C55-2,DATEVALUE($C55)-2),"") -> 45250 | E55: main_board_profitable | F55: =IF(AND(G55<>"",G55<>0),1,0) -> 0 | H55: 地产建筑业(HS)-建筑(HS)-重型基建(HS) | I55: 2.18 | J55: 2.1 | K55: 2.36 | L55: 814199480 | M55: 1.33 | N55: 0.6 | O55: =IF(IFERROR(N55*1,0)>=15,1,0) -> 0 | P55: 0.845 | Q55: 山证国际证券有限公司,华泰金融控股(香港)有限公司,交银国际证券有限公司,中国光大证券(香港)有限公司,招银国际融资有限公司,富途证券国际(香港)有限公司,工银国际融资有限公司,中泰国际证券有限公司,艾德证券期货有限公司,百惠证券有限公司,胜利证券有限公司,中募金融资管有限公司 | R55: =IF(Q55="",0,LEN(Q55)-LEN(SUBSTITUTE(Q55,",",""))+1) -> 12 | U55: 17.208411 | V55: =IFERROR((SUMIFS($U$3:$U$392,$H$3:$H$392,$H55,$U$3:$U$392,">0")-IF(IFERROR($U55,0)>0,$U55,0))/(COUNTIFS($H$3:$H$392,$H55,$U$3:$U$392,">0")-IF(IFERROR($U55,0)>0,1,0)),"") -> 9.3172195 | X55: 36 | Y55: =[1]!wss(AB55,"sec_status","cols=1;rows=1") -> L | AB55: =IF(LEFT(A55,1)="0",MID(A55,2,99),A55) -> 2520.HK | AC55: 2.18 | AD55: 2.18 | AE55: 2.25 | AF55: 2.18 | AG55: 主板 | AH55: H股 | AI55: 主板 | AJ55: 0
A56: 2643.HK | B56: 曹操出行 | C56: 45833 | D56: =IFERROR(IF(ISNUMBER($C56),$C56-2,DATEVALUE($C56)-2),"") -> 45831 | E56: main_board_profitable | F56: =IF(AND(G56<>"",G56<>0),1,0) -> 0 | H56: 非必需性消费(HS)-旅游及消闲设施(HS)-公共运输(HS) | I56: 41.94 | J56: 41.94 | K56: 41.94 | L56: 1852850484 | M56: 2.78 | N56: 21.14 | O56: =IF(IFERROR(N56*1,0)>=15,1,0) -> 1 | P56: 0 | Q56: 华泰金融控股(香港)有限公司,农银国际证券有限公司,广发证券(香港)经纪有限公司,中国国际金融香港证券有限公司,中国银河国际证券(香港)有限公司,光银国际资本有限公司,中银国际亚洲有限公司,东吴证券国际经纪有限公司,工银国际证券有限公司,富途证券国际(香港)有限公司,老虎证券(香港)环球有限公司,胜利证券有限公司,中和金控有限公司,星河证券有限公司,农银国际融资有限公司 | R56: =IF(Q56="",0,LEN(Q56)-LEN(SUBSTITUTE(Q56,",",""))+1) -> 15 | U56: -16.897503 | V56: =IFERROR((SUMIFS($U$3:$U$392,$H$3:$H$392,$H56,$U$3:$U$392,">0")-IF(IFERROR($U56,0)>0,$U56,0))/(COUNTIFS($H$3:$H$392,$H56,$U$3:$U$392,">0")-IF(IFERROR($U56,0)>0,1,0)),"") -> 17.992258 | X56: 6 | Y56: =[1]!wss(AB56,"sec_status","cols=1;rows=1") -> L | AB56: =IF(LEFT(A56,1)="0",MID(A56,2,99),A56) -> 2643.HK | AC56: 36 | AD56: 33.8 | AE56: 36.8 | AF56: 32.85 | AG56: 主板 | AI56: 主板 | AJ56: 0
A57: 1768.HK | B57: 鸣鸣很忙 | C57: 46050 | D57: =IFERROR(IF(ISNUMBER($C57),$C57-2,DATEVALUE($C57)-2),"") -> 46048 | E57: main_board_profitable | F57: =IF(AND(G57<>"",G57<>0),1,0) -> 0 | H57: 必需性消费(HS)-食物饮品(HS)-包装食品(HS) | I57: 236.6 | J57: 229.6 | K57: 236.6 | L57: 4220423480 | M57: 44.44 | N57: 1899.49 | O57: =IF(IFERROR(N57*1,0)>=15,1,0) -> 1 | P57: 5.34 | Q57: 高盛(亚洲)有限责任公司,华泰金融控股(香港)有限公司,德意志银行香港分行,海通国际证券有限公司,浦银国际融资有限公司,富途证券国际(香港)有限公司 | R57: =IF(Q57="",0,LEN(Q57)-LEN(SUBSTITUTE(Q57,",",""))+1) -> 6 | U57: 56.637491 | V57: =IFERROR((SUMIFS($U$3:$U$392,$H$3:$H$392,$H57,$U$3:$U$392,">0")-IF(IFERROR($U57,0)>0,$U57,0))/(COUNTIFS($H$3:$H$392,$H57,$U$3:$U$392,">0")-IF(IFERROR($U57,0)>0,1,0)),"") -> 24.933801 | X57: 6 | Y57: =[1]!wss(AB57,"sec_status","cols=1;rows=1") -> L | AB57: =IF(LEFT(A57,1)="0",MID(A57,2,99),A57) -> 1768.HK | AC57: 400 | AD57: 445 | AE57: 445 | AF57: 399.2 | AG57: 主板 | AH57: H股 | AI57: 主板 | AJ57: 0
A58: 9930.HK | B58: 宏信建发 | C58: 45071 | D58: =IFERROR(IF(ISNUMBER($C58),$C58-2,DATEVALUE($C58)-2),"") -> 45069 | E58: main_board_profitable | F58: =IF(AND(G58<>"",G58<>0),1,0) -> 0 | H58: 工业(HS)-工业工程(HS)-重型机械(HS) | I58: 4.52 | J58: 4.52 | K58: 4.8 | L58: 1648416880 | M58: 1.47 | N58: 0.12 | O58: =IF(IFERROR(N58*1,0)>=15,1,0) -> 0 | P58: 0 | Q58: 华泰金融控股(香港)有限公司,花旗环球金融亚洲有限公司,Citigroup Global Markets Limited,招银国际融资有限公司,星展亚洲融资有限公司,中银国际亚洲有限公司,申万宏源证券(香港)有限公司,国泰君安证券(香港)有限公司,交银国际证券有限公司,建银国际金融有限公司,农银国际证券有限公司,中泰国际证券有限公司,富途证券国际(香港)有限公司,老虎证券(香港)环球有限公司,华盛资本证券有限公司 | R58: =IF(Q58="",0,LEN(Q58)-LEN(SUBSTITUTE(Q58,",",""))+1) -> 15 | U58: 19.366735 | V58: =IFERROR((SUMIFS($U$3:$U$392,$H$3:$H$392,$H58,$U$3:$U$392,">0")-IF(IFERROR($U58,0)>0,$U58,0))/(COUNTIFS($H$3:$H$392,$H58,$U$3:$U$392,">0")-IF(IFERROR($U58,0)>0,1,0)),"") -> 30.058394 | X58: 6 | Y58: =[1]!wss(AB58,"sec_status","cols=1;rows=1") -> L | AB58: =IF(LEFT(A58,1)="0",MID(A58,2,99),A58) -> 9930.HK | AC58: 3.21 | AD58: 3.26 | AE58: 3.74 | AF58: 3.13 | AG58: 主板 | AH58: 红筹股 | AI58: 主板 | AJ58: 0
A59: 9638.HK | B59: 法拉帝 | C59: 44651 | D59: =IFERROR(IF(ISNUMBER($C59),$C59-2,DATEVALUE($C59)-2),"") -> 44649 | E59: main_board_profitable | F59: =IF(AND(G59<>"",G59<>0),1,0) -> 0 | H59: 工业(HS)-工业工程(HS)-商用运输工具及货车(HS) | I59: 22.88 | J59: 21.82 | K59: 28.24 | L59: 2007667376 | M59: 2.06 | N59: 1.07 | O59: =IF(IFERROR(N59*1,0)>=15,1,0) -> 0 | P59: 0.9154 | Q59: 中国国际金融(香港)有限公司,法国巴黎证券(亚洲)有限公司,中泰国际证券有限公司 | R59: =IF(Q59="",0,LEN(Q59)-LEN(SUBSTITUTE(Q59,",",""))+1) -> 3 | U59: 23.071798 | V59: =IFERROR((SUMIFS($U$3:$U$392,$H$3:$H$392,$H59,$U$3:$U$392,">0")-IF(IFERROR($U59,0)>0,$U59,0))/(COUNTIFS($H$3:$H$392,$H59,$U$3:$U$392,">0")-IF(IFERROR($U59,0)>0,1,0)),"") -> 9.5616298 | X59: 6 | Y59: =[1]!wss(AB59,"sec_status","cols=1;rows=1") -> L | AB59: =IF(LEFT(A59,1)="0",MID(A59,2,99),A59) -> 9638.HK | AC59: 22.85 | AD59: 23.05 | AE59: 23.75 | AF59: 22.85 | AG59: 主板 | AH59: 红筹股 | AI59: 主板 | AJ59: 0
A60: 2465.HK | B60: 龙蟠科技 | C60: 45595 | D60: =IFERROR(IF(ISNUMBER($C60),$C60-2,DATEVALUE($C60)-2),"") -> 45593 | E60: a_plus_h | F60: =IF(AND(G60<>"",G60<>0),1,0) -> 1 | G60: 603906.SH | H60: 工业(HS)-工业工程(HS)-能源储存装置(HS) | I60: 5.5 | J60: 4.5 | K60: 7 | L60: 550000000 | M60: 3.23 | N60: 3.99 | O60: =IF(IFERROR(N60*1,0)>=15,1,0) -> 0 | P60: 0 | Q60: 国泰君安证券(香港)有限公司,铠盛证券有限公司,工银国际证券有限公司,中银国际亚洲有限公司,建银国际金融有限公司,农银国际融资有限公司,农银国际证券有限公司,招银国际融资有限公司,TradeGo Markets Limited,利弗莫尔证券有限公司 | R60: =IF(Q60="",0,LEN(Q60)-LEN(SUBSTITUTE(Q60,",",""))+1) -> 10 | U60: -2.6878433 | V60: =IFERROR((SUMIFS($U$3:$U$392,$H$3:$H$392,$H60,$U$3:$U$392,">0")-IF(IFERROR($U60,0)>0,$U60,0))/(COUNTIFS($H$3:$H$392,$H60,$U$3:$U$392,">0")-IF(IFERROR($U60,0)>0,1,0)),"") -> 143.35541 | X60: 6 | Y60: =[1]!wss(AB60,"sec_status","cols=1;rows=1") -> L | AB60: =IF(LEFT(A60,1)="0",MID(A60,2,99),A60) -> 2465.HK | AC60: 4.75 | AD60: 5.08 | AE60: 5.46 | AF60: 4.2 | AG60: 主板 | AH60: H股 | AI60: 主板 | AJ60: 0
A61: 2519.HK | B61: 傲基股份 | C61: 45604 | D61: =IFERROR(IF(ISNUMBER($C61),$C61-2,DATEVALUE($C61)-2),"") -> 45602 | E61: main_board_profitable | F61: =IF(AND(G61<>"",G61<>0),1,0) -> 0 | H61: 非必需性消费(HS)-专业零售(HS)-家居装修零售商(HS) | I61: 15.6 | J61: 14.56 | K61: 15.6 | L61: 466357320 | M61: 2.45 | N61: 17.74 | O61: =IF(IFERROR(N61*1,0)>=15,1,0) -> 1 | P61: 0 | Q61: 华泰金融控股(香港)有限公司,中信里昂证券有限公司,星展亚洲融资有限公司,利弗莫尔证券有限公司 | R61: =IF(Q61="",0,LEN(Q61)-LEN(SUBSTITUTE(Q61,",",""))+1) -> 4 | U61: 11.033212 | V61: =IFERROR((SUMIFS($U$3:$U$392,$H$3:$H$392,$H61,$U$3:$U$392,">0")-IF(IFERROR($U61,0)>0,$U61,0))/(COUNTIFS($H$3:$H$392,$H61,$U$3:$U$392,">0")-IF(IFERROR($U61,0)>0,1,0)),"") | X61: 6 | Y61: =[1]!wss(AB61,"sec_status","cols=1;rows=1") -> L | AB61: =IF(LEFT(A61,1)="0",MID(A61,2,99),A61) -> 2519.HK | AC61: 13.82 | AD61: 13.88 | AE61: 14.96 | AF61: 12.5 | AG61: 主板 | AH61: H股 | AI61: 主板 | AJ61: 0
A62: 2476.HK | B62: 胜宏科技 | C62: 46133 | D62: =IFERROR(IF(ISNUMBER($C62),$C62-2,DATEVALUE($C62)-2),"") -> 46131 | E62: a_plus_h | F62: =IF(AND(G62<>"",G62<>0),1,0) -> 1 | G62: 300476.SZ | H62: 工业(HS)-工业工程(HS)-电子零件(HS) | I62: 209.88 | K62: 209.88 | L62: 23134547700 | M62: 18.5 | N62: 431.15 | O62: =IF(IFERROR(N62*1,0)>=15,1,0) -> 1 | P62: 29.9039 | Q62: 中信建投(国际)融资有限公司,中国国际金融香港证券有限公司,农银国际证券有限公司,农银国际融资有限公司,华泰金融控股(香港)有限公司,广发证券(香港)经纪有限公司,J.P. Morgan Securities (Asia Pacific) Limited | R62: =IF(Q62="",0,LEN(Q62)-LEN(SUBSTITUTE(Q62,",",""))+1) -> 7 | U62: 42.574065 | V62: =IFERROR((SUMIFS($U$3:$U$392,$H$3:$H$392,$H62,$U$3:$U$392,">0")-IF(IFERROR($U62,0)>0,$U62,0))/(COUNTIFS($H$3:$H$392,$H62,$U$3:$U$392,">0")-IF(IFERROR($U62,0)>0,1,0)),"") -> 32.235335 | X62: 6 | Y62: =[1]!wss(AB62,"sec_status","cols=1;rows=1") -> L | AB62: =IF(LEFT(A62,1)="0",MID(A62,2,99),A62) -> 2476.HK | AC62: 315 | AD62: 330 | AE62: 336.2 | AF62: 302 | AG62: 主板 | AH62: H股 | AI62: 主板 | AJ62: 0
A63: 1364.HK | B63: 古茗 | C63: 45700 | D63: =IFERROR(IF(ISNUMBER($C63),$C63-2,DATEVALUE($C63)-2),"") -> 45698 | E63: main_board_profitable | F63: =IF(AND(G63<>"",G63<>0),1,0) -> 0 | H63: 必需性消费(HS)-食物饮品(HS)-非酒精饮料(HS) | I63: 9.94 | J63: 8.68 | K63: 9.94 | L63: 2030471632 | M63: 15.03 | N63: 194.87 | O63: =IF(IFERROR(N63*1,0)>=15,1,0) -> 1 | P63: 2.09 | Q63: 高盛(亚洲)有限责任公司,UBS AG Hong Kong Branch,中国国际金融香港证券有限公司,香港上海汇丰银行有限公司,农银国际证券有限公司,中银国际亚洲有限公司,招银国际融资有限公司,富途证券国际(香港)有限公司 | R63: =IF(Q63="",0,LEN(Q63)-LEN(SUBSTITUTE(Q63,",",""))+1) -> 8 | U63: 19.65982 | V63: =IFERROR((SUMIFS($U$3:$U$392,$H$3:$H$392,$H63,$U$3:$U$392,">0")-IF(IFERROR($U63,0)>0,$U63,0))/(COUNTIFS($H$3:$H$392,$H63,$U$3:$U$392,">0")-IF(IFERROR($U63,0)>0,1,0)),"") -> 27.284799 | X63: 6 | Y63: =[1]!wss(AB63,"sec_status","cols=1;rows=1") -> L | AB63: =IF(LEFT(A63,1)="0",MID(A63,2,99),A63) -> 1364.HK | AC63: 9.3 | AD63: 10 | AE63: 10.4 | AF63: 8.93 | AG63: 主板 | AI63: 主板 | AJ63: 0
A64: 2507.HK | B64: 西锐 | C64: 45485 | D64: =IFERROR(IF(ISNUMBER($C64),$C64-2,DATEVALUE($C64)-2),"") -> 45483 | E64: main_board_profitable | F64: =IF(AND(G64<>"",G64<>0),1,0) -> 0 | H64: 工业(HS)-工业工程(HS)-航空航天与国防(HS) | I64: 27.5 | J64: 27.34 | K64: 28 | L64: 1513201250 | M64: 1.57 | N64: 1.56 | O64: =IF(IFERROR(N64*1,0)>=15,1,0) -> 0 | P64: 0.04 | Q64: 中国国际金融香港证券有限公司,农银国际证券有限公司,中航资信环球资产管理有限公司,中银国际亚洲有限公司,中国银河国际证券(香港)有限公司,招商证券(香港)有限公司,招银国际融资有限公司,富途证券国际(香港)有限公司,国信证券(香港)融资有限公司,华泰金融控股(香港)有限公司,工银国际证券有限公司,老虎证券(香港)环球有限公司 | R64: =IF(Q64="",0,LEN(Q64)-LEN(SUBSTITUTE(Q64,",",""))+1) -> 12 | U64: 14.123243 | V64: =IFERROR((SUMIFS($U$3:$U$392,$H$3:$H$392,$H64,$U$3:$U$392,">0")-IF(IFERROR($U64,0)>0,$U64,0))/(COUNTIFS($H$3:$H$392,$H64,$U$3:$U$392,">0")-IF(IFERROR($U64,0)>0,1,0)),"") | X64: 6 | Y64: =[1]!wss(AB64,"sec_status","cols=1;rows=1") -> L | AB64: =IF(LEFT(A64,1)="0",MID(A64,2,99),A64) -> 2507.HK | AC64: 27.5 | AD64: 27.5 | AE64: 27.5 | AF64: 26.05 | AG64: 主板 | AI64: 主板 | AJ64: 0
A65: 6693.HK | B65: 赤峰黄金 | C65: 45726 | D65: =IFERROR(IF(ISNUMBER($C65),$C65-2,DATEVALUE($C65)-2),"") -> 45724 | E65: a_plus_h | F65: =IF(AND(G65<>"",G65<>0),1,0) -> 1 | G65: 600988.SH | H65: 原材料业(HS)-黄金及贵金属(HS)-黄金及贵金属Ⅲ(HS) | I65: 13.72 | J65: 13.72 | K65: 15.83 | L65: 3244777256 | M65: 3.67 | N65: 9.53 | O65: =IF(IFERROR(N65*1,0)>=15,1,0) -> 0 | P65: 4.232 | Q65: 中信里昂证券有限公司,麦格理资本股份有限公司,中国国际金融香港证券有限公司,农银国际融资有限公司,农银国际证券有限公司,中银国际亚洲有限公司,工银国际证券有限公司,华泰金融控股(香港)有限公司,建银国际金融有限公司,第一上海证券有限公司,富途证券国际(香港)有限公司,利弗莫尔证券有限公司,申万宏源证券(香港)有限公司,南非标准银行有限公司,胜利证券有限公司,星河证券有限公司,老虎证券(香港)环球有限公司 | R65: =IF(Q65="",0,LEN(Q65)-LEN(SUBSTITUTE(Q65,",",""))+1) -> 17 | U65: 28.894658 | V65: =IFERROR((SUMIFS($U$3:$U$392,$H$3:$H$392,$H65,$U$3:$U$392,">0")-IF(IFERROR($U65,0)>0,$U65,0))/(COUNTIFS($H$3:$H$392,$H65,$U$3:$U$392,">0")-IF(IFERROR($U65,0)>0,1,0)),"") -> 31.040388 | X65: 6 | Y65: =[1]!wss(AB65,"sec_status","cols=1;rows=1") -> L | AB65: =IF(LEFT(A65,1)="0",MID(A65,2,99),A65) -> 6693.HK | AC65: 13.72 | AD65: 13.72 | AE65: 13.92 | AF65: 13.54 | AG65: 主板 | AH65: H股 | AI65: 主板 | AJ65: 0
A66: 3896.HK | B66: 金山云 | C66: 44925 | D66: =IFERROR(IF(ISNUMBER($C66),$C66-2,DATEVALUE($C66)-2),"") -> 44923 | E66: main_board_profitable | F66: =IF(AND(G66<>"",G66<>0),1,0) -> 0 | H66: 资讯科技业(HS)-软件服务(HS)-互联网服务及基础设施(HS) | L66: 0 | M66: 0 | N66: 0 | O66: =IF(IFERROR(N66*1,0)>=15,1,0) -> 0 | P66: 0 | Q66: 0 | R66: =IF(Q66="",0,LEN(Q66)-LEN(SUBSTITUTE(Q66,",",""))+1) -> 1 | U66: 0 | V66: =IFERROR((SUMIFS($U$3:$U$392,$H$3:$H$392,$H66,$U$3:$U$392,">0")-IF(IFERROR($U66,0)>0,$U66,0))/(COUNTIFS($H$3:$H$392,$H66,$U$3:$U$392,">0")-IF(IFERROR($U66,0)>0,1,0)),"") -> 59.107369 | Y66: =[1]!wss(AB66,"sec_status","cols=1;rows=1") -> L | AB66: =IF(LEFT(A66,1)="0",MID(A66,2,99),A66) -> 3896.HK | AC66: 2.1 | AD66: 1.99 | AE66: 2.15 | AF66: 1.99 | AG66: 主板 | AI66: 主板 | AJ66: 0
A67: 6979.HK | B67: 珍酒李渡 | C67: 45043 | D67: =IFERROR(IF(ISNUMBER($C67),$C67-2,DATEVALUE($C67)-2),"") -> 45041 | E67: main_board_profitable | F67: =IF(AND(G67<>"",G67<>0),1,0) -> 0 | H67: 必需性消费(HS)-食物饮品(HS)-酒精饮料(HS) | I67: 10.82 | J67: 10.78 | K67: 12.98 | L67: 5309371836 | M67: 3.9 | N67: 1.94 | O67: =IF(IFERROR(N67*1,0)>=15,1,0) -> 0 | P67: 0 | Q67: KKR Capital Markets Asia Limited,高盛(亚洲)有限责任公司,中信建投(国际)融资有限公司,中国国际金融香港证券有限公司 | R67: =IF(Q67="",0,LEN(Q67)-LEN(SUBSTITUTE(Q67,",",""))+1) -> 4 | U67: 30.701089 | V67: =IFERROR((SUMIFS($U$3:$U$392,$H$3:$H$392,$H67,$U$3:$U$392,">0")-IF(IFERROR($U67,0)>0,$U67,0))/(COUNTIFS($H$3:$H$392,$H67,$U$3:$U$392,">0")-IF(IFERROR($U67,0)>0,1,0)),"") | Y67: =[1]!wss(AB67,"sec_status","cols=1;rows=1") -> L | AB67: =IF(LEFT(A67,1)="0",MID(A67,2,99),A67) -> 6979.HK | AC67: 8.88 | AD67: 9 | AE67: 9.97 | AF67: 8.82 | AG67: 主板 | AI67: 主板 | AJ67: 0
A68: 2603.HK | B68: 吉宏股份 | C68: 45804 | D68: =IFERROR(IF(ISNUMBER($C68),$C68-2,DATEVALUE($C68)-2),"") -> 45802 | E68: a_plus_h | F68: =IF(AND(G68<>"",G68<>0),1,0) -> 1 | G68: 002803.SZ | H68: 非必需性消费(HS)-专业零售(HS)-线上零售商(HS) | I68: 7.68 | J68: 7.48 | K68: 10.68 | L68: 521548800 | M68: 1.62 | N68: 49.39 | O68: =IF(IFERROR(N68*1,0)>=15,1,0) -> 1 | P68: 0 | Q68: 中国国际金融香港证券有限公司,招银国际融资有限公司,中银国际亚洲有限公司,中国银河国际证券(香港)有限公司,工银国际证券有限公司,建银国际金融有限公司,华富建业证券有限公司,山高国际证券有限公司,复星国际证券有限公司,长桥证券(香港)有限公司,利弗莫尔证券有限公司,国金证券(香港)有限公司,华福国际证券有限公司 | R68: =IF(Q68="",0,LEN(Q68)-LEN(SUBSTITUTE(Q68,",",""))+1) -> 13 | U68: 17.695991 | V68: =IFERROR((SUMIFS($U$3:$U$392,$H$3:$H$392,$H68,$U$3:$U$392,">0")-IF(IFERROR($U68,0)>0,$U68,0))/(COUNTIFS($H$3:$H$392,$H68,$U$3:$U$392,">0")-IF(IFERROR($U68,0)>0,1,0)),"") -> 34.103898 | X68: 6 | Y68: =[1]!wss(AB68,"sec_status","cols=1;rows=1") -> L | AB68: =IF(LEFT(A68,1)="0",MID(A68,2,99),A68) -> 2603.HK | AC68: 10.68 | AD68: 11 | AE68: 12.46 | AF68: 10.2 | AG68: 主板 | AH68: H股 | AI68: 主板 | AJ68: 0
A69: 6680.HK | B69: 金力永磁 | C69: 44575 | D69: =IFERROR(IF(ISNUMBER($C69),$C69-2,DATEVALUE($C69)-2),"") -> 44573 | E69: a_plus_h | F69: =IF(AND(G69<>"",G69<>0),1,0) -> 1 | G69: 300748.SZ | H69: 原材料业(HS)-一般金属及矿石(HS)-其他金属及矿物(HS) | I69: 33.8 | L69: 4240750800 | M69: 1.57 | N69: 2.39 | O69: =IF(IFERROR(N69*1,0)>=15,1,0) -> 0 | P69: 0 | Q69: 中信里昂证券有限公司,法国巴黎证券(亚洲)有限公司,星展亚洲融资有限公司,富途证券国际(香港)有限公司,利弗莫尔证券有限公司 | R69: =IF(Q69="",0,LEN(Q69)-LEN(SUBSTITUTE(Q69,",",""))+1) -> 5 | U69: 97.318461 | V69: =IFERROR((SUMIFS($U$3:$U$392,$H$3:$H$392,$H69,$U$3:$U$392,">0")-IF(IFERROR($U69,0)>0,$U69,0))/(COUNTIFS($H$3:$H$392,$H69,$U$3:$U$392,">0")-IF(IFERROR($U69,0)>0,1,0)),"") -> 21.061255 | X69: 6 | Y69: =[1]!wss(AB69,"sec_status","cols=1;rows=1") -> L | AB69: =IF(LEFT(A69,1)="0",MID(A69,2,99),A69) -> 6680.HK | AC69: 28.2 | AD69: 30.8 | AE69: 30.8 | AF69: 28 | AG69: 主板 | AI69: 主板 | AJ69: 0
A70: 9890.HK | B70: 贪玩 | C70: 45197 | D70: =IFERROR(IF(ISNUMBER($C70),$C70-2,DATEVALUE($C70)-2),"") -> 45195 | E70: main_board_profitable | F70: =IF(AND(G70<>"",G70<>0),1,0) -> 0 | H70: 资讯科技业(HS)-软件服务(HS)-游戏软件(HS) | I70: 14 | J70: 11 | K70: 14 | L70: 265664000 | M70: 1.67 | N70: 104 | O70: =IF(IFERROR(N70*1,0)>=15,1,0) -> 1 | P70: 0 | Q70: 中国国际金融香港证券有限公司,中信建投(国际)融资有限公司,招商证券(香港)有限公司,中信里昂证券有限公司,招银国际融资有限公司,工银国际证券有限公司,老虎证券(香港)环球有限公司,富途证券国际(香港)有限公司 | R70: =IF(Q70="",0,LEN(Q70)-LEN(SUBSTITUTE(Q70,",",""))+1) -> 8 | U70: 13.001395 | V70: =IFERROR((SUMIFS($U$3:$U$392,$H$3:$H$392,$H70,$U$3:$U$392,">0")-IF(IFERROR($U70,0)>0,$U70,0))/(COUNTIFS($H$3:$H$392,$H70,$U$3:$U$392,">0")-IF(IFERROR($U70,0)>0,1,0)),"") -> 18.341099 | X70: 12 | Y70: =[1]!wss(AB70,"sec_status","cols=1;rows=1") -> L | AB70: =IF(LEFT(A70,1)="0",MID(A70,2,99),A70) -> 9890.HK | AC70: 14 | AD70: 13.78 | AE70: 14.5 | AF70: 13.48 | AG70: 主板 | AI70: 主板 | AJ70: 0
A71: 6887.HK | B71: 东阳光药 | C71: 45876 | D71: =IFERROR(IF(ISNUMBER($C71),$C71-2,DATEVALUE($C71)-2),"") -> 45874 | E71: main_board_profitable | F71: =IF(AND(G71<>"",G71<>0),1,0) -> 0 | H71: 医疗保健业(HS)-药品及生物科技(HS)-药品(HS) | L71: 0 | M71: 0 | N71: 0 | O71: =IF(IFERROR(N71*1,0)>=15,1,0) -> 0 | P71: 0 | Q71: 0 | R71: =IF(Q71="",0,LEN(Q71)-LEN(SUBSTITUTE(Q71,",",""))+1) -> 1 | U71: 0 | V71: =IFERROR((SUMIFS($U$3:$U$392,$H$3:$H$392,$H71,$U$3:$U$392,">0")-IF(IFERROR($U71,0)>0,$U71,0))/(COUNTIFS($H$3:$H$392,$H71,$U$3:$U$392,">0")-IF(IFERROR($U71,0)>0,1,0)),"") -> 89.319919 | Y71: =[1]!wss(AB71,"sec_status","cols=1;rows=1") -> L | AB71: =IF(LEFT(A71,1)="0",MID(A71,2,99),A71) -> 6887.HK | AC71: 59.9 | AD71: 57.5 | AE71: 62.3 | AF71: 57.5 | AG71: 主板 | AH71: H股 | AI71: 主板 | AJ71: 0
A72: 2510.HK | B72: 德翔海运 | C72: 45597 | D72: =IFERROR(IF(ISNUMBER($C72),$C72-2,DATEVALUE($C72)-2),"") -> 45595 | E72: main_board_profitable | F72: =IF(AND(G72<>"",G72<>0),1,0) -> 0 | H72: 工业(HS)-工用运输(HS)-航运及港口(HS) | I72: 4.18 | J72: 3.5 | K72: 4.5 | L72: 1107829580 | M72: 2.22 | N72: 12.09 | O72: =IF(IFERROR(N72*1,0)>=15,1,0) -> 0 | P72: 0.5854 | Q72: J.P. Morgan Securities (Far East) Limited,招商证券(香港)有限公司,富途证券国际(香港)有限公司,元大证券(香港)有限公司,利弗莫尔证券有限公司,J.P. Morgan Securities (Asia Pacific) Limited | R72: =IF(Q72="",0,LEN(Q72)-LEN(SUBSTITUTE(Q72,",",""))+1) -> 6 | U72: 42.636666 | V72: =IFERROR((SUMIFS($U$3:$U$392,$H$3:$H$392,$H72,$U$3:$U$392,">0")-IF(IFERROR($U72,0)>0,$U72,0))/(COUNTIFS($H$3:$H$392,$H72,$U$3:$U$392,">0")-IF(IFERROR($U72,0)>0,1,0)),"") -> 3.5371101 | X72: 6 | Y72: =[1]!wss(AB72,"sec_status","cols=1;rows=1") -> L | AB72: =IF(LEFT(A72,1)="0",MID(A72,2,99),A72) -> 2510.HK | AC72: 4.1 | AD72: 4.18 | AE72: 4.25 | AF72: 3.91 | AG72: 主板 | AI72: 主板 | AJ72: 0
A73: 2517.HK | B73: 锅圈 | C73: 45232 | D73: =IFERROR(IF(ISNUMBER($C73),$C73-2,DATEVALUE($C73)-2),"") -> 45230 | E73: main_board_profitable | F73: =IF(AND(G73<>"",G73<>0),1,0) -> 0 | H73: 必需性消费(HS)-食物饮品(HS)-包装食品(HS) | I73: 5.98 | J73: 5.98 | K73: 5.98 | L73: 462615192 | M73: 1.33 | N73: 4.34 | O73: =IF(IFERROR(N73*1,0)>=15,1,0) -> 0 | P73: 0.515 | Q73: 华泰金融控股(香港)有限公司,中国国际金融香港证券有限公司,招银国际融资有限公司,中州国际融资有限公司,广发证券(香港)经纪有限公司,光源资本(香港)金融有限公司 | R73: =IF(Q73="",0,LEN(Q73)-LEN(SUBSTITUTE(Q73,",",""))+1) -> 6 | U73: 63.63448 | V73: =IFERROR((SUMIFS($U$3:$U$392,$H$3:$H$392,$H73,$U$3:$U$392,">0")-IF(IFERROR($U73,0)>0,$U73,0))/(COUNTIFS($H$3:$H$392,$H73,$U$3:$U$392,">0")-IF(IFERROR($U73,0)>0,1,0)),"") -> 23.934231 | X73: 6 | Y73: =[1]!wss(AB73,"sec_status","cols=1;rows=1") -> L | AB73: =IF(LEFT(A73,1)="0",MID(A73,2,99),A73) -> 2517.HK | AC73: 5.98 | AD73: 5.98 | AE73: 6.22 | AF73: 5.98 | AG73: 主板 | AH73: H股 | AI73: 主板 | AJ73: 0
A74: 2076.HK | B74: BOSS直聘-W | C74: 44917 | D74: =IFERROR(IF(ISNUMBER($C74),$C74-2,DATEVALUE($C74)-2),"") -> 44915 | E74: 18a | F74: =IF(AND(G74<>"",G74<>0),1,0) -> 0 | H74: 非必需性消费(HS)-支援服务(HS)-其他支援服务(HS) | L74: 0 | M74: 0 | N74: 0 | O74: =IF(IFERROR(N74*1,0)>=15,1,0) -> 0 | P74: 0 | Q74: 0 | R74: =IF(Q74="",0,LEN(Q74)-LEN(SUBSTITUTE(Q74,",",""))+1) -> 1 | U74: 0 | V74: =IFERROR((SUMIFS($U$3:$U$392,$H$3:$H$392,$H74,$U$3:$U$392,">0")-IF(IFERROR($U74,0)>0,$U74,0))/(COUNTIFS($H$3:$H$392,$H74,$U$3:$U$392,">0")-IF(IFERROR($U74,0)>0,1,0)),"") -> 12.357005 | Y74: =[1]!wss(AB74,"sec_status","cols=1;rows=1") -> L | AB74: =IF(LEFT(A74,1)="0",MID(A74,2,99),A74) -> 2076.HK | AC74: 78.5 | AD74: 77.85 | AE74: 78.75 | AF74: 77.45 | AG74: 主板 | AI74: 主板 | AJ74: 0
A75: 3986.HK | B75: 兆易创新 | C75: 46035 | D75: =IFERROR(IF(ISNUMBER($C75),$C75-2,DATEVALUE($C75)-2),"") -> 46033 | E75: a_plus_h | F75: =IF(AND(G75<>"",G75<>0),1,0) -> 1 | G75: 603986.SH | H75: 资讯科技业(HS)-半导体(HS)-半导体Ⅲ(HS) | I75: 162 | J75: 132 | K75: 162 | L75: 5387002200 | M75: 18.52 | N75: 542.22 | O75: =IF(IFERROR(N75*1,0)>=15,1,0) -> 1 | P75: 6.97 | Q75: 中国国际金融香港证券有限公司,华泰金融控股(香港)有限公司 | R75: =IF(Q75="",0,LEN(Q75)-LEN(SUBSTITUTE(Q75,",",""))+1) -> 2 | U75: 94.805961 | V75: =IFERROR((SUMIFS($U$3:$U$392,$H$3:$H$392,$H75,$U$3:$U$392,">0")-IF(IFERROR($U75,0)>0,$U75,0))/(COUNTIFS($H$3:$H$392,$H75,$U$3:$U$392,">0")-IF(IFERROR($U75,0)>0,1,0)),"") -> 48.236295 | X75: 6 | Y75: =[1]!wss(AB75,"sec_status","cols=1;rows=1") -> L | AB75: =IF(LEFT(A75,1)="0",MID(A75,2,99),A75) -> 3986.HK | AC75: 222.8 | AD75: 235 | AE75: 248.8 | AF75: 220 | AG75: 主板 | AH75: H股 | AI75: 主板 | AJ75: 0
A76: 9981.HK | B76: 沃尔核材 | C76: 46066 | D76: =IFERROR(IF(ISNUMBER($C76),$C76-2,DATEVALUE($C76)-2),"") -> 46064 | E76: a_plus_h | F76: =IF(AND(G76<>"",G76<>0),1,0) -> 1 | G76: 002130.SZ | H76: 工业(HS)-工业工程(HS)-工业零件及器材(HS) | I76: 20.09 | K76: 20.09 | L76: 2812374992 | M76: 8.19 | N76: 569.58 | O76: =IF(IFERROR(N76*1,0)>=15,1,0) -> 1 | P76: 0 | Q76: 中信建投(国际)融资有限公司,招商证券(香港)有限公司,山证国际证券有限公司,星展亚洲融资有限公司,富途证券国际(香港)有限公司,老虎证券(香港)环球有限公司 | R76: =IF(Q76="",0,LEN(Q76)-LEN(SUBSTITUTE(Q76,",",""))+1) -> 6 | U76: 30.728187 | V76: =IFERROR((SUMIFS($U$3:$U$392,$H$3:$H$392,$H76,$U$3:$U$392,">0")-IF(IFERROR($U76,0)>0,$U76,0))/(COUNTIFS($H$3:$H$392,$H76,$U$3:$U$392,">0")-IF(IFERROR($U76,0)>0,1,0)),"") -> 87.789423 | X76: 6 | Y76: =[1]!wss(AB76,"sec_status","cols=1;rows=1") -> L | AB76: =IF(LEFT(A76,1)="0",MID(A76,2,99),A76) -> 9981.HK | AC76: 20.68 | AD76: 20.1 | AE76: 21.8 | AF76: 20.1 | AG76: 主板 | AH76: H股 | AI76: 主板 | AJ76: 0
A77: 2555.HK | B77: 茶百道 | C77: 45405 | D77: =IFERROR(IF(ISNUMBER($C77),$C77-2,DATEVALUE($C77)-2),"") -> 45403 | E77: main_board_profitable | F77: =IF(AND(G77<>"",G77<>0),1,0) -> 0 | H77: 必需性消费(HS)-食物饮品(HS)-非酒精饮料(HS) | I77: 17.5 | J77: 17.5 | K77: 17.5 | L77: 2585859500 | M77: 1.11 | N77: 0.5 | O77: =IF(IFERROR(N77*1,0)>=15,1,0) -> 0 | P77: 0 | Q77: 中国国际金融香港证券有限公司,花旗环球金融亚洲有限公司,Citigroup Global Markets Limited,招银国际融资有限公司,建银国际金融有限公司,申万宏源证券(香港)有限公司,招商证券(香港)有限公司,富途证券国际(香港)有限公司,老虎证券(香港)环球有限公司,复星国际证券有限公司,迈时资本有限公司,恒宇证券有限公司 | R77: =IF(Q77="",0,LEN(Q77)-LEN(SUBSTITUTE(Q77,",",""))+1) -> 12 | U77: 20.570008 | V77: =IFERROR((SUMIFS($U$3:$U$392,$H$3:$H$392,$H77,$U$3:$U$392,">0")-IF(IFERROR($U77,0)>0,$U77,0))/(COUNTIFS($H$3:$H$392,$H77,$U$3:$U$392,">0")-IF(IFERROR($U77,0)>0,1,0)),"") -> 27.183667 | Y77: =[1]!wss(AB77,"sec_status","cols=1;rows=1") -> L | AB77: =IF(LEFT(A77,1)="0",MID(A77,2,99),A77) -> 2555.HK | AC77: 12.8 | AD77: 15.74 | AE77: 15.74 | AF77: 10.8 | AG77: 主板 | AH77: H股 | AI77: 主板 | AJ77: 0
A78: 0638.HK | B78: 广和通 | C78: 45952 | D78: =IFERROR(IF(ISNUMBER($C78),$C78-2,DATEVALUE($C78)-2),"") -> 45950 | E78: a_plus_h | F78: =IF(AND(G78<>"",G78<>0),1,0) -> 1 | G78: 300638.SZ | H78: 工业(HS)-工业工程(HS)-电子零件(HS) | I78: 21.5 | J78: 19.88 | K78: 21.5 | L78: 2904224300 | M78: 9.16 | N78: 550.99 | O78: =IF(IFERROR(N78*1,0)>=15,1,0) -> 1 | P78: 0 | Q78: 富途证券国际(香港)有限公司,华升证券(国际)有限公司,农银国际证券有限公司,招银国际融资有限公司,国证国际证券(香港)有限公司,中信里昂证券有限公司 | R78: =IF(Q78="",0,LEN(Q78)-LEN(SUBSTITUTE(Q78,",",""))+1) -> 6 | U78: 26.842017 | V78: =IFERROR((SUMIFS($U$3:$U$392,$H$3:$H$392,$H78,$U$3:$U$392,">0")-IF(IFERROR($U78,0)>0,$U78,0))/(COUNTIFS($H$3:$H$392,$H78,$U$3:$U$392,">0")-IF(IFERROR($U78,0)>0,1,0)),"") -> 35.381745 | X78: 6 | Y78: =[1]!wss(AB78,"sec_status","cols=1;rows=1") | AB78: =IF(LEFT(A78,1)="0",MID(A78,2,99),A78) -> 638.HK | AC78: 18.98 | AD78: 21.5 | AE78: 21.6 | AF78: 18.89 | AG78: 主板 | AH78: H股 | AI78: 主板 | AJ78: 0
A79: 2482.HK | B79: 维天运通 | C79: 44994 | D79: =IFERROR(IF(ISNUMBER($C79),$C79-2,DATEVALUE($C79)-2),"") -> 44992 | E79: main_board_profitable | F79: =IF(AND(G79<>"",G79<>0),1,0) -> 0 | H79: 工业(HS)-工用运输(HS)-公路运输(HS) | I79: 2.9 | J79: 2.9 | K79: 3.5 | L79: 125311900 | M79: 1.43 | N79: 23.09 | O79: =IF(IFERROR(N79*1,0)>=15,1,0) -> 1 | P79: 0 | Q79: 海通国际证券有限公司,中信里昂证券有限公司,华盛资本证券有限公司,山高国际证券有限公司,佳富达证券有限公司 | R79: =IF(Q79="",0,LEN(Q79)-LEN(SUBSTITUTE(Q79,",",""))+1) -> 5 | U79: 65.129592 | V79: =IFERROR((SUMIFS($U$3:$U$392,$H$3:$H$392,$H79,$U$3:$U$392,">0")-IF(IFERROR($U79,0)>0,$U79,0))/(COUNTIFS($H$3:$H$392,$H79,$U$3:$U$392,">0")-IF(IFERROR($U79,0)>0,1,0)),"") | X79: 6 | Y79: =[1]!wss(AB79,"sec_status","cols=1;rows=1") -> L | AB79: =IF(LEFT(A79,1)="0",MID(A79,2,99),A79) -> 2482.HK | AC79: 2.84 | AD79: 2.81 | AE79: 2.9 | AF79: 2.7 | AG79: 主板 | AH79: H股 | AI79: 主板 | AJ79: 0
A80: 6168.HK | B80: 周六福 | C80: 45834 | D80: =IFERROR(IF(ISNUMBER($C80),$C80-2,DATEVALUE($C80)-2),"") -> 45832 | E80: main_board_profitable | F80: =IF(AND(G80<>"",G80<>0),1,0) -> 0 | H80: 非必需性消费(HS)-专业零售(HS)-其他零售商(HS) | I80: 24 | J80: 24 | K80: 24 | L80: 1485684000 | M80: 13.55 | N80: 711.11 | O80: =IF(IFERROR(N80*1,0)>=15,1,0) -> 1 | P80: 1.8727 | Q80: 中国国际金融香港证券有限公司,中信建投(国际)融资有限公司,招银国际融资有限公司,农银国际证券有限公司,交银国际证券有限公司,中国银河国际证券(香港)有限公司,兴证国际融资有限公司,复星国际证券有限公司,富途证券国际(香港)有限公司,老虎证券(香港)环球有限公司 | R80: =IF(Q80="",0,LEN(Q80)-LEN(SUBSTITUTE(Q80,",",""))+1) -> 10 | U80: 13.610448 | V80: =IFERROR((SUMIFS($U$3:$U$392,$H$3:$H$392,$H80,$U$3:$U$392,">0")-IF(IFERROR($U80,0)>0,$U80,0))/(COUNTIFS($H$3:$H$392,$H80,$U$3:$U$392,">0")-IF(IFERROR($U80,0)>0,1,0)),"") -> 12.887822 | X80: 6 | Y80: =[1]!wss(AB80,"sec_status","cols=1;rows=1") -> L | AB80: =IF(LEFT(A80,1)="0",MID(A80,2,99),A80) -> 6168.HK | AC80: 30 | AD80: 26.7 | AE80: 30 | AF80: 26.7 | AG80: 主板 | AH80: H股 | AI80: 主板 | AJ80: 0
A81: 2451.HK | B81: 绿源集团控股 | C81: 45211 | D81: =IFERROR(IF(ISNUMBER($C81),$C81-2,DATEVALUE($C81)-2),"") -> 45209 | E81: main_board_profitable | F81: =IF(AND(G81<>"",G81<>0),1,0) -> 0 | H81: 非必需性消费(HS)-汽车(HS)-摩托车及其他(HS) | I81: 7.37 | J81: 6 | K81: 8 | L81: 786135790 | M81: 0.9 | N81: 7.66 | O81: =IF(IFERROR(N81*1,0)>=15,1,0) -> 0 | P81: 0 | Q81: 中信建投(国际)融资有限公司,天风国际证券与期货有限公司,农银国际证券有限公司,国泰君安证券(香港)有限公司,招银国际融资有限公司,工银国际证券有限公司,浦银国际融资有限公司,大和资本市场香港有限公司,华盛证券,利弗莫尔证券有限公司,富途证券国际(香港)有限公司,软库中华金融服务有限公司,中国银河国际证券(香港)有限公司 | R81: =IF(Q81="",0,LEN(Q81)-LEN(SUBSTITUTE(Q81,",",""))+1) -> 13 | U81: 23.798352 | V81: =IFERROR((SUMIFS($U$3:$U$392,$H$3:$H$392,$H81,$U$3:$U$392,">0")-IF(IFERROR($U81,0)>0,$U81,0))/(COUNTIFS($H$3:$H$392,$H81,$U$3:$U$392,">0")-IF(IFERROR($U81,0)>0,1,0)),"") | X81: 6 | Y81: =[1]!wss(AB81,"sec_status","cols=1;rows=1") -> L | AB81: =IF(LEFT(A81,1)="0",MID(A81,2,99),A81) -> 2451.HK | AC81: 7.44 | AD81: 7.34 | AE81: 8.05 | AF81: 7.21 | AG81: 主板 | AI81: 主板 | AJ81: 0
A82: 9658.HK | B82: 特海国际 | C82: 44925 | D82: =IFERROR(IF(ISNUMBER($C82),$C82-2,DATEVALUE($C82)-2),"") -> 44923 | E82: main_board_profitable | F82: =IF(AND(G82<>"",G82<>0),1,0) -> 0 | H82: 非必需性消费(HS)-旅游及消闲设施(HS)-餐饮(HS) | L82: 0 | M82: 0 | N82: 0 | O82: =IF(IFERROR(N82*1,0)>=15,1,0) -> 0 | P82: 0 | Q82: 0 | R82: =IF(Q82="",0,LEN(Q82)-LEN(SUBSTITUTE(Q82,",",""))+1) -> 1 | U82: 0 | V82: =IFERROR((SUMIFS($U$3:$U$392,$H$3:$H$392,$H82,$U$3:$U$392,">0")-IF(IFERROR($U82,0)>0,$U82,0))/(COUNTIFS($H$3:$H$392,$H82,$U$3:$U$392,">0")-IF(IFERROR($U82,0)>0,1,0)),"") -> 35.389357 | Y82: =[1]!wss(AB82,"sec_status","cols=1;rows=1") -> L | AB82: =IF(LEFT(A82,1)="0",MID(A82,2,99),A82) -> 9658.HK | AC82: 9.94 | AD82: 7 | AE82: 14.5 | AF82: 7 | AG82: 主板 | AI82: 主板 | AJ82: 0
A83: 9985.HK | B83: 卫龙美味 | C83: 44910 | D83: =IFERROR(IF(ISNUMBER($C83),$C83-2,DATEVALUE($C83)-2),"") -> 44908 | E83: main_board_profitable | F83: =IF(AND(G83<>"",G83<>0),1,0) -> 0 | H83: 必需性消费(HS)-食物饮品(HS)-包装食品(HS) | I83: 10.56 | J83: 10.4 | K83: 11.4 | L83: 1017952320 | M83: 2.6 | N83: 15.3 | O83: =IF(IFERROR(N83*1,0)>=15,1,0) -> 1 | P83: 0 | Q83: UBS AG Hong Kong Branch,摩根士丹利亚洲有限公司,中国国际金融香港证券有限公司,法国巴黎证券(亚洲)有限公司,富途证券国际(香港)有限公司,建银国际金融有限公司 | R83: =IF(Q83="",0,LEN(Q83)-LEN(SUBSTITUTE(Q83,",",""))+1) -> 6 | U83: 24.553938 | V83: =IFERROR((SUMIFS($U$3:$U$392,$H$3:$H$392,$H83,$U$3:$U$392,">0")-IF(IFERROR($U83,0)>0,$U83,0))/(COUNTIFS($H$3:$H$392,$H83,$U$3:$U$392,">0")-IF(IFERROR($U83,0)>0,1,0)),"") -> 29.517166 | X83: 6 | Y83: =[1]!wss(AB83,"sec_status","cols=1;rows=1") -> L | AB83: =IF(LEFT(A83,1)="0",MID(A83,2,99),A83) -> 9985.HK | AC83: 10.02 | AD83: 10.2 | AE83: 10.78 | AF83: 10.02 | AG83: 主板 | AI83: 主板 | AJ83: 0
A84: 9676.HK | B84: 十月稻田 | C84: 45211 | D84: =IFERROR(IF(ISNUMBER($C84),$C84-2,DATEVALUE($C84)-2),"") -> 45209 | E84: main_board_profitable | F84: =IF(AND(G84<>"",G84<>0),1,0) -> 0 | H84: 必需性消费(HS)-农业产品(HS)-农产品(HS) | I84: 15.36 | J84: 13 | K84: 15.8 | L84: 820339200 | M84: 1.26 | N84: 1.31 | O84: =IF(IFERROR(N84*1,0)>=15,1,0) -> 0 | P84: 0 | Q84: 中国国际金融香港证券有限公司,中信建投(国际)融资有限公司,摩根士丹利亚洲有限公司,老虎证券(香港)环球有限公司 | R84: =IF(Q84="",0,LEN(Q84)-LEN(SUBSTITUTE(Q84,",",""))+1) -> 4 | U84: -25.975253 | V84: =IFERROR((SUMIFS($U$3:$U$392,$H$3:$H$392,$H84,$U$3:$U$392,">0")-IF(IFERROR($U84,0)>0,$U84,0))/(COUNTIFS($H$3:$H$392,$H84,$U$3:$U$392,">0")-IF(IFERROR($U84,0)>0,1,0)),"") -> 9.9402559 | X84: 6 | Y84: =[1]!wss(AB84,"sec_status","cols=1;rows=1") -> L | AB84: =IF(LEFT(A84,1)="0",MID(A84,2,99),A84) -> 9676.HK | AC84: 18.84 | AD84: 16.6 | AE84: 19.94 | AF84: 16.6 | AG84: 主板 | AH84: H股 | AI84: 主板 | AJ84: 0
A85: 9886.HK | B85: 叮当健康 | C85: 44818 | D85: =IFERROR(IF(ISNUMBER($C85),$C85-2,DATEVALUE($C85)-2),"") -> 44816 | E85: main_board_profitable | F85: =IF(AND(G85<>"",G85<>0),1,0) -> 0 | H85: 医疗保健业(HS)-药品及生物科技(HS)-药品分销(HS) | I85: 12 | L85: 402444000 | M85: 1.7 | N85: 7.2 | O85: =IF(IFERROR(N85*1,0)>=15,1,0) -> 0 | P85: 0 | Q85: 元库证券有限公司,富途证券国际(香港)有限公司,招银国际融资有限公司,中国国际金融香港证券有限公司 | R85: =IF(Q85="",0,LEN(Q85)-LEN(SUBSTITUTE(Q85,",",""))+1) -> 4 | U85: -8.3404576 | V85: =IFERROR((SUMIFS($U$3:$U$392,$H$3:$H$392,$H85,$U$3:$U$392,">0")-IF(IFERROR($U85,0)>0,$U85,0))/(COUNTIFS($H$3:$H$392,$H85,$U$3:$U$392,">0")-IF(IFERROR($U85,0)>0,1,0)),"") | X85: 6 | Y85: =[1]!wss(AB85,"sec_status","cols=1;rows=1") -> L | AB85: =IF(LEFT(A85,1)="0",MID(A85,2,99),A85) -> 9886.HK | AC85: 12 | AD85: 12.34 | AE85: 12.34 | AF85: 12 | AG85: 主板 | AI85: 主板 | AJ85: 0
A86: 2610.HK | B86: 南山铝业国际 | C86: 45741 | D86: =IFERROR(IF(ISNUMBER($C86),$C86-2,DATEVALUE($C86)-2),"") -> 45739 | E86: main_board_profitable | F86: =IF(AND(G86<>"",G86<>0),1,0) -> 0 | H86: 原材料业(HS)-一般金属及矿石(HS)-铝(HS) | I86: 26.6 | J86: 26.6 | K86: 31.5 | L86: 2378976320 | M86: 1.67 | N86: 3.89 | O86: =IF(IFERROR(N86*1,0)>=15,1,0) -> 0 | P86: 0.3096 | Q86: 华泰金融控股(香港)有限公司,招银国际融资有限公司,中国银河国际证券(香港)有限公司,中国国际金融香港证券有限公司,中信里昂证券有限公司,大和资本市场香港有限公司,星展亚洲融资有限公司,工银国际证券有限公司,大华继显(香港)有限公司,中航资信环球资产管理有限公司,中银国际亚洲有限公司,富途证券国际(香港)有限公司,辉立证券(香港)有限公司,老虎证券(香港)环球有限公司,中泰国际证券有限公司,申万宏源证券(香港)有限公司 | R86: =IF(Q86="",0,LEN(Q86)-LEN(SUBSTITUTE(Q86,",",""))+1) -> 16 | U86: 5.0165752 | V86: =IFERROR((SUMIFS($U$3:$U$392,$H$3:$H$392,$H86,$U$3:$U$392,">0")-IF(IFERROR($U86,0)>0,$U86,0))/(COUNTIFS($H$3:$H$392,$H86,$U$3:$U$392,">0")-IF(IFERROR($U86,0)>0,1,0)),"") -> 9.8988872 | X86: 6 | Y86: =[1]!wss(AB86,"sec_status","cols=1;rows=1") -> L | AB86: =IF(LEFT(A86,1)="0",MID(A86,2,99),A86) -> 2610.HK | AC86: 25.25 | AD86: 26.6 | AE86: 26.9 | AF86: 25.25 | AG86: 主板 | AI86: 主板 | AJ86: 0
A87: 9879.HK | B87: 米高集团 | C87: 45372 | D87: =IFERROR(IF(ISNUMBER($C87),$C87-2,DATEVALUE($C87)-2),"") -> 45370 | E87: main_board_profitable | F87: =IF(AND(G87<>"",G87<>0),1,0) -> 0 | H87: 原材料业(HS)-原材料(HS)-化肥及农用化合物(HS) | I87: 4.08 | J87: 3.3 | K87: 4.3 | L87: 954475200 | M87: 1.28 | N87: 9.79 | O87: =IF(IFERROR(N87*1,0)>=15,1,0) -> 0 | P87: 0.3574 | Q87: 广发证券(香港)经纪有限公司,招银国际融资有限公司,安信国际证券(香港)有限公司,招商证券(香港)有限公司,农银国际证券有限公司,中国光大证券(香港)有限公司,东吴证券国际经纪有限公司,申万宏源证券(香港)有限公司,东方证券(香港)有限公司,利弗莫尔证券有限公司 | R87: =IF(Q87="",0,LEN(Q87)-LEN(SUBSTITUTE(Q87,",",""))+1) -> 10 | U87: 7.9353069 | V87: =IFERROR((SUMIFS($U$3:$U$392,$H$3:$H$392,$H87,$U$3:$U$392,">0")-IF(IFERROR($U87,0)>0,$U87,0))/(COUNTIFS($H$3:$H$392,$H87,$U$3:$U$392,">0")-IF(IFERROR($U87,0)>0,1,0)),"") | X87: 12 | Y87: =[1]!wss(AB87,"sec_status","cols=1;rows=1") -> L | AB87: =IF(LEFT(A87,1)="0",MID(A87,2,99),A87) -> 9879.HK | AC87: 4.09 | AD87: 4.38 | AE87: 4.58 | AF87: 4.08 | AG87: 主板 | AI87: 主板 | AJ87: 0
A88: 0314.HK | B88: 思派健康 | C88: 44918 | D88: =IFERROR(IF(ISNUMBER($C88),$C88-2,DATEVALUE($C88)-2),"") -> 44916 | E88: main_board_profitable | F88: =IF(AND(G88<>"",G88<>0),1,0) -> 0 | H88: 医疗保健业(HS)-药品及生物科技(HS)-药品分销(HS) | I88: 18.6 | J88: 18.6 | K88: 18.6 | L88: 184500840 | M88: 1.41 | N88: 8.27 | O88: =IF(IFERROR(N88*1,0)>=15,1,0) -> 0 | P88: 0 | Q88: 摩根士丹利亚洲有限公司,海通国际证券有限公司,富途证券国际(香港)有限公司,迈时资本有限公司,一盈证券有限公司 | R88: =IF(Q88="",0,LEN(Q88)-LEN(SUBSTITUTE(Q88,",",""))+1) -> 5 | U88: -3.1021896 | V88: =IFERROR((SUMIFS($U$3:$U$392,$H$3:$H$392,$H88,$U$3:$U$392,">0")-IF(IFERROR($U88,0)>0,$U88,0))/(COUNTIFS($H$3:$H$392,$H88,$U$3:$U$392,">0")-IF(IFERROR($U88,0)>0,1,0)),"") | Y88: =[1]!wss(AB88,"sec_status","cols=1;rows=1") | AB88: =IF(LEFT(A88,1)="0",MID(A88,2,99),A88) -> 314.HK | AC88: 25 | AD88: 23.7 | AE88: 26.35 | AF88: 21.75 | AG88: 主板 | AI88: 主板 | AJ88: 0
A89: 2425.HK | B89: 澳亚集团 | C89: 44925 | D89: =IFERROR(IF(ISNUMBER($C89),$C89-2,DATEVALUE($C89)-2),"") -> 44923 | E89: main_board_profitable | F89: =IF(AND(G89<>"",G89<>0),1,0) -> 0 | H89: 必需性消费(HS)-食物饮品(HS)-乳制品(HS) | I89: 6.4 | J89: 5.79 | K89: 7 | L89: 199974400 | M89: 1.16 | N89: 2.08 | O89: =IF(IFERROR(N89*1,0)>=15,1,0) -> 0 | P89: 0.0388 | Q89: 大和资本市场香港有限公司,农银国际证券有限公司,交银国际证券有限公司,富途证券国际(香港)有限公司,中国国际金融香港证券有限公司,星展亚洲融资有限公司,元库证券有限公司 | R89: =IF(Q89="",0,LEN(Q89)-LEN(SUBSTITUTE(Q89,",",""))+1) -> 7 | U89: 5.4927135 | V89: =IFERROR((SUMIFS($U$3:$U$392,$H$3:$H$392,$H89,$U$3:$U$392,">0")-IF(IFERROR($U89,0)>0,$U89,0))/(COUNTIFS($H$3:$H$392,$H89,$U$3:$U$392,">0")-IF(IFERROR($U89,0)>0,1,0)),"") | X89: 6 | Y89: =[1]!wss(AB89,"sec_status","cols=1;rows=1") -> L | AB89: =IF(LEFT(A89,1)="0",MID(A89,2,99),A89) -> 2425.HK | AC89: 6.37 | AD89: 6.1 | AE89: 6.38 | AF89: 5.42 | AG89: 主板 | AI89: 主板 | AJ89: 0
A90: 2715.HK | B90: 埃斯顿 | C90: 46090 | D90: =IFERROR(IF(ISNUMBER($C90),$C90-2,DATEVALUE($C90)-2),"") -> 46088 | E90: a_plus_h | F90: =IF(AND(G90<>"",G90<>0),1,0) -> 1 | G90: 002747.SZ | H90: 工业(HS)-工业工程(HS)-重型机械(HS) | I90: 15.36 | J90: 15.36 | K90: 17 | L90: 1486540800 | M90: 3.34 | N90: 19.67 | O90: =IF(IFERROR(N90*1,0)>=15,1,0) -> 1 | P90: 0 | Q90: TradeGo Markets Limited,富途证券国际(香港)有限公司,工银国际证券有限公司,广发证券(香港)经纪有限公司,华安证券(香港)经纪有限公司,华泰金融控股(香港)有限公司,交银国际证券有限公司,利弗莫尔证券有限公司,农银国际证券有限公司,招银国际融资有限公司,中银国际亚洲有限公司 | R90: =IF(Q90="",0,LEN(Q90)-LEN(SUBSTITUTE(Q90,",",""))+1) -> 11 | U90: -16.975519 | V90: =IFERROR((SUMIFS($U$3:$U$392,$H$3:$H$392,$H90,$U$3:$U$392,">0")-IF(IFERROR($U90,0)>0,$U90,0))/(COUNTIFS($H$3:$H$392,$H90,$U$3:$U$392,">0")-IF(IFERROR($U90,0)>0,1,0)),"") -> 24.712565 | X90: 6 | Y90: =[1]!wss(AB90,"sec_status","cols=1;rows=1") -> L | AB90: =IF(LEFT(A90,1)="0",MID(A90,2,99),A90) -> 2715.HK | AC90: 12.9 | AD90: 15.36 | AE90: 15.36 | AF90: 12.5 | AG90: 主板 | AH90: H股 | AI90: 主板 | AJ90: 0
A91: 0999.HK | B91: 小菜园 | C91: 45646 | D91: =IFERROR(IF(ISNUMBER($C91),$C91-2,DATEVALUE($C91)-2),"") -> 45644 | E91: main_board_profitable | F91: =IF(AND(G91<>"",G91<>0),1,0) -> 0 | H91: 非必需性消费(HS)-旅游及消闲设施(HS)-餐饮(HS) | I91: 8.5 | J91: 8.5 | K91: 8.5 | L91: 860036800 | M91: 1.29 | N91: 1.44 | O91: =IF(IFERROR(N91*1,0)>=15,1,0) -> 0 | P91: 0 | Q91: UBS AG Hong Kong Branch,国元证券经纪(香港)有限公司,招银国际融资有限公司,农银国际证券有限公司,工银国际证券有限公司,富途证券国际(香港)有限公司,华泰金融控股(香港)有限公司,TradeGo Markets Limited | R91: =IF(Q91="",0,LEN(Q91)-LEN(SUBSTITUTE(Q91,",",""))+1) -> 8 | U91: 17.03302 | V91: =IFERROR((SUMIFS($U$3:$U$392,$H$3:$H$392,$H91,$U$3:$U$392,">0")-IF(IFERROR($U91,0)>0,$U91,0))/(COUNTIFS($H$3:$H$392,$H91,$U$3:$U$392,">0")-IF(IFERROR($U91,0)>0,1,0)),"") -> 44.567526 | Y91: =[1]!wss(AB91,"sec_status","cols=1;rows=1") | AB91: =IF(LEFT(A91,1)="0",MID(A91,2,99),A91) -> 999.HK | AC91: 9.66 | AD91: 9 | AE91: 9.7 | AF91: 8.5 | AG91: 主板 | AI91: 主板 | AJ91: 0
A92: 6960.HK | B92: 双登股份 | C92: 45895 | D92: =IFERROR(IF(ISNUMBER($C92),$C92-2,DATEVALUE($C92)-2),"") -> 45893 | E92: main_board_profitable | F92: =IF(AND(G92<>"",G92<>0),1,0) -> 0 | H92: 工业(HS)-工业工程(HS)-能源储存装置(HS) | I92: 14.51 | J92: 14.51 | K92: 14.51 | L92: 977110655 | M92: 18.75 | N92: 3876.25 | O92: =IF(IFERROR(N92*1,0)>=15,1,0) -> 1 | P92: 1.2158 | Q92: 中国国际金融香港证券有限公司,华泰金融控股(香港)有限公司,建银国际金融有限公司,工银国际证券有限公司,农银国际证券有限公司,利弗莫尔证券有限公司,中国银河国际证券(香港)有限公司 | R92: =IF(Q92="",0,LEN(Q92)-LEN(SUBSTITUTE(Q92,",",""))+1) -> 7 | U92: 15.851495 | V92: =IFERROR((SUMIFS($U$3:$U$392,$H$3:$H$392,$H92,$U$3:$U$392,">0")-IF(IFERROR($U92,0)>0,$U92,0))/(COUNTIFS($H$3:$H$392,$H92,$U$3:$U$392,">0")-IF(IFERROR($U92,0)>0,1,0)),"") -> 168.85619 | X92: 12 | Y92: =[1]!wss(AB92,"sec_status","cols=1;rows=1") -> L | AB92: =IF(LEFT(A92,1)="0",MID(A92,2,99),A92) -> 6960.HK | AC92: 19.05 | AD92: 22.5 | AE92: 23.18 | AF92: 18.86 | AG92: 主板 | AH92: H股 | AI92: 主板 | AJ92: 0
A93: 6682.HK | B93: 范式智能 | C93: 45197 | D93: =IFERROR(IF(ISNUMBER($C93),$C93-2,DATEVALUE($C93)-2),"") -> 45195 | E93: main_board_profitable | F93: =IF(AND(G93<>"",G93<>0),1,0) -> 0 | H93: 资讯科技业(HS)-软件服务(HS)-数码解决方案服务(HS) | I93: 55.6 | J93: 55.6 | K93: 61.16 | L93: 1122797520 | M93: 1.57 | N93: 11.4 | O93: =IF(IFERROR(N93*1,0)>=15,1,0) -> 0 | P93: 0.965 | Q93: 中国国际金融香港证券有限公司,建银国际金融有限公司,招银国际融资有限公司,招商证券(香港)有限公司,东方证券(香港)有限公司,浦银国际融资有限公司,复星国际证券有限公司,老虎证券(香港)环球有限公司,华盛资本证券有限公司,富明证券有限公司 | R93: =IF(Q93="",0,LEN(Q93)-LEN(SUBSTITUTE(Q93,",",""))+1) -> 10 | U93: -14.011785 | V93: =IFERROR((SUMIFS($U$3:$U$392,$H$3:$H$392,$H93,$U$3:$U$392,">0")-IF(IFERROR($U93,0)>0,$U93,0))/(COUNTIFS($H$3:$H$392,$H93,$U$3:$U$392,">0")-IF(IFERROR($U93,0)>0,1,0)),"") -> 472.70515 | X93: 6 | Y93: =[1]!wss(AB93,"sec_status","cols=1;rows=1") -> L | AB93: =IF(LEFT(A93,1)="0",MID(A93,2,99),A93) -> 6682.HK | AC93: 58.5 | AD93: 63.1 | AE93: 65 | AF93: 56.45 | AG93: 主板 | AH93: H股 | AI93: 主板 | AJ93: 0
A94: 2390.HK | B94: 知乎-W | C94: 44673 | D94: =IFERROR(IF(ISNUMBER($C94),$C94-2,DATEVALUE($C94)-2),"") -> 44671 | E94: 18a | F94: =IF(AND(G94<>"",G94<>0),1,0) -> 0 | H94: 非必需性消费(HS)-媒体及娱乐(HS)-广告及宣传(HS) | I94: 32.06 | K94: 51.8 | L94: 833560000 | M94: 4.37 | N94: 1 | O94: =IF(IFERROR(N94*1,0)>=15,1,0) -> 0 | P94: 0 | Q94: 瑞士信贷(香港)有限公司,J.P. Morgan Securities (Asia Pacific) Limited,J.P. Morgan Securities LLC,中国国际金融香港证券有限公司,招银国际融资有限公司,建银国际金融有限公司,海通国际证券有限公司 | R94: =IF(Q94="",0,LEN(Q94)-LEN(SUBSTITUTE(Q94,",",""))+1) -> 7 | U94: -6.5802735 | V94: =IFERROR((SUMIFS($U$3:$U$392,$H$3:$H$392,$H94,$U$3:$U$392,">0")-IF(IFERROR($U94,0)>0,$U94,0))/(COUNTIFS($H$3:$H$392,$H94,$U$3:$U$392,">0")-IF(IFERROR($U94,0)>0,1,0)),"") -> 60.573278 | Y94: =[1]!wss(AB94,"sec_status","cols=1;rows=1") -> L | AB94: =IF(LEFT(A94,1)="0",MID(A94,2,99),A94) -> 2390.HK | AC94: 24.5 | AD94: 24.95 | AE94: 26.1 | AF94: 23.45 | AG94: 主板 | AI94: 主板 | AJ94: 0
A95: 2145.HK | B95: 上美股份 | C95: 44917 | D95: =IFERROR(IF(ISNUMBER($C95),$C95-2,DATEVALUE($C95)-2),"") -> 44915 | E95: main_board_profitable | F95: =IF(AND(G95<>"",G95<>0),1,0) -> 0 | H95: 医疗保健业(HS)-其他医疗保健(HS)-护肤与化妆品(HS) | I95: 25.2 | J95: 25.2 | K95: 29.8 | L95: 956539080 | M95: 1.42 | N95: 0.48 | O95: =IF(IFERROR(N95*1,0)>=15,1,0) -> 0 | P95: 0.246 | Q95: 中国国际金融香港证券有限公司,J.P. Morgan Securities plc,J.P. Morgan Securities (Asia Pacific) Limited,中银国际亚洲有限公司,华盛资本证券有限公司,富途证券国际(香港)有限公司,老虎证券(香港)环球有限公司,申万宏源证券(香港)有限公司,中泰国际证券有限公司,中信里昂证券有限公司 | R95: =IF(Q95="",0,LEN(Q95)-LEN(SUBSTITUTE(Q95,",",""))+1) -> 10 | U95: 24.134098 | V95: =IFERROR((SUMIFS($U$3:$U$392,$H$3:$H$392,$H95,$U$3:$U$392,">0")-IF(IFERROR($U95,0)>0,$U95,0))/(COUNTIFS($H$3:$H$392,$H95,$U$3:$U$392,">0")-IF(IFERROR($U95,0)>0,1,0)),"") -> 28.188534 | Y95: =[1]!wss(AB95,"sec_status","cols=1;rows=1") -> L | AB95: =IF(LEFT(A95,1)="0",MID(A95,2,99),A95) -> 2145.HK | AC95: 25.2 | AD95: 25.2 | AE95: 26 | AF95: 24.2 | AG95: 主板 | AH95: H股 | AI95: 主板 | AJ95: 0
A96: 3677.HK | B96: 正力新能 | C96: 45761 | D96: =IFERROR(IF(ISNUMBER($C96),$C96-2,DATEVALUE($C96)-2),"") -> 45759 | E96: main_board_profitable | F96: =IF(AND(G96<>"",G96<>0),1,0) -> 0 | H96: 工业(HS)-工业工程(HS)-能源储存装置(HS) | I96: 8.27 | J96: 8.27 | K96: 8.27 | L96: 1005000999 | M96: 1.13 | N96: 3.51 | O96: =IF(IFERROR(N96*1,0)>=15,1,0) -> 0 | P96: 0 | Q96: 中国国际金融香港证券有限公司,招银国际融资有限公司,建银国际金融有限公司,兴证国际融资有限公司,华福国际证券有限公司,工银国际证券有限公司,光银国际资本有限公司,中银国际亚洲有限公司,农银国际证券有限公司,百惠证券有限公司,富途证券国际(香港)有限公司,老虎证券(香港)环球有限公司,利弗莫尔证券有限公司 | R96: =IF(Q96="",0,LEN(Q96)-LEN(SUBSTITUTE(Q96,",",""))+1) -> 13 | U96: 211.07713 | V96: =IFERROR((SUMIFS($U$3:$U$392,$H$3:$H$392,$H96,$U$3:$U$392,">0")-IF(IFERROR($U96,0)>0,$U96,0))/(COUNTIFS($H$3:$H$392,$H96,$U$3:$U$392,">0")-IF(IFERROR($U96,0)>0,1,0)),"") -> 129.81106 | X96: 6 | Y96: =[1]!wss(AB96,"sec_status","cols=1;rows=1") -> L | AB96: =IF(LEFT(A96,1)="0",MID(A96,2,99),A96) -> 3677.HK | AC96: 8.39 | AD96: 8.46 | AE96: 8.46 | AF96: 8.33 | AG96: 主板 | AH96: H股 | AI96: 主板 | AJ96: 0
A97: 9955.HK | B97: 智云健康 | C97: 44748 | D97: =IFERROR(IF(ISNUMBER($C97),$C97-2,DATEVALUE($C97)-2),"") -> 44746 | E97: main_board_profitable | F97: =IF(AND(G97<>"",G97<>0),1,0) -> 0 | H97: 医疗保健业(HS)-其他医疗保健(HS)-医疗设备及用品(HS) | I97: 30.5 | L97: 579500000 | M97: 2.15 | N97: 7.89 | O97: =IF(IFERROR(N97*1,0)>=15,1,0) -> 0 | P97: 0 | Q97: 摩根士丹利亚洲有限公司,摩根大通证券(亚太)有限公司,摩根大通证券公开股份有限公司,中国国际金融香港证券有限公司,招银国际融资有限公司,华盛资本证券有限公司 | R97: =IF(Q97="",0,LEN(Q97)-LEN(SUBSTITUTE(Q97,",",""))+1) -> 6 | U97: -3.5368839 | V97: =IFERROR((SUMIFS($U$3:$U$392,$H$3:$H$392,$H97,$U$3:$U$392,">0")-IF(IFERROR($U97,0)>0,$U97,0))/(COUNTIFS($H$3:$H$392,$H97,$U$3:$U$392,">0")-IF(IFERROR($U97,0)>0,1,0)),"") -> 140.51039 | X97: 6 | Y97: =[1]!wss(AB97,"sec_status","cols=1;rows=1") -> L | AB97: =IF(LEFT(A97,1)="0",MID(A97,2,99),A97) -> 9955.HK | AC97: 28.2 | AD97: 30.5 | AE97: 30.7 | AF97: 24.35 | AG97: 主板 | AI97: 主板 | AJ97: 0
A98: 6831.HK | B98: 绿茶集团 | C98: 45793 | D98: =IFERROR(IF(ISNUMBER($C98),$C98-2,DATEVALUE($C98)-2),"") -> 45791 | E98: main_board_profitable | F98: =IF(AND(G98<>"",G98<>0),1,0) -> 0 | H98: 非必需性消费(HS)-旅游及消闲设施(HS)-餐饮(HS) | I98: 7.19 | J98: 7.19 | K98: 7.19 | L98: 847376012 | M98: 7.2 | N98: 317.54 | O98: =IF(IFERROR(N98*1,0)>=15,1,0) -> 1 | P98: 0 | Q98: 花旗环球金融亚洲有限公司,Citigroup Global Markets Limited,招银国际融资有限公司,广发证券(香港)经纪有限公司,国元证券经纪(香港)有限公司,农银国际融资有限公司,农银国际证券有限公司,时富证券有限公司,中国银河国际证券(香港)有限公司,民银证券有限公司,第一上海证券有限公司,富途证券国际(香港)有限公司,长桥证券(香港)有限公司,万基证券有限公司,东方证券(香港)有限公司,百惠证券有限公司,国证国际证券(香港)有限公司,中泰国际证券有限公司 | R98: =IF(Q98="",0,LEN(Q98)-LEN(SUBSTITUTE(Q98,",",""))+1) -> 18 | U98: 12.805362 | V98: =IFERROR((SUMIFS($U$3:$U$392,$H$3:$H$392,$H98,$U$3:$U$392,">0")-IF(IFERROR($U98,0)>0,$U98,0))/(COUNTIFS($H$3:$H$392,$H98,$U$3:$U$392,">0")-IF(IFERROR($U98,0)>0,1,0)),"") -> 46.681354 | X98: 6 | Y98: =[1]!wss(AB98,"sec_status","cols=1;rows=1") -> L | AB98: =IF(LEFT(A98,1)="0",MID(A98,2,99),A98) -> 6831.HK | AC98: 6.29 | AD98: 7.19 | AE98: 7.2 | AF98: 6.29 | AG98: 主板 | AI98: 主板 | AJ98: 0
A99: 2367.HK | B99: 巨子生物 | C99: 44869 | D99: =IFERROR(IF(ISNUMBER($C99),$C99-2,DATEVALUE($C99)-2),"") -> 44867 | E99: main_board_profitable | F99: =IF(AND(G99<>"",G99<>0),1,0) -> 0 | H99: 医疗保健业(HS)-其他医疗保健(HS)-护肤与化妆品(HS) | I99: 24.3 | J99: 24.3 | K99: 27.7 | L99: 631800000 | M99: 4.22 | N99: 2.08 | O99: =IF(IFERROR(N99*1,0)>=15,1,0) -> 0 | P99: 0.779 | Q99: 中国国际金融香港证券有限公司,高盛(亚洲)有限责任公司,华泰金融控股(香港)有限公司,广发证券(香港)经纪有限公司,富途证券国际(香港)有限公司,元库证券有限公司 | R99: =IF(Q99="",0,LEN(Q99)-LEN(SUBSTITUTE(Q99,",",""))+1) -> 6 | U99: 23.789645 | V99: =IFERROR((SUMIFS($U$3:$U$392,$H$3:$H$392,$H99,$U$3:$U$392,">0")-IF(IFERROR($U99,0)>0,$U99,0))/(COUNTIFS($H$3:$H$392,$H99,$U$3:$U$392,">0")-IF(IFERROR($U99,0)>0,1,0)),"") -> 28.274647 | Y99: =[1]!wss(AB99,"sec_status","cols=1;rows=1") -> L | AB99: =IF(LEFT(A99,1)="0",MID(A99,2,99),A99) -> 2367.HK | AC99: 26.7 | AD99: 26 | AE99: 31.1 | AF99: 26 | AG99: 主板 | AI99: 主板 | AJ99: 0
A100: 2589.HK | B100: 沪上阿姨 | C100: 45785 | D100: =IFERROR(IF(ISNUMBER($C100),$C100-2,DATEVALUE($C100)-2),"") -> 45783 | E100: main_board_profitable | F100: =IF(AND(G100<>"",G100<>0),1,0) -> 0 | H100: 必需性消费(HS)-食物饮品(HS)-非酒精饮料(HS) | I100: 113.12 | J100: 95.57 | K100: 113.12 | L100: 3.1368402e+08 | M100: 2.57 | N100: 3616.83 | O100: =IF(IFERROR(N100*1,0)>=15,1,0) -> 1 | P100: 0.389 | Q100: 东方证券(香港)有限公司,中信里昂证券有限公司,海通国际证券有限公司,工银国际证券有限公司,招商证券(香港)有限公司,民银证券有限公司,万基证券有限公司,东吴证券国际经纪有限公司,老虎证券(香港)环球有限公司 | R100: =IF(Q100="",0,LEN(Q100)-LEN(SUBSTITUTE(Q100,",",""))+1) -> 9 | U100: 33.388499 | V100: =IFERROR((SUMIFS($U$3:$U$392,$H$3:$H$392,$H100,$U$3:$U$392,">0")-IF(IFERROR($U100,0)>0,$U100,0))/(COUNTIFS($H$3:$H$392,$H100,$U$3:$U$392,">0")-IF(IFERROR($U100,0)>0,1,0)),"") -> 25.75939 | X100: 6 | Y100: =[1]!wss(AB100,"sec_status","cols=1;rows=1") -> L | AB100: =IF(LEFT(A100,1)="0",MID(A100,2,99),A100) -> 2589.HK | AC100: 158.4 | AD100: 190.6 | AE100: 197.6 | AF100: 152 | AG100: 主板 | AH100: H股 | AI100: 主板 | AJ100: 0
...

Sheet 02_ipo_cornerstones
A1: stock_code | B1: ipo_listing_date | C1: cornerstone_raw_name | D1: cornerstone_full_name | E1: ticket_amount_value | F1: ticket_amount_ccy | G1: lockup_months | H1: affiliation_disclosed | I1: unlock_date | J1: controlling_shareholder | K1: notes
A2: Wind代码 ★必填 | B2: (关联) yyyy-mm-dd ★必填 | C2: 招股书原文(不要归一) ★必填 | D2: 全称/带说明 ○选填 | E2: 认购金额数值 ★必填 | F2: 币种 HKD/USD ★必填 | G2: 锁定期 月 ★必填 | H2: 1=确认与发行人关联(名字含发行人 token或员工持股),0=独立财务投资者或未披露 规则法重置 2026-05 | I2: 解禁日 yyyy-mm-dd | J2: 实际控制人 | K2: 备注 ○选填
A3: 03296.HK | B3: 2026-04-23 | C3: JPMAMAPL | D3: JPMAMAPL (J.P. Morgan AM Asia Pac) | E3: 2500000000 | F3: HKD | G3: 6 | J3: prospectus_2026-04-15
A4: 1187.HK | B4: 46148 | C4: ODI TRUST LIMITED | D4: ODI TRUST LIMITED | E4: 7826670 | F4: HKD | G4: 6 | I4: 46332
A5: 1187.HK | B5: 46148 | C5: 蓝思科技(香港)有限公司 | D5: 蓝思科技(香港)有限公司 | E5: 78302097 | F5: HKD | G5: 6 | I5: 46332 | J5: 周群飞
A6: 1187.HK | B6: 46148 | C6: 远信(珠海)私募基金管理有限公司及中国银河国际投资有限公司 | D6: 远信(珠海)私募基金管理有限公司及中国银河国际投资有限公司 | E6: 50971680 | F6: HKD | G6: 6 | I6: 46332 | J6: 刘岩
A7: 1187.HK | B7: 46148 | C7: 盘京港景投资基金 | D7: 盘京港景投资基金 | E7: 39149082 | F7: HKD | J7: XIAO Jian
A8: 1187.HK | B8: 46148 | C8: 大成国际资产管理有限公司 | D8: 大成国际资产管理有限公司 | E8: 15657273 | F8: HKD | G8: 6 | I8: 46332 | J8: 大成基金管理有限公司
A9: 1187.HK | B9: 46148 | C9: 中康科技控股有限公司 | D9: 中康科技控股有限公司 | E9: 15657273 | F9: HKD | G9: 6 | I9: 46332 | J9: 吴郁抒
A10: 1187.HK | B10: 46148 | C10: 黄雪林 | D10: 黄雪林 | E10: 39149082 | F10: HKD | G10: 6 | I10: 46332
A11: 1187.HK | B11: 46148 | C11: 戴钧安 | D11: 戴钧安 | E11: 19574541 | F11: HKD | G11: 6 | I11: 46332
A12: 1187.HK | B12: 46148 | C12: 陆勤超 | D12: 陆勤超 | E12: 15657273 | F12: HKD | G12: 6 | I12: 46332
A13: 1187.HK | B13: 46148 | C13: 长沙雨丰科技有限公司 | D13: 长沙雨丰科技有限公司 | E13: 54696231 | F13: HKD | G13: 6 | I13: 46332 | J13: 湖南环保科技产业园管理委员会
A14: 1187.HK | B14: 46148 | C14: 香港汉清达实业有限公司 | D14: 香港汉清达实业有限公司 | E14: 19574541 | F14: HKD | G14: 6 | I14: 46332 | J14: 侯守山
A15: 1187.HK | B15: 46148 | C15: FR M CONSULTING CO., LTD | D15: FR M CONSULTING CO., LTD | E15: 23487876 | F15: HKD | G15: 6 | I15: 46332 | J15: 张国锋
A16: 1609.HK | B16: 46147 | C16: 大湾区发展基金管理有限公司 | D16: 大湾区发展基金管理有限公司 | E16: 54834950 | F16: HKD | G16: 6 | I16: 46331
A17: 1609.HK | B17: 46147 | C17: JSC International Investment Fund SPC | D17: JSC International Investment Fund SPC | E17: 193902175 | F17: HKD | G17: 6 | I17: 46331
A18: 1609.HK | B18: 46147 | C18: OAP IV (HK) Limited | D18: OAP IV (HK) Limited | E18: 39168525 | F18: HKD | G18: 6 | I18: 46331
A19: 6810.HK | B19: 46141 | C19: China Orient International Asset Management Limited - China Orient Enhanced Income Fund | D19: China Orient International Asset Management Limited - China Orient Enhanced Income Fund | E19: 39156986 | F19: HKD | G19: 6 | I19: 46324 | J19: 中央汇金投资有限责任公司
A20: 6810.HK | B20: 46141 | C20: XINWUTANG CO., LIMITED | D20: XINWUTANG CO., LIMITED | E20: 247250102 | F20: HKD | G20: 6 | I20: 46324 | J20: 嘉善县财政局
A21: 1879.HK | B21: 46140 | C21: 上海中移数字转型产业私募基金合伙企业(有限合伙) | D21: 上海中移数字转型产业私募基金合伙企业(有限合伙) | E21: 114360768 | F21: HKD | G21: 6 | I21: 46323
A22: 1879.HK | B22: 46140 | C22: Alibaba Investment Limited | D22: Alibaba Investment Limited | E22: 203659776 | F22: HKD | G22: 6 | I22: 46323 | J22: 阿里巴巴集团控股有限公司
A23: 1879.HK | B23: 46140 | C23: 富达基金(香港)有限公司 | D23: 富达基金(香港)有限公司 | E23: 117496236 | F23: HKD | G23: 6 | I23: 46323
A24: 1879.HK | B24: 46140 | C24: GIC PRIVATE LIMITED | D24: GIC PRIVATE LIMITED | E24: 156660732 | F24: HKD | G24: 6 | I24: 46323
A25: 1879.HK | B25: 46140 | C25: BlackRock, Inc. | D25: BlackRock, Inc. | E25: 117496236 | F25: HKD | G25: 6 | I25: 46323
A26: 1879.HK | B26: 46140 | C26: Baillie Gifford Overseas Limited及Baillie Gifford & Co | D26: Baillie Gifford Overseas Limited及Baillie Gifford & Co | E26: 117496236 | F26: HKD | G26: 6 | I26: 46323
A27: 1879.HK | B27: 46140 | C27: 工银理财有限责任公司 | D27: 工银理财有限责任公司 | E27: 19582248 | F27: HKD | G27: 6 | I27: 46323 | J27: 中国工商银行股份有限公司
A28: 1879.HK | B28: 46140 | C28: 中国平安资产管理(香港)有限公司 | D28: 中国平安资产管理(香港)有限公司 | E28: 19582248 | F28: HKD | G28: 6 | I28: 46323 | J28: 中国平安保险(集团)股份有限公司
A29: 1879.HK | B29: 46140 | C29: 中兴通讯(香港)有限公司 | D29: 中兴通讯(香港)有限公司 | E29: 33682236 | F29: HKD | G29: 6 | I29: 46323 | J29: 中兴通讯股份有限公司
A30: 1879.HK | B30: 46140 | C30: 3W Fund Management Limited | D30: 3W Fund Management Limited | E30: 78328992 | F30: HKD | G30: 6 | I30: 46323
A31: 1879.HK | B31: 46140 | C31: TEMASEK HOLDINGS (PRIVATE) LIMITED | D31: TEMASEK HOLDINGS (PRIVATE) LIMITED | E31: 117496236 | F31: HKD | G31: 6 | I31: 46323
A32: 1879.HK | B32: 46140 | C32: Aspex Master Fund | D32: Aspex Master Fund | E32: 78328992 | F32: HKD | G32: 6 | I32: 46323
A33: 1879.HK | B33: 46140 | C33: CPE Fir Investment Limited | D33: CPE Fir Investment Limited | E33: 39164496 | F33: HKD | G33: 6 | I33: 46323
A34: 1879.HK | B34: 46140 | C34: HHLR ADVISORS, LTD. | D34: HHLR ADVISORS, LTD. | E34: 78328992 | F34: HKD | G34: 6 | I34: 46323
A35: 1879.HK | B35: 46140 | C35: Schroder Investment Management (Singapore) Ltd,Schroder Investment Management (Hong Kong) Limited及Schroder Investment Management Limited | D35: Schroder Investment Management (Singapore) Ltd,Schroder Investment Management (Hong Kong) Limited及Schroder Investment Management Limited | E35: 117496236 | F35: HKD | G35: 6 | I35: 46323
A36: 1879.HK | B36: 46140 | C36: 未来资产证券(香港)有限公司 | D36: 未来资产证券(香港)有限公司 | E36: 39164496 | F36: HKD | G36: 6 | I36: 46323 | J36: MIRAE ASSET CAPITAL CO., LTD.
A37: 1879.HK | B37: 46140 | C37: 联想集团有限公司 | D37: 联想集团有限公司 | E37: 39164496 | F37: HKD | G37: 6 | I37: 46323
A38: 1879.HK | B38: 46140 | C38: 广发基金管理有限公司及广发国际资产管理有限公司 | D38: 广发基金管理有限公司及广发国际资产管理有限公司 | E38: 39161748 | F38: HKD | G38: 6 | I38: 46323
A39: 1879.HK | B39: 46140 | C39: 景林资产管理香港有限公司,上海景林资产管理有限公司及CICC Financial Trading Limited | D39: 景林资产管理香港有限公司,上海景林资产管理有限公司及CICC Financial Trading Limited | E39: 39161748 | F39: HKD | G39: 6 | I39: 46323
A40: 1879.HK | B40: 46140 | C40: 瑞银环球资产管理(新加坡)有限公司 | D40: 瑞银环球资产管理(新加坡)有限公司 | E40: 78328992 | F40: HKD | G40: 6 | I40: 46323 | J40: UBS Asset Management AG
A41: 2493.HK | B41: 46140 | C41: 香港君實有限公司 | D41: 香港君實有限公司 | E41: 156669048 | F41: HKD | G41: 6 | I41: 46323 | J41: 熊凤祥与熊俊
A42: 2493.HK | B42: 46140 | C42: SANJIN INTERNATIONAL CO.,LTD. | D42: SANJIN INTERNATIONAL CO.,LTD. | E42: 117503168 | F42: HKD | G42: 6 | I42: 46323
A43: 2493.HK | B43: 46140 | C43: 國惠(香港)控股有限公司 | D43: 國惠(香港)控股有限公司 | E43: 54832232 | F43: HKD | G43: 6 | I43: 46323 | J43: 山东发展投资控股集团有限公司
A44: 2493.HK | B44: 46140 | C44: 锦绣中和(天津)投资管理有限公司 | D44: 锦绣中和(天津)投资管理有限公司 | E44: 7833176 | F44: HKD | G44: 6 | I44: 46323 | J44: 张敬庭
A45: 2493.HK | B45: 46140 | C45: WuXi Biologics HealthCare Venture | D45: WuXi Biologics HealthCare Venture | E45: 23499528 | F45: HKD | G45: 6 | I45: 46323 | J45: 药明生物技术有限公司
A46: 2493.HK | B46: 46140 | C46: 昌荣国际有限公司 | D46: 昌荣国际有限公司 | E46: 54832232 | F46: HKD | G46: 6 | I46: 46323 | J46: 唐春山
A47: 3296.HK | B47: 46135 | C47: 常春藤資產管理(香港)有限公司 | D47: 常春藤資產管理(香港)有限公司 | E47: 78368220 | F47: HKD | G47: 6 | I47: 46318 | J47: 黄勇
A48: 3296.HK | B48: 46135 | C48: Green Better Limited | D48: Green Better Limited | E48: 78368220 | F48: HKD | G48: 6 | I48: 46318 | J48: 小米集团
A49: 3296.HK | B49: 46135 | C49: 北京君正集成电路(香港)集团有限公司 | D49: 北京君正集成电路(香港)集团有限公司 | E49: 78368220 | F49: HKD | G49: 6 | I49: 46318 | J49: 北京君正集成电路股份有限公司
A50: 3296.HK | B50: 46135 | C50: 摩根大通资产管理(亚太)有限公司 | D50: 摩根大通资产管理(亚太)有限公司 | E50: 532928760 | F50: HKD | G50: 6 | I50: 46318 | J50: JPMorgan Chase & Co.
A51: 3296.HK | B51: 46135 | C51: 瑞银环球资产管理(新加坡)有限公司 | D51: 瑞银环球资产管理(新加坡)有限公司 | E51: 78368220 | F51: HKD | G51: 6 | I51: 46318 | J51: UBS Group AG
A52: 3296.HK | B52: 46135 | C52: 上海高毅资产管理合伙企业(有限合伙),CICC Financial Trading Limited | D52: 上海高毅资产管理合伙企业(有限合伙),CICC Financial Trading Limited | E52: 95609850 | F52: HKD | G52: 6 | I52: 46318
A53: 3296.HK | B53: 46135 | C53: 新華資產管理(香港)有限公司 | D53: 新華資產管理(香港)有限公司 | E53: 78368220 | F53: HKD | G53: 6 | I53: 46318
A54: 3296.HK | B54: 46135 | C54: Aurora SF | D54: Aurora SF | E54: 195928320 | F54: HKD | G54: 6 | I54: 46318
A55: 3296.HK | B55: 46135 | C55: Cloud Map Holdings Limited | D55: Cloud Map Holdings Limited | E55: 156744210 | F55: HKD | G55: 6 | I55: 46318
A56: 3296.HK | B56: 46135 | C56: 泰康人寿保险有限责任公司 | D56: 泰康人寿保险有限责任公司 | E56: 156744210 | F56: HKD | G56: 6 | I56: 46318 | J56: 泰康保险集团股份有限公司
A57: 3296.HK | B57: 46135 | C57: 光大理财有限责任公司 | D57: 光大理财有限责任公司 | E57: 78368220 | F57: HKD | G57: 6 | I57: 46318 | J57: 中国光大银行股份有限公司
A58: 3296.HK | B58: 46135 | C58: 建滔投資有限公司 | D58: 建滔投資有限公司 | E58: 195928320 | F58: HKD | G58: 6 | I58: 46318 | J58: 建滔集团有限公司
A59: 3296.HK | B59: 46135 | C59: 3W Fund Management Limited | D59: 3W Fund Management Limited | E59: 117552330 | F59: HKD | G59: 6 | I59: 46318 | J59: Wu Weiwei
A60: 3296.HK | B60: 46135 | C60: 艾唯技术有限公司 | D60: 艾唯技术有限公司 | E60: 78368220 | F60: HKD | G60: 6 | I60: 46318 | J60: 上海艾为电子技术股份有限公司
A61: 3296.HK | B61: 46135 | C61: 宏興國際科技有限公司 | D61: 宏興國際科技有限公司 | E61: 78368220 | F61: HKD | G61: 6 | I61: 46318 | J61: 胜宏科技(惠州)股份有限公司
A62: 3296.HK | B62: 46135 | C62: Perseverance Asset Management International (Singapore) Pte. Ltd. | D62: Perseverance Asset Management International (Singapore) Pte. Ltd. | E62: 61126590 | F62: HKD | G62: 6 | I62: 46318
A63: 3296.HK | B63: 46135 | C63: 韦尔半导体香港有限公司 | D63: 韦尔半导体香港有限公司 | E63: 117552330 | F63: HKD | G63: 6 | I63: 46318 | J63: 豪威集成电路(集团)股份有限公司
A64: 3296.HK | B64: 46135 | C64: JinYi Capital Multi-Strategy Fund SPC Ltd. | D64: JinYi Capital Multi-Strategy Fund SPC Ltd. | E64: 15672090 | F64: HKD | G64: 6 | I64: 46318
A65: 2476.HK | B65: 46133 | C65: 博时基金(国际)有限公司 | D65: 博时基金(国际)有限公司 | E65: 156738384 | F65: HKD | G65: 6 | I65: 46316
A66: 2476.HK | B66: 46133 | C66: HHLR ADVISORS, LTD. | D66: HHLR ADVISORS, LTD. | E66: 235128564 | F66: HKD | G66: 6 | I66: 46316
A67: 2476.HK | B67: 46133 | C67: 贪玩 | D67: 贪玩 | E67: 235128564 | F67: HKD | G67: 6 | I67: 46316
A68: 2476.HK | B68: 46133 | C68: Tropical Terrain Limited | D68: Tropical Terrain Limited | E68: 235128564 | F68: HKD | G68: 6 | I68: 46316
A69: 2476.HK | B69: 46133 | C69: RUIHUA (INTERNATIONAL) INVESTMENT LIMITED | D69: RUIHUA (INTERNATIONAL) INVESTMENT LIMITED | E69: 156738384 | F69: HKD | G69: 6 | I69: 46316 | J69: 张建斌
A70: 2476.HK | B70: 46133 | C70: Mega Prime Development Limited | D70: Mega Prime Development Limited | E70: 97950996 | F70: HKD | G70: 6 | I70: 46316
A71: 2476.HK | B71: 46133 | C71: Poly Platinum Enterprises Limited | D71: Poly Platinum Enterprises Limited | E71: 58766400 | F71: HKD | G71: 6 | I71: 46316
A72: 2476.HK | B72: 46133 | C72: Golden K2 Falcon Open-ended Fund Company | D72: Golden K2 Falcon Open-ended Fund Company | E72: 156738384 | F72: HKD | G72: 6 | I72: 46316
A73: 2476.HK | B73: 46133 | C73: Infore Funds Series 1 Open-ended Fund Company – Infore Global Equity Fund | D73: Infore Funds Series 1 Open-ended Fund Company – Infore Global Equity Fund | E73: 156738384 | F73: HKD | G73: 6 | I73: 46316
A74: 2476.HK | B74: 46133 | C74: 鲁花道生(北京)企业管理发展有限公司 | D74: 鲁花道生(北京)企业管理发展有限公司 | E74: 117553788 | F74: HKD | G74: 6 | I74: 46316 | J74: 孙孟全
A75: 2476.HK | B75: 46133 | C75: MY.Alpha Management HK Advisors Limited | D75: MY.Alpha Management HK Advisors Limited | E75: 156738384 | F75: HKD | G75: 6 | I75: 46316
A76: 2476.HK | B76: 46133 | C76: Foresight Global Superior Choice SPC | D76: Foresight Global Superior Choice SPC | E76: 235128564 | F76: HKD | G76: 6 | I76: 46316
A77: 2476.HK | B77: 46133 | C77: 歐萬達基金管理有限公司 | D77: 歐萬達基金管理有限公司 | E77: 156738384 | F77: HKD | G77: 6 | I77: 46316
A78: 2476.HK | B78: 46133 | C78: 深圳市前海奇点财富资产管理有限公司 | D78: 深圳市前海奇点财富资产管理有限公司 | E78: 117553788 | F78: HKD | G78: 6 | I78: 46316
A79: 2476.HK | B79: 46133 | C79: Jump Trading Pacific Pte. Ltd. | D79: Jump Trading Pacific Pte. Ltd. | E79: 117553788 | F79: HKD | G79: 6 | I79: 46316
A80: 2476.HK | B80: 46133 | C80: 未来资产证券有限公司 | D80: 未来资产证券有限公司 | E80: 117553788 | F80: HKD | G80: 6 | I80: 46316
A81: 2476.HK | B81: 46133 | C81: 盘京港景投资基金 | D81: 盘京港景投资基金 | E81: 117553788 | F81: HKD | G81: 6 | I81: 46316
A82: 2476.HK | B82: 46133 | C82: Wind Sabre Opportunities Fund SP | D82: Wind Sabre Opportunities Fund SP | E82: 117553788 | F82: HKD | G82: 6 | I82: 46316
A83: 2476.HK | B83: 46133 | C83: Black Dragon AP SPV1 | D83: Black Dragon AP SPV1 | E83: 78369192 | F83: HKD | G83: 6 | I83: 46316
A84: 2476.HK | B84: 46133 | C84: HQ TELECOM SINGAPORE PTE.LTD. | D84: HQ TELECOM SINGAPORE PTE.LTD. | E84: 78369192 | F84: HKD | G84: 6 | I84: 46316
A85: 2476.HK | B85: 46133 | C85: 景林资产管理香港有限公司 | D85: 景林资产管理香港有限公司 | E85: 195922980 | F85: HKD | G85: 6 | I85: 46316 | J85: 蒋锦志
A86: 2476.HK | B86: 46133 | C86: Cloudview Capital Limited | D86: Cloudview Capital Limited | E86: 156738384 | F86: HKD | G86: 6 | I86: 46316 | J86: 陈劲松
A87: 2476.HK | B87: 46133 | C87: New Alternative Limited | D87: New Alternative Limited | E87: 313497756 | F87: HKD | G87: 6 | I87: 46316 | J87: 虞锋
A88: 2476.HK | B88: 46133 | C88: 叶国富 | D88: 叶国富 | E88: 156738384 | F88: HKD | G88: 6 | I88: 46316
A89: 2476.HK | B89: 46133 | C89: 摩根士丹利国际股份有限公司 | D89: 摩根士丹利国际股份有限公司 | E89: 274313160 | F89: HKD | G89: 6 | I89: 46316
A90: 2476.HK | B90: 46133 | C90: Deliante Holdings Co., Ltd. | D90: Deliante Holdings Co., Ltd. | E90: 415394496 | F90: HKD | G90: 6 | I90: 46316
A91: 2476.HK | B91: 46133 | C91: Janchor Partners Pan-Asian Master Fund | D91: Janchor Partners Pan-Asian Master Fund | E91: 587810916 | F91: HKD | G91: 6 | I91: 46316
A92: 2476.HK | B92: 46133 | C92: 阳光人寿保险股份有限公司 | D92: 阳光人寿保险股份有限公司 | E92: 235128564 | F92: HKD | G92: 6 | I92: 46316 | J92: 阳光保险集团股份有限公司
A93: 2476.HK | B93: 46133 | C93: 光大理财有限责任公司 | D93: 光大理财有限责任公司 | E93: 117553788 | F93: HKD | G93: 6 | I93: 46316 | J93: 中国光大银行股份有限公司
A94: 2476.HK | B94: 46133 | C94: 天弘基金管理有限公司 | D94: 天弘基金管理有限公司 | E94: 156738384 | F94: HKD | G94: 6 | I94: 46316 | J94: 蚂蚁科技集团股份有限公司
A95: 2476.HK | B95: 46133 | C95: 信银(香港)投资有限公司 | D95: 信银(香港)投资有限公司 | E95: 156738384 | F95: HKD | G95: 6 | I95: 46316 | J95: 中信银行股份有限公司
A96: 2476.HK | B96: 46133 | C96: 惠州市惠联投资合伙企业(有限合伙) | D96: 惠州市惠联投资合伙企业(有限合伙) | E96: 225306180 | F96: HKD | G96: 6 | I96: 46316 | J96: 惠州市惠城区国有资产监督管理局
A97: 2476.HK | B97: 46133 | C97: 香港麦逊电子有限公司 | D97: 香港麦逊电子有限公司 | E97: 391866948 | F97: HKD | G97: 6 | I97: 46316 | J97: 深圳市大族数控科技股份有限公司
A98: 2476.HK | B98: 46133 | C98: 涌容(香港)資產管理有限公司 | D98: 涌容(香港)資產管理有限公司 | E98: 235128564 | F98: HKD | G98: 6 | I98: 46316 | J98: 黄勇
A99: 2476.HK | B99: 46133 | C99: 上海保银资产管理有限公司 | D99: 上海保银资产管理有限公司 | E99: 235128564 | F99: HKD | G99: 6 | I99: 46316 | J99: 王强
A100: 2476.HK | B100: 46133 | C100: Metazone Link (HK) Limited | D100: Metazone Link (HK) Limited | E100: 156738384 | F100: HKD | G100: 6 | I100: 46316 | J100: 李东生
...

Sheet 03_company_fundamentals
A1: stock_code | B1: ipo_year | C1: revenue_n3 | D1: revenue_n2 | E1: revenue_n1 | F1: net_profit_n3 | G1: net_profit_n2 | H1: net_profit_n1 | I1: gross_margin_n3 | J1: gross_margin_n2 | K1: gross_margin_n1 | L1: roe_avg_3y | M1: net_debt_to_ebitda | N1: fcf_positive_years_3y | O1: top1_customer_pct_n1 | P1: _diag_revenue_2023 | Q1: _diag_revenue_2024 | R1: _diag_revenue_2025 | S1: _diag_netprofit_2023 | T1: _diag_netprofit_2024 | U1: _diag_netprofit_2025 | V1: _diag_grossmargin_2023 | W1: _diag_grossmargin_2024 | X1: grossmargin_2025
A2: Wind代码 ★必填 | B2: 上市年份(N年) 从01_ipo_master.listing_date提取 ★自动 | C2: N-3年营收 (rptDate=ipo_year-3) RMB亿 ★必填 | D2: N-2年营收 (rptDate=ipo_year-2) RMB亿 ★必填 | E2: N-1年营收 (rptDate=ipo_year-1) RMB亿 ★必填 | F2: N-3年净利润 (rptDate=ipo_year-3) RMB亿 ★必填 | G2: N-2年净利润 (rptDate=ipo_year-2) RMB亿 ★必填 | H2: N-1年净利润 (rptDate=ipo_year-1) RMB亿 ★必填 | I2: N-3年毛利率 (rptDate=ipo_year-3) % ★必填 | J2: N-2年毛利率 (rptDate=ipo_year-2) % ★必填 | K2: N-1年毛利率 (rptDate=ipo_year-1) % ★必填 | L2: N-1年ROE (rptDate=ipo_year-1) % ○选填 | M2: N-1年资产负债率 (rptDate=ipo_year-1) % ○选填 | N2: 近3年自由现金流为正的年数 0-3 ○选填 | O2: N-1 年第一大客户收入占比 % ○选填 | P2: raw 2023 (备份) | Q2: raw 2024 (备份) | R2: raw 2025 (备份) | S2: raw 2023 (备份) | T2: raw 2024 (备份) | U2: raw 2025 (备份) | V2: raw 2023 (备份) | W2: raw 2024 (备份) | X2: raw 2025 (备份)
A3: 3296.HK | B3: =IFERROR(YEAR(VLOOKUP($A3,'01_ipo_master'!$A:$C,3,FALSE)),YEAR(VLOOKUP("0"&$A3,'01_ipo_master'!$A:$C,3,FALSE))) -> 2026 | C3: =[1]!wss($A3:$A3,"hks_stm_is","item=83","rptDate="&($B3-3)&"1231","rptType=1","currencyType=Cur=CNY","WssConvert=0","WssDivide=8","showcodes=N","cols=1;rows=1") -> 853.38484 | D3: =[1]!wss($A3:$A3,"hks_stm_is","item=83","rptDate="&($B3-2)&"1231","rptType=1","currencyType=Cur=CNY","WssConvert=0","WssDivide=8","showcodes=N","cols=1;rows=1") -> 1098.7799 | E3: =[1]!wss($A3:$A3,"hks_stm_is","item=83","rptDate="&($B3-1)&"1231","rptType=1","currencyType=Cur=CNY","WssConvert=0","WssDivide=8","showcodes=N","cols=1;rows=1") -> 1714.3693 | F3: =[1]!wss($A3:$A3,"hks_stm_is","item=61","rptDate="&($B3-3)&"1231","rptType=1","currencyType=Cur=CNY","WssConvert=0","WssDivide=8","showcodes=N","cols=1;rows=1") -> 27.08451 | G3: =[1]!wss($A3:$A3,"hks_stm_is","item=61","rptDate="&($B3-2)&"1231","rptType=1","currencyType=Cur=CNY","WssConvert=0","WssDivide=8","showcodes=N","cols=1;rows=1") -> 29.2894 | H3: =[1]!wss($A3:$A3,"hks_stm_is","item=61","rptDate="&($B3-1)&"1231","rptType=1","currencyType=Cur=CNY","WssConvert=0","WssDivide=8","showcodes=N","cols=1;rows=1") -> 40.81338 | I3: =[1]!wss($A3:$A3,"hks_fa_grossprofitmargin","rptDate="&($B3-3)&"1231","WssConvert=0","showcodes=N","cols=1;rows=1") -> 10.941 | J3: =[1]!wss($A3:$A3,"hks_fa_grossprofitmargin","rptDate="&($B3-2)&"1231","WssConvert=0","showcodes=N","cols=1;rows=1") -> 8.995 | K3: =[1]!wss($A3:$A3,"hks_fa_grossprofitmargin","rptDate="&($B3-1)&"1231","WssConvert=0","showcodes=N","cols=1;rows=1") -> 7.7174 | L3: =[1]!wss($A3:$A3,"hks_fa_roe","rptDate="&($B3-1)&"1231","WssConvert=0","showcodes=N","cols=1;rows=1") -> 16.8858 | M3: =[1]!wss($A3:$A3,"hks_fa_debttoassets","rptDate="&($B3-1)&"1231","WssConvert=0","showcodes=N","cols=1;rows=1") -> 72.6156 | N3: 取数代码 | O3: 诊断H3:净利字段ID占位为W45364519,如报错请在Wind"指标查询"搜"归母净利润"拿准确ID | P3: 853.38484 | Q3: 1098.7799 | R3: 1714.3693 | S3: 27.08451 | T3: 29.2894 | U3: 40.81338 | V3: 10.941 | W3: 8.995 | X3: 7.7174
A4: 2555.HK | B4: =IFERROR(YEAR(VLOOKUP($A4,'01_ipo_master'!$A:$C,3,FALSE)),YEAR(VLOOKUP("0"&$A4,'01_ipo_master'!$A:$C,3,FALSE))) -> 2024 | C4: =[1]!wss($A4:$A4,"hks_stm_is","item=83","rptDate="&($B4-3)&"1231","rptType=1","currencyType=Cur=CNY","WssConvert=0","WssDivide=8","showcodes=N","cols=1;rows=1") -> 36.44209 | D4: =[1]!wss($A4:$A4,"hks_stm_is","item=83","rptDate="&($B4-2)&"1231","rptType=1","currencyType=Cur=CNY","WssConvert=0","WssDivide=8","showcodes=N","cols=1;rows=1") -> 42.3167 | E4: =[1]!wss($A4:$A4,"hks_stm_is","item=83","rptDate="&($B4-1)&"1231","rptType=1","currencyType=Cur=CNY","WssConvert=0","WssDivide=8","showcodes=N","cols=1;rows=1") -> 57.04307 | F4: =[1]!wss($A4:$A4,"hks_stm_is","item=61","rptDate="&($B4-3)&"1231","rptType=1","currencyType=Cur=CNY","WssConvert=0","WssDivide=8","showcodes=N","cols=1;rows=1") -> 7.55816 | G4: =[1]!wss($A4:$A4,"hks_stm_is","item=61","rptDate="&($B4-2)&"1231","rptType=1","currencyType=Cur=CNY","WssConvert=0","WssDivide=8","showcodes=N","cols=1;rows=1") -> 9.54316 | H4: =[1]!wss($A4:$A4,"hks_stm_is","item=61","rptDate="&($B4-1)&"1231","rptType=1","currencyType=Cur=CNY","WssConvert=0","WssDivide=8","showcodes=N","cols=1;rows=1") -> 11.39211 | I4: =[1]!wss($A4:$A4,"hks_fa_grossprofitmargin","rptDate="&($B4-3)&"1231","WssConvert=0","showcodes=N","cols=1;rows=1") -> 35.7016 | J4: =[1]!wss($A4:$A4,"hks_fa_grossprofitmargin","rptDate="&($B4-2)&"1231","WssConvert=0","showcodes=N","cols=1;rows=1") -> 34.4117 | K4: =[1]!wss($A4:$A4,"hks_fa_grossprofitmargin","rptDate="&($B4-1)&"1231","WssConvert=0","showcodes=N","cols=1;rows=1") -> 34.4263 | L4: =[1]!wss($A4:$A4,"hks_fa_roe","rptDate="&($B4-1)&"1231","WssConvert=0","showcodes=N","cols=1;rows=1") -> 154.6065 | M4: =[1]!wss($A4:$A4,"hks_fa_debttoassets","rptDate="&($B4-1)&"1231","WssConvert=0","showcodes=N","cols=1;rows=1") -> 72.5605 | N4: =IFERROR(IF(VLOOKUP($A4,'01_ipo_master'!$A:$G,7,0)="",$A4,VLOOKUP($A4,'01_ipo_master'!$A:$G,7,0)),$A4) -> 2555.HK | P4: 57.04307 | Q4: 49.17997 | R4: 53.95068 | S4: 11.39211 | T4: 4.72184 | U4: 8.04897 | V4: 34.4263 | W4: 31.2054 | X4: 32.5082
A5: 3750.HK | B5: =IFERROR(YEAR(VLOOKUP($A5,'01_ipo_master'!$A:$C,3,FALSE)),YEAR(VLOOKUP("0"&$A5,'01_ipo_master'!$A:$C,3,FALSE))) -> 2025 | C5: =[1]!wss($A5:$A5,"hks_stm_is","item=83","rptDate="&($B5-3)&"1231","rptType=1","currencyType=Cur=CNY","WssConvert=0","WssDivide=8","showcodes=N","cols=1;rows=1") -> 3285.9399 | D5: =[1]!wss($A5:$A5,"hks_stm_is","item=83","rptDate="&($B5-2)&"1231","rptType=1","currencyType=Cur=CNY","WssConvert=0","WssDivide=8","showcodes=N","cols=1;rows=1") -> 4009.1705 | E5: =[1]!wss($A5:$A5,"hks_stm_is","item=83","rptDate="&($B5-1)&"1231","rptType=1","currencyType=Cur=CNY","WssConvert=0","WssDivide=8","showcodes=N","cols=1;rows=1") -> 3620.1255 | F5: =[1]!wss($A5:$A5,"hks_stm_is","item=61","rptDate="&($B5-3)&"1231","rptType=1","currencyType=Cur=CNY","WssConvert=0","WssDivide=8","showcodes=N","cols=1;rows=1") -> 307.29164 | G5: =[1]!wss($A5:$A5,"hks_stm_is","item=61","rptDate="&($B5-2)&"1231","rptType=1","currencyType=Cur=CNY","WssConvert=0","WssDivide=8","showcodes=N","cols=1;rows=1") -> 447.02249 | H5: =[1]!wss($A5:$A5,"hks_stm_is","item=61","rptDate="&($B5-1)&"1231","rptType=1","currencyType=Cur=CNY","WssConvert=0","WssDivide=8","showcodes=N","cols=1;rows=1") -> 520.32846 | I5: =[1]!wss($A5:$A5,"hks_fa_grossprofitmargin","rptDate="&($B5-3)&"1231","WssConvert=0","showcodes=N","cols=1;rows=1") -> 15.1739 | J5: =[1]!wss($A5:$A5,"hks_fa_grossprofitmargin","rptDate="&($B5-2)&"1231","WssConvert=0","showcodes=N","cols=1;rows=1") -> 16.5641 | K5: =[1]!wss($A5:$A5,"hks_fa_grossprofitmargin","rptDate="&($B5-1)&"1231","WssConvert=0","showcodes=N","cols=1;rows=1") -> 21.1433 | L5: =[1]!wss($A5:$A5,"hks_fa_roe","rptDate="&($B5-1)&"1231","WssConvert=0","showcodes=N","cols=1;rows=1") -> 23.4046 | M5: =[1]!wss($A5:$A5,"hks_fa_debttoassets","rptDate="&($B5-1)&"1231","WssConvert=0","showcodes=N","cols=1;rows=1") -> 65.2382 | P5: 4009.1705 | Q5: 3620.1255 | R5: 4237.0183 | S5: 447.02249 | T5: 520.32846 | U5: 722.01282 | V5: 16.5641 | W5: 21.1433 | X5: 26.2728
A6: 0300.HK | B6: =IFERROR(YEAR(VLOOKUP($A6,'01_ipo_master'!$A:$C,3,FALSE)),YEAR(VLOOKUP("0"&$A6,'01_ipo_master'!$A:$C,3,FALSE))) -> 2024 | C6: =[1]!wss($A6:$A6,"hks_stm_is","item=83","rptDate="&($B6-3)&"1231","rptType=1","currencyType=Cur=CNY","WssConvert=0","WssDivide=8","showcodes=N","cols=1;rows=1") -> 3433.6083 | D6: =[1]!wss($A6:$A6,"hks_stm_is","item=83","rptDate="&($B6-2)&"1231","rptType=1","currencyType=Cur=CNY","WssConvert=0","WssDivide=8","showcodes=N","cols=1;rows=1") -> 3457.0871 | E6: =[1]!wss($A6:$A6,"hks_stm_is","item=83","rptDate="&($B6-1)&"1231","rptType=1","currencyType=Cur=CNY","WssConvert=0","WssDivide=8","showcodes=N","cols=1;rows=1") -> 3737.098 | F6: =[1]!wss($A6:$A6,"hks_stm_is","item=61","rptDate="&($B6-3)&"1231","rptType=1","currencyType=Cur=CNY","WssConvert=0","WssDivide=8","showcodes=N","cols=1;rows=1") -> 285.8698 | G6: =[1]!wss($A6:$A6,"hks_stm_is","item=61","rptDate="&($B6-2)&"1231","rptType=1","currencyType=Cur=CNY","WssConvert=0","WssDivide=8","showcodes=N","cols=1;rows=1") -> 295.53342 | H6: =[1]!wss($A6:$A6,"hks_stm_is","item=61","rptDate="&($B6-1)&"1231","rptType=1","currencyType=Cur=CNY","WssConvert=0","WssDivide=8","showcodes=N","cols=1;rows=1") -> 337.21536 | I6: =[1]!wss($A6:$A6,"hks_fa_grossprofitmargin","rptDate="&($B6-3)&"1231","WssConvert=0","showcodes=N","cols=1;rows=1") -> 22.3992 | J6: =[1]!wss($A6:$A6,"hks_fa_grossprofitmargin","rptDate="&($B6-2)&"1231","WssConvert=0","showcodes=N","cols=1;rows=1") -> 24.1206 | K6: =[1]!wss($A6:$A6,"hks_fa_grossprofitmargin","rptDate="&($B6-1)&"1231","WssConvert=0","showcodes=N","cols=1;rows=1") -> 26.3278 | L6: =[1]!wss($A6:$A6,"hks_fa_roe","rptDate="&($B6-1)&"1231","WssConvert=0","showcodes=N","cols=1;rows=1") -> 22.054 | M6: =[1]!wss($A6:$A6,"hks_fa_debttoassets","rptDate="&($B6-1)&"1231","WssConvert=0","showcodes=N","cols=1;rows=1") -> 64.1389 | P6: 3737.098 | Q6: 4090.8427 | R6: 4585.0241 | S6: 337.21536 | T6: 385.38987 | U6: 439.45411 | V6: 26.3278 | W6: 26.1808 | X6: 26.1809
A7: 6936.HK | B7: =IFERROR(YEAR(VLOOKUP($A7,'01_ipo_master'!$A:$C,3,FALSE)),YEAR(VLOOKUP("0"&$A7,'01_ipo_master'!$A:$C,3,FALSE))) -> 2024 | C7: =[1]!wss($A7:$A7,"hks_stm_is","item=83","rptDate="&($B7-3)&"1231","rptType=1","currencyType=Cur=CNY","WssConvert=0","WssDivide=8","showcodes=N","cols=1;rows=1") -> 2071.8665 | D7: =[1]!wss($A7:$A7,"hks_stm_is","item=83","rptDate="&($B7-2)&"1231","rptType=1","currencyType=Cur=CNY","WssConvert=0","WssDivide=8","showcodes=N","cols=1;rows=1") -> 2674.9041 | E7: =[1]!wss($A7:$A7,"hks_stm_is","item=83","rptDate="&($B7-1)&"1231","rptType=1","currencyType=Cur=CNY","WssConvert=0","WssDivide=8","showcodes=N","cols=1;rows=1") -> 2584.094 | F7: =[1]!wss($A7:$A7,"hks_stm_is","item=61","rptDate="&($B7-3)&"1231","rptType=1","currencyType=Cur=CNY","WssConvert=0","WssDivide=8","showcodes=N","cols=1;rows=1") -> 47.31979 | G7: =[1]!wss($A7:$A7,"hks_stm_is","item=61","rptDate="&($B7-2)&"1231","rptType=1","currencyType=Cur=CNY","WssConvert=0","WssDivide=8","showcodes=N","cols=1;rows=1") -> 62.27058 | H7: =[1]!wss($A7:$A7,"hks_stm_is","item=61","rptDate="&($B7-1)&"1231","rptType=1","currencyType=Cur=CNY","WssConvert=0","WssDivide=8","showcodes=N","cols=1;rows=1") -> 82.34493 | I7: =[1]!wss($A7:$A7,"hks_fa_grossprofitmargin","rptDate="&($B7-3)&"1231","WssConvert=0","showcodes=N","cols=1;rows=1") -> 12.4417 | J7: =[1]!wss($A7:$A7,"hks_fa_grossprofitmargin","rptDate="&($B7-2)&"1231","WssConvert=0","showcodes=N","cols=1;rows=1") -> 12.3415 | K7: =[1]!wss($A7:$A7,"hks_fa_grossprofitmargin","rptDate="&($B7-1)&"1231","WssConvert=0","showcodes=N","cols=1;rows=1") -> 12.6287 | L7: =[1]!wss($A7:$A7,"hks_fa_roe","rptDate="&($B7-1)&"1231","WssConvert=0","showcodes=N","cols=1;rows=1") -> 9.1978 | M7: =[1]!wss($A7:$A7,"hks_fa_debttoassets","rptDate="&($B7-1)&"1231","WssConvert=0","showcodes=N","cols=1;rows=1") -> 53.3688 | P7: 2584.094 | Q7: 2844.2006 | R7: 3082.2665 | S7: 82.34493 | T7: 101.70427 | U7: 111.17216 | V7: 12.6287 | W7: 13.6755 | X7: 13.0695
A8: 9973.HK | B8: =IFERROR(YEAR(VLOOKUP($A8,'01_ipo_master'!$A:$C,3,FALSE)),YEAR(VLOOKUP("0"&$A8,'01_ipo_master'!$A:$C,3,FALSE))) -> 2025 | C8: =[1]!wss($A8:$A8,"hks_stm_is","item=83","rptDate="&($B8-3)&"1231","rptType=1","currencyType=Cur=CNY","WssConvert=0","WssDivide=8","showcodes=N","cols=1;rows=1") -> 926.18 | D8: =[1]!wss($A8:$A8,"hks_stm_is","item=83","rptDate="&($B8-2)&"1231","rptType=1","currencyType=Cur=CNY","WssConvert=0","WssDivide=8","showcodes=N","cols=1;rows=1") -> 1632.05 | E8: =[1]!wss($A8:$A8,"hks_stm_is","item=83","rptDate="&($B8-1)&"1231","rptType=1","currencyType=Cur=CNY","WssConvert=0","WssDivide=8","showcodes=N","cols=1;rows=1") -> 2698.97 | F8: =[1]!wss($A8:$A8,"hks_stm_is","item=61","rptDate="&($B8-3)&"1231","rptType=1","currencyType=Cur=CNY","WssConvert=0","WssDivide=8","showcodes=N","cols=1;rows=1") -> 62.66 | G8: =[1]!wss($A8:$A8,"hks_stm_is","item=61","rptDate="&($B8-2)&"1231","rptType=1","currencyType=Cur=CNY","WssConvert=0","WssDivide=8","showcodes=N","cols=1;rows=1") -> 119.53 | H8: =[1]!wss($A8:$A8,"hks_stm_is","item=61","rptDate="&($B8-1)&"1231","rptType=1","currencyType=Cur=CNY","WssConvert=0","WssDivide=8","showcodes=N","cols=1;rows=1") -> 141.35 | I8: =[1]!wss($A8:$A8,"hks_fa_grossprofitmargin","rptDate="&($B8-3)&"1231","WssConvert=0","showcodes=N","cols=1;rows=1") -> 13.8256 | J8: =[1]!wss($A8:$A8,"hks_fa_grossprofitmargin","rptDate="&($B8-2)&"1231","WssConvert=0","showcodes=N","cols=1;rows=1") -> 15.986 | K8: =[1]!wss($A8:$A8,"hks_fa_grossprofitmargin","rptDate="&($B8-1)&"1231","WssConvert=0","showcodes=N","cols=1;rows=1") -> 13.4525 | L8: =[1]!wss($A8:$A8,"hks_fa_roe","rptDate="&($B8-1)&"1231","WssConvert=0","showcodes=N","cols=1;rows=1") -> 67.4074 | M8: =[1]!wss($A8:$A8,"hks_fa_debttoassets","rptDate="&($B8-1)&"1231","WssConvert=0","showcodes=N","cols=1;rows=1") -> 87.8858 | P8: 1632.05 | Q8: 2698.97 | R8: 3002.87 | S8: 119.53 | T8: 141.35 | U8: 190.19 | V8: 15.986 | W8: 13.4525 | X8: 13.8011
A9: 2714.HK | B9: =IFERROR(YEAR(VLOOKUP($A9,'01_ipo_master'!$A:$C,3,FALSE)),YEAR(VLOOKUP("0"&$A9,'01_ipo_master'!$A:$C,3,FALSE))) -> 2026 | C9: =[1]!wss($A9:$A9,"hks_stm_is","item=83","rptDate="&($B9-3)&"1231","rptType=1","currencyType=Cur=CNY","WssConvert=0","WssDivide=8","showcodes=N","cols=1;rows=1") -> 1108.6073 | D9: =[1]!wss($A9:$A9,"hks_stm_is","item=83","rptDate="&($B9-2)&"1231","rptType=1","currencyType=Cur=CNY","WssConvert=0","WssDivide=8","showcodes=N","cols=1;rows=1") -> 1379.4689 | E9: =[1]!wss($A9:$A9,"hks_stm_is","item=83","rptDate="&($B9-1)&"1231","rptType=1","currencyType=Cur=CNY","WssConvert=0","WssDivide=8","showcodes=N","cols=1;rows=1") -> 1441.4497 | F9: =[1]!wss($A9:$A9,"hks_stm_is","item=61","rptDate="&($B9-3)&"1231","rptType=1","currencyType=Cur=CNY","WssConvert=0","WssDivide=8","showcodes=N","cols=1;rows=1") -> -42.632808 | G9: =[1]!wss($A9:$A9,"hks_stm_is","item=61","rptDate="&($B9-2)&"1231","rptType=1","currencyType=Cur=CNY","WssConvert=0","WssDivide=8","showcodes=N","cols=1;rows=1") -> 178.8126 | H9: =[1]!wss($A9:$A9,"hks_stm_is","item=61","rptDate="&($B9-1)&"1231","rptType=1","currencyType=Cur=CNY","WssConvert=0","WssDivide=8","showcodes=N","cols=1;rows=1") -> 154.86891 | I9: =[1]!wss($A9:$A9,"hks_fa_grossprofitmargin","rptDate="&($B9-3)&"1231","WssConvert=0","showcodes=N","cols=1;rows=1") -> 3.1084 | J9: =[1]!wss($A9:$A9,"hks_fa_grossprofitmargin","rptDate="&($B9-2)&"1231","WssConvert=0","showcodes=N","cols=1;rows=1") -> 19.0511 | K9: =[1]!wss($A9:$A9,"hks_fa_grossprofitmargin","rptDate="&($B9-1)&"1231","WssConvert=0","showcodes=N","cols=1;rows=1") -> 17.8181 | L9: =[1]!wss($A9:$A9,"hks_fa_roe","rptDate="&($B9-1)&"1231","WssConvert=0","showcodes=N","cols=1;rows=1") -> 20.6877 | M9: =[1]!wss($A9:$A9,"hks_fa_debttoassets","rptDate="&($B9-1)&"1231","WssConvert=0","showcodes=N","cols=1;rows=1") -> 54.1508 | P9: 1108.6073 | Q9: 1379.4689 | R9: 1441.4497 | S9: -42.632808 | T9: 178.8126 | U9: 154.86891 | V9: 3.1084 | W9: 19.0511 | X9: 17.8181
A10: 9878.HK | B10: =IFERROR(YEAR(VLOOKUP($A10,'01_ipo_master'!$A:$C,3,FALSE)),YEAR(VLOOKUP("0"&$A10,'01_ipo_master'!$A:$C,3,FALSE))) -> 2022 | C10: =[1]!wss($A10:$A10,"hks_stm_is","item=83","rptDate="&($B10-3)&"1231","rptType=1","currencyType=Cur=CNY","WssConvert=0","WssDivide=8","showcodes=N","cols=1;rows=1") -> 436.34056 | D10: =[1]!wss($A10:$A10,"hks_stm_is","item=83","rptDate="&($B10-2)&"1231","rptType=1","currencyType=Cur=CNY","WssConvert=0","WssDivide=8","showcodes=N","cols=1;rows=1") -> 496.29135 | E10: =[1]!wss($A10:$A10,"hks_stm_is","item=83","rptDate="&($B10-1)&"1231","rptType=1","currencyType=Cur=CNY","WssConvert=0","WssDivide=8","showcodes=N","cols=1;rows=1") -> 657.63174 | F10: =[1]!wss($A10:$A10,"hks_stm_is","item=61","rptDate="&($B10-3)&"1231","rptType=1","currencyType=Cur=CNY","WssConvert=0","WssDivide=8","showcodes=N","cols=1;rows=1") -> -4.15333 | G10: =[1]!wss($A10:$A10,"hks_stm_is","item=61","rptDate="&($B10-2)&"1231","rptType=1","currencyType=Cur=CNY","WssConvert=0","WssDivide=8","showcodes=N","cols=1;rows=1") -> -4.05287 | H10: =[1]!wss($A10:$A10,"hks_stm_is","item=61","rptDate="&($B10-1)&"1231","rptType=1","currencyType=Cur=CNY","WssConvert=0","WssDivide=8","showcodes=N","cols=1;rows=1") -> -3.49881 | I10: =[1]!wss($A10:$A10,"hks_fa_grossprofitmargin","rptDate="&($B10-3)&"1231","WssConvert=0","showcodes=N","cols=1;rows=1") -> 2.9315 | J10: =[1]!wss($A10:$A10,"hks_fa_grossprofitmargin","rptDate="&($B10-2)&"1231","WssConvert=0","showcodes=N","cols=1;rows=1") -> 2.7091 | K10: =[1]!wss($A10:$A10,"hks_fa_grossprofitmargin","rptDate="&($B10-1)&"1231","WssConvert=0","showcodes=N","cols=1;rows=1") -> 2.8404 | L10: =[1]!wss($A10:$A10,"hks_fa_roe","rptDate="&($B10-1)&"1231","WssConvert=0","showcodes=N","cols=1;rows=1") | M10: =[1]!wss($A10:$A10,"hks_fa_debttoassets","rptDate="&($B10-1)&"1231","WssConvert=0","showcodes=N","cols=1;rows=1") -> 106.7093 | P10: 824.3252 | Q10: 600.59328 | R10: 522.97458 | S10: 4.48275 | T10: 2.69738 | U10: 3.00294 | V10: 3.3236 | W10: 3.8444 | X10: 4.4582
A11: 6963.HK | B11: =IFERROR(YEAR(VLOOKUP($A11,'01_ipo_master'!$A:$C,3,FALSE)),YEAR(VLOOKUP("0"&$A11,'01_ipo_master'!$A:$C,3,FALSE))) -> 2022 | C11: =[1]!wss($A11:$A11,"hks_stm_is","item=83","rptDate="&($B11-3)&"1231","rptType=1","currencyType=Cur=CNY","WssConvert=0","WssDivide=8","showcodes=N","cols=1;rows=1") -> 968.09 | D11: =[1]!wss($A11:$A11,"hks_stm_is","item=83","rptDate="&($B11-2)&"1231","rptType=1","currencyType=Cur=CNY","WssConvert=0","WssDivide=8","showcodes=N","cols=1;rows=1") -> 1063.49 | E11: =[1]!wss($A11:$A11,"hks_stm_is","item=83","rptDate="&($B11-1)&"1231","rptType=1","currencyType=Cur=CNY","WssConvert=0","WssDivide=8","showcodes=N","cols=1;rows=1") -> 1139.72 | F11: =[1]!wss($A11:$A11,"hks_stm_is","item=61","rptDate="&($B11-3)&"1231","rptType=1","currencyType=Cur=CNY","WssConvert=0","WssDivide=8","showcodes=N","cols=1;rows=1") -> 50.86 | G11: =[1]!wss($A11:$A11,"hks_stm_is","item=61","rptDate="&($B11-2)&"1231","rptType=1","currencyType=Cur=CNY","WssConvert=0","WssDivide=8","showcodes=N","cols=1;rows=1") -> 56.19 | H11: =[1]!wss($A11:$A11,"hks_stm_is","item=61","rptDate="&($B11-1)&"1231","rptType=1","currencyType=Cur=CNY","WssConvert=0","WssDivide=8","showcodes=N","cols=1;rows=1") -> 58.83 | I11: =[1]!wss($A11:$A11,"hks_fa_grossprofitmargin","rptDate="&($B11-3)&"1231","WssConvert=0","showcodes=N","cols=1;rows=1") | J11: =[1]!wss($A11:$A11,"hks_fa_grossprofitmargin","rptDate="&($B11-2)&"1231","WssConvert=0","showcodes=N","cols=1;rows=1") | K11: =[1]!wss($A11:$A11,"hks_fa_grossprofitmargin","rptDate="&($B11-1)&"1231","WssConvert=0","showcodes=N","cols=1;rows=1") | L11: =[1]!wss($A11:$A11,"hks_fa_roe","rptDate="&($B11-1)&"1231","WssConvert=0","showcodes=N","cols=1;rows=1") -> 10.3388 | M11: =[1]!wss($A11:$A11,"hks_fa_debttoassets","rptDate="&($B11-1)&"1231","WssConvert=0","showcodes=N","cols=1;rows=1") -> 86.5913 | P11: 786.88 | Q11: 837.41 | R11: 851.32 | S11: 37.38 | T11: 54.49 | U11: 63.07
A12: 2423.HK | B12: =IFERROR(YEAR(VLOOKUP($A12,'01_ipo_master'!$A:$C,3,FALSE)),YEAR(VLOOKUP("0"&$A12,'01_ipo_master'!$A:$C,3,FALSE))) -> 2022 | C12: =[1]!wss($A12:$A12,"hks_stm_is","item=83","rptDate="&($B12-3)&"1231","rptType=1","currencyType=Cur=CNY","WssConvert=0","WssDivide=8","showcodes=N","cols=1;rows=1") -> 460.14906 | D12: =[1]!wss($A12:$A12,"hks_stm_is","item=83","rptDate="&($B12-2)&"1231","rptType=1","currencyType=Cur=CNY","WssConvert=0","WssDivide=8","showcodes=N","cols=1;rows=1") -> 704.80978 | E12: =[1]!wss($A12:$A12,"hks_stm_is","item=83","rptDate="&($B12-1)&"1231","rptType=1","currencyType=Cur=CNY","WssConvert=0","WssDivide=8","showcodes=N","cols=1;rows=1") -> 807.52439 | F12: =[1]!wss($A12:$A12,"hks_stm_is","item=61","rptDate="&($B12-3)&"1231","rptType=1","currencyType=Cur=CNY","WssConvert=0","WssDivide=8","showcodes=N","cols=1;rows=1") -> -21.83546 | G12: =[1]!wss($A12:$A12,"hks_stm_is","item=61","rptDate="&($B12-2)&"1231","rptType=1","currencyType=Cur=CNY","WssConvert=0","WssDivide=8","showcodes=N","cols=1;rows=1") -> 27.77592 | H12: =[1]!wss($A12:$A12,"hks_stm_is","item=61","rptDate="&($B12-1)&"1231","rptType=1","currencyType=Cur=CNY","WssConvert=0","WssDivide=8","showcodes=N","cols=1;rows=1") -> -5.24129 | I12: =[1]!wss($A12:$A12,"hks_fa_grossprofitmargin","rptDate="&($B12-3)&"1231","WssConvert=0","showcodes=N","cols=1;rows=1") -> 24.4878 | J12: =[1]!wss($A12:$A12,"hks_fa_grossprofitmargin","rptDate="&($B12-2)&"1231","WssConvert=0","showcodes=N","cols=1;rows=1") -> 23.9211 | K12: =[1]!wss($A12:$A12,"hks_fa_grossprofitmargin","rptDate="&($B12-1)&"1231","WssConvert=0","showcodes=N","cols=1;rows=1") -> 19.59 | L12: =[1]!wss($A12:$A12,"hks_fa_roe","rptDate="&($B12-1)&"1231","WssConvert=0","showcodes=N","cols=1;rows=1") -> -0.7838 | M12: =[1]!wss($A12:$A12,"hks_fa_debttoassets","rptDate="&($B12-1)&"1231","WssConvert=0","showcodes=N","cols=1;rows=1") -> 33.1576 | P12: 777.76932 | Q12: 934.57498 | R12: 945.80205 | S12: 58.83224 | T12: 40.649 | U12: 29.93975 | V12: 27.9235 | W12: 24.5503 | X12: 21.3703
A13: 6031.HK | B13: =IFERROR(YEAR(VLOOKUP($A13,'01_ipo_master'!$A:$C,3,FALSE)),YEAR(VLOOKUP("0"&$A13,'01_ipo_master'!$A:$C,3,FALSE))) -> 2025 | C13: =[1]!wss($A13:$A13,"hks_stm_is","item=83","rptDate="&($B13-3)&"1231","rptType=1","currencyType=Cur=CNY","WssConvert=0","WssDivide=8","showcodes=N","cols=1;rows=1") -> 808.3853 | D13: =[1]!wss($A13:$A13,"hks_stm_is","item=83","rptDate="&($B13-2)&"1231","rptType=1","currencyType=Cur=CNY","WssConvert=0","WssDivide=8","showcodes=N","cols=1;rows=1") -> 740.18936 | E13: =[1]!wss($A13:$A13,"hks_stm_is","item=83","rptDate="&($B13-1)&"1231","rptType=1","currencyType=Cur=CNY","WssConvert=0","WssDivide=8","showcodes=N","cols=1;rows=1") -> 783.83379 | F13: =[1]!wss($A13:$A13,"hks_stm_is","item=61","rptDate="&($B13-3)&"1231","rptType=1","currencyType=Cur=CNY","WssConvert=0","WssDivide=8","showcodes=N","cols=1;rows=1") -> 43.01041 | G13: =[1]!wss($A13:$A13,"hks_stm_is","item=61","rptDate="&($B13-2)&"1231","rptType=1","currencyType=Cur=CNY","WssConvert=0","WssDivide=8","showcodes=N","cols=1;rows=1") -> 45.27451 | H13: =[1]!wss($A13:$A13,"hks_stm_is","item=61","rptDate="&($B13-1)&"1231","rptType=1","currencyType=Cur=CNY","WssConvert=0","WssDivide=8","showcodes=N","cols=1;rows=1") -> 59.75451 | I13: =[1]!wss($A13:$A13,"hks_fa_grossprofitmargin","rptDate="&($B13-3)&"1231","WssConvert=0","showcodes=N","cols=1;rows=1") -> 22.6331 | J13: =[1]!wss($A13:$A13,"hks_fa_grossprofitmargin","rptDate="&($B13-2)&"1231","WssConvert=0","showcodes=N","cols=1;rows=1") -> 26.4476 | K13: =[1]!wss($A13:$A13,"hks_fa_grossprofitmargin","rptDate="&($B13-1)&"1231","WssConvert=0","showcodes=N","cols=1;rows=1") -> 26.6676 | L13: =[1]!wss($A13:$A13,"hks_fa_roe","rptDate="&($B13-1)&"1231","WssConvert=0","showcodes=N","cols=1;rows=1") -> 8.5374 | M13: =[1]!wss($A13:$A13,"hks_fa_debttoassets","rptDate="&($B13-1)&"1231","WssConvert=0","showcodes=N","cols=1;rows=1") -> 52.0184 | P13: 740.18936 | Q13: 783.83379 | R13: 896.99505 | S13: 45.27451 | T13: 59.75451 | U13: 84.08057 | V13: 26.4476 | W13: 26.6676 | X13: 27.724
A14: 1880.HK | B14: =IFERROR(YEAR(VLOOKUP($A14,'01_ipo_master'!$A:$C,3,FALSE)),YEAR(VLOOKUP("0"&$A14,'01_ipo_master'!$A:$C,3,FALSE))) -> 2022 | C14: =[1]!wss($A14:$A14,"hks_stm_is","item=83","rptDate="&($B14-3)&"1231","rptType=1","currencyType=Cur=CNY","WssConvert=0","WssDivide=8","showcodes=N","cols=1;rows=1") -> 480.64669 | D14: =[1]!wss($A14:$A14,"hks_stm_is","item=83","rptDate="&($B14-2)&"1231","rptType=1","currencyType=Cur=CNY","WssConvert=0","WssDivide=8","showcodes=N","cols=1;rows=1") -> 525.97807 | E14: =[1]!wss($A14:$A14,"hks_stm_is","item=83","rptDate="&($B14-1)&"1231","rptType=1","currencyType=Cur=CNY","WssConvert=0","WssDivide=8","showcodes=N","cols=1;rows=1") -> 676.75515 | F14: =[1]!wss($A14:$A14,"hks_stm_is","item=61","rptDate="&($B14-3)&"1231","rptType=1","currencyType=Cur=CNY","WssConvert=0","WssDivide=8","showcodes=N","cols=1;rows=1") -> 44.97573 | G14: =[1]!wss($A14:$A14,"hks_stm_is","item=61","rptDate="&($B14-2)&"1231","rptType=1","currencyType=Cur=CNY","WssConvert=0","WssDivide=8","showcodes=N","cols=1;rows=1") -> 59.31348 | H14: =[1]!wss($A14:$A14,"hks_stm_is","item=61","rptDate="&($B14-1)&"1231","rptType=1","currencyType=Cur=CNY","WssConvert=0","WssDivide=8","showcodes=N","cols=1;rows=1") -> 97.26557 | I14: =[1]!wss($A14:$A14,"hks_fa_grossprofitmargin","rptDate="&($B14-3)&"1231","WssConvert=0","showcodes=N","cols=1;rows=1") -> 51.0755 | J14: =[1]!wss($A14:$A14,"hks_fa_grossprofitmargin","rptDate="&($B14-2)&"1231","WssConvert=0","showcodes=N","cols=1;rows=1") -> 38.9151 | K14: =[1]!wss($A14:$A14,"hks_fa_grossprofitmargin","rptDate="&($B14-1)&"1231","WssConvert=0","showcodes=N","cols=1;rows=1") -> 32.9428 | L14: =[1]!wss($A14:$A14,"hks_fa_roe","rptDate="&($B14-1)&"1231","WssConvert=0","showcodes=N","cols=1;rows=1") -> 38.02 | M14: =[1]!wss($A14:$A14,"hks_fa_debttoassets","rptDate="&($B14-1)&"1231","WssConvert=0","showcodes=N","cols=1;rows=1") -> 37.5351 | P14: 675.40105 | Q14: 564.73848 | R14: 536.93579 | S14: 67.90027 | T14: 43.23643 | U14: 36.43905 | V14: 30.8747 | W14: 30.7165 | X14: 31.7575
A15: 1519.HK | B15: =IFERROR(YEAR(VLOOKUP($A15,'01_ipo_master'!$A:$C,3,FALSE)),YEAR(VLOOKUP("0"&$A15,'01_ipo_master'!$A:$C,3,FALSE))) -> 2023 | C15: =[1]!wss($A15:$A15,"hks_stm_is","item=83","rptDate="&($B15-3)&"1231","rptType=1","currencyType=Cur=CNY","WssConvert=0","WssDivide=8","showcodes=N","cols=1;rows=1") -> 100.18495 | D15: =[1]!wss($A15:$A15,"hks_stm_is","item=83","rptDate="&($B15-2)&"1231","rptType=1","currencyType=Cur=CNY","WssConvert=0","WssDivide=8","showcodes=N","cols=1;rows=1") -> 309.33621 | E15: =[1]!wss($A15:$A15,"hks_stm_is","item=83","rptDate="&($B15-1)&"1231","rptType=1","currencyType=Cur=CNY","WssConvert=0","WssDivide=8","showcodes=N","cols=1;rows=1") -> 506.14729 | F15: =[1]!wss($A15:$A15,"hks_stm_is","item=61","rptDate="&($B15-3)&"1231","rptType=1","currencyType=Cur=CNY","WssConvert=0","WssDivide=8","showcodes=N","cols=1;rows=1") -> -36.854984 | G15: =[1]!wss($A15:$A15,"hks_stm_is","item=61","rptDate="&($B15-2)&"1231","rptType=1","currencyType=Cur=CNY","WssConvert=0","WssDivide=8","showcodes=N","cols=1;rows=1") -> -385.5375 | H15: =[1]!wss($A15:$A15,"hks_stm_is","item=61","rptDate="&($B15-1)&"1231","rptType=1","currencyType=Cur=CNY","WssConvert=0","WssDivide=8","showcodes=N","cols=1;rows=1") -> 115.34548 | I15: =[1]!wss($A15:$A15,"hks_fa_grossprofitmargin","rptDate="&($B15-3)&"1231","WssConvert=0","showcodes=N","cols=1;rows=1") -> -17.0303 | J15: =[1]!wss($A15:$A15,"hks_fa_grossprofitmargin","rptDate="&($B15-2)&"1231","WssConvert=0","showcodes=N","cols=1;rows=1") -> -11.2277 | K15: =[1]!wss($A15:$A15,"hks_fa_grossprofitmargin","rptDate="&($B15-1)&"1231","WssConvert=0","showcodes=N","cols=1;rows=1") -> -3.7185 | L15: =[1]!wss($A15:$A15,"hks_fa_roe","rptDate="&($B15-1)&"1231","WssConvert=0","showcodes=N","cols=1;rows=1") | M15: =[1]!wss($A15:$A15,"hks_fa_debttoassets","rptDate="&($B15-1)&"1231","WssConvert=0","showcodes=N","cols=1;rows=1") -> 183.9727 | P15: 626.7659 | Q15: 737.46543 | R15: 854.54787 | S15: -77.979677 | T15: 7.2285832 | U15: 13.945983 | V15: 5.3428 | W15: 10.5098 | X15: 12.0307
A16: 0699.HK | B16: =IFERROR(YEAR(VLOOKUP($A16,'01_ipo_master'!$A:$C,3,FALSE)),YEAR(VLOOKUP("0"&$A16,'01_ipo_master'!$A:$C,3,FALSE))) -> 2025 | C16: =[1]!wss($A16:$A16,"hks_stm_is","item=83","rptDate="&($B16-3)&"1231","rptType=1","currencyType=Cur=CNY","WssConvert=0","WssDivide=8","showcodes=N","cols=1;rows=1") -> 497.93352 | D16: =[1]!wss($A16:$A16,"hks_stm_is","item=83","rptDate="&($B16-2)&"1231","rptType=1","currencyType=Cur=CNY","WssConvert=0","WssDivide=8","showcodes=N","cols=1;rows=1") -> 557.28476 | E16: =[1]!wss($A16:$A16,"hks_stm_is","item=83","rptDate="&($B16-1)&"1231","rptType=1","currencyType=Cur=CNY","WssConvert=0","WssDivide=8","showcodes=N","cols=1;rows=1") -> 558.63577 | F16: =[1]!wss($A16:$A16,"hks_stm_is","item=61","rptDate="&($B16-3)&"1231","rptType=1","currencyType=Cur=CNY","WssConvert=0","WssDivide=8","showcodes=N","cols=1;rows=1") -> 3.94184 | G16: =[1]!wss($A16:$A16,"hks_stm_is","item=61","rptDate="&($B16-2)&"1231","rptType=1","currencyType=Cur=CNY","WssConvert=0","WssDivide=8","showcodes=N","cols=1;rows=1") -> 10.83191 | H16: =[1]!wss($A16:$A16,"hks_stm_is","item=61","rptDate="&($B16-1)&"1231","rptType=1","currencyType=Cur=CNY","WssConvert=0","WssDivide=8","showcodes=N","cols=1;rows=1") -> 9.6047 | I16: =[1]!wss($A16:$A16,"hks_fa_grossprofitmargin","rptDate="&($B16-3)&"1231","WssConvert=0","showcodes=N","cols=1;rows=1") -> 11.13 | J16: =[1]!wss($A16:$A16,"hks_fa_grossprofitmargin","rptDate="&($B16-2)&"1231","WssConvert=0","showcodes=N","cols=1;rows=1") -> 14.4575 | K16: =[1]!wss($A16:$A16,"hks_fa_grossprofitmargin","rptDate="&($B16-1)&"1231","WssConvert=0","showcodes=N","cols=1;rows=1") -> 16.2248 | L16: =[1]!wss($A16:$A16,"hks_fa_roe","rptDate="&($B16-1)&"1231","WssConvert=0","showcodes=N","cols=1;rows=1") -> 7.0786 | M16: =[1]!wss($A16:$A16,"hks_fa_debttoassets","rptDate="&($B16-1)&"1231","WssConvert=0","showcodes=N","cols=1;rows=1") -> 69.0715 | P16: 557.28476 | Q16: 558.63577 | R16: 611.82689 | S16: 10.83191 | T16: 9.6047 | U16: 13.3582 | V16: 14.4575 | W16: 16.2248 | X16: 18.2994
A17: 9866.HK | B17: =IFERROR(YEAR(VLOOKUP($A17,'01_ipo_master'!$A:$C,3,FALSE)),YEAR(VLOOKUP("0"&$A17,'01_ipo_master'!$A:$C,3,FALSE))) -> 2022 | C17: =[1]!wss($A17:$A17,"hks_stm_is","item=83","rptDate="&($B17-3)&"1231","rptType=1","currencyType=Cur=CNY","WssConvert=0","WssDivide=8","showcodes=N","cols=1;rows=1") -> 78.24904 | D17: =[1]!wss($A17:$A17,"hks_stm_is","item=83","rptDate="&($B17-2)&"1231","rptType=1","currencyType=Cur=CNY","WssConvert=0","WssDivide=8","showcodes=N","cols=1;rows=1") -> 162.57933 | E17: =[1]!wss($A17:$A17,"hks_stm_is","item=83","rptDate="&($B17-1)&"1231","rptType=1","currencyType=Cur=CNY","WssConvert=0","WssDivide=8","showcodes=N","cols=1;rows=1") -> 361.36423 | F17: =[1]!wss($A17:$A17,"hks_stm_is","item=61","rptDate="&($B17-3)&"1231","rptType=1","currencyType=Cur=CNY","WssConvert=0","WssDivide=8","showcodes=N","cols=1;rows=1") -> -114.13101 | G17: =[1]!wss($A17:$A17,"hks_stm_is","item=61","rptDate="&($B17-2)&"1231","rptType=1","currencyType=Cur=CNY","WssConvert=0","WssDivide=8","showcodes=N","cols=1;rows=1") -> -56.1079 | H17: =[1]!wss($A17:$A17,"hks_stm_is","item=61","rptDate="&($B17-1)&"1231","rptType=1","currencyType=Cur=CNY","WssConvert=0","WssDivide=8","showcodes=N","cols=1;rows=1") -> -105.72309 | I17: =[1]!wss($A17:$A17,"hks_fa_grossprofitmargin","rptDate="&($B17-3)&"1231","WssConvert=0","showcodes=N","cols=1;rows=1") -> -15.3206 | J17: =[1]!wss($A17:$A17,"hks_fa_grossprofitmargin","rptDate="&($B17-2)&"1231","WssConvert=0","showcodes=N","cols=1;rows=1") -> 11.5231 | K17: =[1]!wss($A17:$A17,"hks_fa_grossprofitmargin","rptDate="&($B17-1)&"1231","WssConvert=0","showcodes=N","cols=1;rows=1") -> 18.8769 | L17: =[1]!wss($A17:$A17,"hks_fa_roe","rptDate="&($B17-1)&"1231","WssConvert=0","showcodes=N","cols=1;rows=1") -> -34.171 | M17: =[1]!wss($A17:$A17,"hks_fa_debttoassets","rptDate="&($B17-1)&"1231","WssConvert=0","showcodes=N","cols=1;rows=1") -> 54.0761 | P17: 556.17933 | Q17: 657.31559 | R17: 874.8751 | S17: -211.46967 | T17: -226.57692 | U17: -155.70678 | V17: 5.4871 | W17: 9.8777 | X17: 13.6199
A18: 6613.HK | B18: =IFERROR(YEAR(VLOOKUP($A18,'01_ipo_master'!$A:$C,3,FALSE)),YEAR(VLOOKUP("0"&$A18,'01_ipo_master'!$A:$C,3,FALSE))) -> 2025 | C18: =[1]!wss($A18:$A18,"hks_stm_is","item=83","rptDate="&($B18-3)&"1231","rptType=1","currencyType=Cur=CNY","WssConvert=0","WssDivide=8","showcodes=N","cols=1;rows=1") -> 466.98546 | D18: =[1]!wss($A18:$A18,"hks_stm_is","item=83","rptDate="&($B18-2)&"1231","rptType=1","currencyType=Cur=CNY","WssConvert=0","WssDivide=8","showcodes=N","cols=1;rows=1") -> 544.90734 | E18: =[1]!wss($A18:$A18,"hks_stm_is","item=83","rptDate="&($B18-1)&"1231","rptType=1","currencyType=Cur=CNY","WssConvert=0","WssDivide=8","showcodes=N","cols=1;rows=1") -> 698.96776 | F18: =[1]!wss($A18:$A18,"hks_stm_is","item=61","rptDate="&($B18-3)&"1231","rptType=1","currencyType=Cur=CNY","WssConvert=0","WssDivide=8","showcodes=N","cols=1;rows=1") -> 24.48037 | G18: =[1]!wss($A18:$A18,"hks_stm_is","item=61","rptDate="&($B18-2)&"1231","rptType=1","currencyType=Cur=CNY","WssConvert=0","WssDivide=8","showcodes=N","cols=1;rows=1") -> 30.21342 | H18: =[1]!wss($A18:$A18,"hks_stm_is","item=61","rptDate="&($B18-1)&"1231","rptType=1","currencyType=Cur=CNY","WssConvert=0","WssDivide=8","showcodes=N","cols=1;rows=1") -> 36.23901 | I18: =[1]!wss($A18:$A18,"hks_fa_grossprofitmargin","rptDate="&($B18-3)&"1231","WssConvert=0","showcodes=N","cols=1;rows=1") -> 18.3023 | J18: =[1]!wss($A18:$A18,"hks_fa_grossprofitmargin","rptDate="&($B18-2)&"1231","WssConvert=0","showcodes=N","cols=1;rows=1") -> 15.5841 | K18: =[1]!wss($A18:$A18,"hks_fa_grossprofitmargin","rptDate="&($B18-1)&"1231","WssConvert=0","showcodes=N","cols=1;rows=1") -> 14.5693 | L18: =[1]!wss($A18:$A18,"hks_fa_roe","rptDate="&($B18-1)&"1231","WssConvert=0","showcodes=N","cols=1;rows=1") -> 7.6296 | M18: =[1]!wss($A18:$A18,"hks_fa_debttoassets","rptDate="&($B18-1)&"1231","WssConvert=0","showcodes=N","cols=1;rows=1") -> 39.7084 | P18: 544.90734 | Q18: 698.96776 | R18: 744.09732 | S18: 30.21342 | T18: 36.23901 | U18: 40.17827 | V18: 15.5841 | W18: 14.5693 | X18: 14.9318
A19: 9696.HK | B19: =IFERROR(YEAR(VLOOKUP($A19,'01_ipo_master'!$A:$C,3,FALSE)),YEAR(VLOOKUP("0"&$A19,'01_ipo_master'!$A:$C,3,FALSE))) -> 2022 | C19: =[1]!wss($A19:$A19,"hks_stm_is","item=83","rptDate="&($B19-3)&"1231","rptType=1","currencyType=Cur=CNY","WssConvert=0","WssDivide=8","showcodes=N","cols=1;rows=1") -> 48.16361 | D19: =[1]!wss($A19:$A19,"hks_stm_is","item=83","rptDate="&($B19-2)&"1231","rptType=1","currencyType=Cur=CNY","WssConvert=0","WssDivide=8","showcodes=N","cols=1;rows=1") -> 32.15231 | E19: =[1]!wss($A19:$A19,"hks_stm_is","item=83","rptDate="&($B19-1)&"1231","rptType=1","currencyType=Cur=CNY","WssConvert=0","WssDivide=8","showcodes=N","cols=1;rows=1") -> 75.97863 | F19: =[1]!wss($A19:$A19,"hks_stm_is","item=61","rptDate="&($B19-3)&"1231","rptType=1","currencyType=Cur=CNY","WssConvert=0","WssDivide=8","showcodes=N","cols=1;rows=1") -> -59.81435 | G19: =[1]!wss($A19:$A19,"hks_stm_is","item=61","rptDate="&($B19-2)&"1231","rptType=1","currencyType=Cur=CNY","WssConvert=0","WssDivide=8","showcodes=N","cols=1;rows=1") -> -18.3092 | H19: =[1]!wss($A19:$A19,"hks_stm_is","item=61","rptDate="&($B19-1)&"1231","rptType=1","currencyType=Cur=CNY","WssConvert=0","WssDivide=8","showcodes=N","cols=1;rows=1") -> 36.49185 | I19: =[1]!wss($A19:$A19,"hks_fa_grossprofitmargin","rptDate="&($B19-3)&"1231","WssConvert=0","showcodes=N","cols=1;rows=1") -> 56.0024 | J19: =[1]!wss($A19:$A19,"hks_fa_grossprofitmargin","rptDate="&($B19-2)&"1231","WssConvert=0","showcodes=N","cols=1;rows=1") -> 41.2721 | K19: =[1]!wss($A19:$A19,"hks_fa_grossprofitmargin","rptDate="&($B19-1)&"1231","WssConvert=0","showcodes=N","cols=1;rows=1") -> 61.7 | L19: =[1]!wss($A19:$A19,"hks_fa_roe","rptDate="&($B19-1)&"1231","WssConvert=0","showcodes=N","cols=1;rows=1") -> 37.3156 | M19: =[1]!wss($A19:$A19,"hks_fa_debttoassets","rptDate="&($B19-1)&"1231","WssConvert=0","showcodes=N","cols=1;rows=1") -> 56.7842 | P19: 404.48303 | Q19: 130.29739 | R19: 103.22472 | S19: 72.78343 | T19: -87.27021 | U19: 4.5843 | V19: 84.9178 | W19: 45.9818 | X19: 39.3166
A20: 9927.HK | B20: =IFERROR(YEAR(VLOOKUP($A20,'01_ipo_master'!$A:$C,3,FALSE)),YEAR(VLOOKUP("0"&$A20,'01_ipo_master'!$A:$C,3,FALSE))) -> 2025 | C20: =[1]!wss($A20:$A20,"hks_stm_is","item=83","rptDate="&($B20-3)&"1231","rptType=1","currencyType=Cur=CNY","WssConvert=0","WssDivide=8","showcodes=N","cols=1;rows=1") -> 340.56074 | D20: =[1]!wss($A20:$A20,"hks_stm_is","item=83","rptDate="&($B20-2)&"1231","rptType=1","currencyType=Cur=CNY","WssConvert=0","WssDivide=8","showcodes=N","cols=1;rows=1") -> 357.88885 | E20: =[1]!wss($A20:$A20,"hks_stm_is","item=83","rptDate="&($B20-1)&"1231","rptType=1","currencyType=Cur=CNY","WssConvert=0","WssDivide=8","showcodes=N","cols=1;rows=1") -> 1451.1362 | F20: =[1]!wss($A20:$A20,"hks_stm_is","item=61","rptDate="&($B20-3)&"1231","rptType=1","currencyType=Cur=CNY","WssConvert=0","WssDivide=8","showcodes=N","cols=1;rows=1") -> -38.31866 | G20: =[1]!wss($A20:$A20,"hks_stm_is","item=61","rptDate="&($B20-2)&"1231","rptType=1","currencyType=Cur=CNY","WssConvert=0","WssDivide=8","showcodes=N","cols=1;rows=1") -> -24.49687 | H20: =[1]!wss($A20:$A20,"hks_stm_is","item=61","rptDate="&($B20-1)&"1231","rptType=1","currencyType=Cur=CNY","WssConvert=0","WssDivide=8","showcodes=N","cols=1;rows=1") -> 59.45945 | I20: =[1]!wss($A20:$A20,"hks_fa_grossprofitmargin","rptDate="&($B20-3)&"1231","WssConvert=0","showcodes=N","cols=1;rows=1") -> 8.0092 | J20: =[1]!wss($A20:$A20,"hks_fa_grossprofitmargin","rptDate="&($B20-2)&"1231","WssConvert=0","showcodes=N","cols=1;rows=1") -> 7.1841 | K20: =[1]!wss($A20:$A20,"hks_fa_grossprofitmargin","rptDate="&($B20-1)&"1231","WssConvert=0","showcodes=N","cols=1;rows=1") -> 23.8093 | L20: =[1]!wss($A20:$A20,"hks_fa_roe","rptDate="&($B20-1)&"1231","WssConvert=0","showcodes=N","cols=1;rows=1") -> 50.2402 | M20: =[1]!wss($A20:$A20,"hks_fa_debttoassets","rptDate="&($B20-1)&"1231","WssConvert=0","showcodes=N","cols=1;rows=1") -> 87.3834 | P20: 357.88885 | Q20: 1451.1362 | R20: 1648.8801 | S20: -24.49687 | T20: 59.45945 | U20: 59.56787 | V20: 7.1841 | W20: 23.8093 | X20: 26.8813
A21: 2579.HK | B21: =IFERROR(YEAR(VLOOKUP($A21,'01_ipo_master'!$A:$C,3,FALSE)),YEAR(VLOOKUP("0"&$A21,'01_ipo_master'!$A:$C,3,FALSE))) -> 2025 | C21: =[1]!wss($A21:$A21,"hks_stm_is","item=83","rptDate="&($B21-3)&"1231","rptType=1","currencyType=Cur=CNY","WssConvert=0","WssDivide=8","showcodes=N","cols=1;rows=1") -> 303.43742 | D21: =[1]!wss($A21:$A21,"hks_stm_is","item=83","rptDate="&($B21-2)&"1231","rptType=1","currencyType=Cur=CNY","WssConvert=0","WssDivide=8","showcodes=N","cols=1;rows=1") -> 342.73223 | E21: =[1]!wss($A21:$A21,"hks_stm_is","item=83","rptDate="&($B21-1)&"1231","rptType=1","currencyType=Cur=CNY","WssConvert=0","WssDivide=8","showcodes=N","cols=1;rows=1") -> 402.2289 | F21: =[1]!wss($A21:$A21,"hks_stm_is","item=61","rptDate="&($B21-3)&"1231","rptType=1","currencyType=Cur=CNY","WssConvert=0","WssDivide=8","showcodes=N","cols=1;rows=1") -> 15.48644 | G21: =[1]!wss($A21:$A21,"hks_stm_is","item=61","rptDate="&($B21-2)&"1231","rptType=1","currencyType=Cur=CNY","WssConvert=0","WssDivide=8","showcodes=N","cols=1;rows=1") -> 19.47559 | H21: =[1]!wss($A21:$A21,"hks_stm_is","item=61","rptDate="&($B21-1)&"1231","rptType=1","currencyType=Cur=CNY","WssConvert=0","WssDivide=8","showcodes=N","cols=1;rows=1") -> 14.67224 | I21: =[1]!wss($A21:$A21,"hks_fa_grossprofitmargin","rptDate="&($B21-3)&"1231","WssConvert=0","showcodes=N","cols=1;rows=1") -> 11.141 | J21: =[1]!wss($A21:$A21,"hks_fa_grossprofitmargin","rptDate="&($B21-2)&"1231","WssConvert=0","showcodes=N","cols=1;rows=1") -> 13.3529 | K21: =[1]!wss($A21:$A21,"hks_fa_grossprofitmargin","rptDate="&($B21-1)&"1231","WssConvert=0","showcodes=N","cols=1;rows=1") -> 12.0382 | L21: =[1]!wss($A21:$A21,"hks_fa_roe","rptDate="&($B21-1)&"1231","WssConvert=0","showcodes=N","cols=1;rows=1") -> 7.342 | M21: =[1]!wss($A21:$A21,"hks_fa_debttoassets","rptDate="&($B21-1)&"1231","WssConvert=0","showcodes=N","cols=1;rows=1") -> 59.5466 | P21: 342.73223 | Q21: 402.2289 | R21: 481.39977 | S21: 19.47559 | T21: 14.67224 | U21: 15.707 | V21: 13.3529 | W21: 12.0382 | X21: 12.0024
A22: 6655.HK | B22: =IFERROR(YEAR(VLOOKUP($A22,'01_ipo_master'!$A:$C,3,FALSE)),YEAR(VLOOKUP("0"&$A22,'01_ipo_master'!$A:$C,3,FALSE))) -> 2022 | C22: =[1]!wss($A22:$A22,"hks_stm_is","item=83","rptDate="&($B22-3)&"1231","rptType=1","currencyType=Cur=CNY","WssConvert=0","WssDivide=8","showcodes=N","cols=1;rows=1") -> 314.39215 | D22: =[1]!wss($A22:$A22,"hks_stm_is","item=83","rptDate="&($B22-2)&"1231","rptType=1","currencyType=Cur=CNY","WssConvert=0","WssDivide=8","showcodes=N","cols=1;rows=1") -> 293.56516 | E22: =[1]!wss($A22:$A22,"hks_stm_is","item=83","rptDate="&($B22-1)&"1231","rptType=1","currencyType=Cur=CNY","WssConvert=0","WssDivide=8","showcodes=N","cols=1;rows=1") -> 324.64083 | F22: =[1]!wss($A22:$A22,"hks_stm_is","item=61","rptDate="&($B22-3)&"1231","rptType=1","currencyType=Cur=CNY","WssConvert=0","WssDivide=8","showcodes=N","cols=1;rows=1") -> 63.423043 | G22: =[1]!wss($A22:$A22,"hks_stm_is","item=61","rptDate="&($B22-2)&"1231","rptType=1","currencyType=Cur=CNY","WssConvert=0","WssDivide=8","showcodes=N","cols=1;rows=1") -> 56.305988 | H22: =[1]!wss($A22:$A22,"hks_stm_is","item=61","rptDate="&($B22-1)&"1231","rptType=1","currencyType=Cur=CNY","WssConvert=0","WssDivide=8","showcodes=N","cols=1;rows=1") -> 53.635257 | I22: =[1]!wss($A22:$A22,"hks_fa_grossprofitmargin","rptDate="&($B22-3)&"1231","WssConvert=0","showcodes=N","cols=1;rows=1") -> 40.7577 | J22: =[1]!wss($A22:$A22,"hks_fa_grossprofitmargin","rptDate="&($B22-2)&"1231","WssConvert=0","showcodes=N","cols=1;rows=1") -> 40.5916 | K22: =[1]!wss($A22:$A22,"hks_fa_grossprofitmargin","rptDate="&($B22-1)&"1231","WssConvert=0","showcodes=N","cols=1;rows=1") -> 34.1041 | L22: =[1]!wss($A22:$A22,"hks_fa_roe","rptDate="&($B22-1)&"1231","WssConvert=0","showcodes=N","cols=1;rows=1") -> 21.3256 | M22: =[1]!wss($A22:$A22,"hks_fa_debttoassets","rptDate="&($B22-1)&"1231","WssConvert=0","showcodes=N","cols=1;rows=1") -> 44.0951 | P22: 337.57087 | Q22: 342.17348 | R22: 353.4828 | S22: 27.621167 | T22: 24.162805 | U22: 28.53332 | V22: 26.7075 | W22: 24.6858 | X22: 30.2194
A23: 2602.HK | B23: =IFERROR(YEAR(VLOOKUP($A23,'01_ipo_master'!$A:$C,3,FALSE)),YEAR(VLOOKUP("0"&$A23,'01_ipo_master'!$A:$C,3,FALSE))) -> 2022 | C23: =[1]!wss($A23:$A23,"hks_stm_is","item=83","rptDate="&($B23-3)&"1231","rptType=1","currencyType=Cur=CNY","WssConvert=0","WssDivide=8","showcodes=N","cols=1;rows=1") -> 139.27289 | D23: =[1]!wss($A23:$A23,"hks_stm_is","item=83","rptDate="&($B23-2)&"1231","rptType=1","currencyType=Cur=CNY","WssConvert=0","WssDivide=8","showcodes=N","cols=1;rows=1") -> 181.45464 | E23: =[1]!wss($A23:$A23,"hks_stm_is","item=83","rptDate="&($B23-1)&"1231","rptType=1","currencyType=Cur=CNY","WssConvert=0","WssDivide=8","showcodes=N","cols=1;rows=1") -> 237.04539 | F23: =[1]!wss($A23:$A23,"hks_stm_is","item=61","rptDate="&($B23-3)&"1231","rptType=1","currencyType=Cur=CNY","WssConvert=0","WssDivide=8","showcodes=N","cols=1;rows=1") -> 10.19894 | G23: =[1]!wss($A23:$A23,"hks_stm_is","item=61","rptDate="&($B23-2)&"1231","rptType=1","currencyType=Cur=CNY","WssConvert=0","WssDivide=8","showcodes=N","cols=1;rows=1") -> 14.64039 | H23: =[1]!wss($A23:$A23,"hks_stm_is","item=61","rptDate="&($B23-1)&"1231","rptType=1","currencyType=Cur=CNY","WssConvert=0","WssDivide=8","showcodes=N","cols=1;rows=1") -> 16.67642 | I23: =[1]!wss($A23:$A23,"hks_fa_grossprofitmargin","rptDate="&($B23-3)&"1231","WssConvert=0","showcodes=N","cols=1;rows=1") -> 17.7234 | J23: =[1]!wss($A23:$A23,"hks_fa_grossprofitmargin","rptDate="&($B23-2)&"1231","WssConvert=0","showcodes=N","cols=1;rows=1") -> 18.5431 | K23: =[1]!wss($A23:$A23,"hks_fa_grossprofitmargin","rptDate="&($B23-1)&"1231","WssConvert=0","showcodes=N","cols=1;rows=1") -> 16.9588 | L23: =[1]!wss($A23:$A23,"hks_fa_roe","rptDate="&($B23-1)&"1231","WssConvert=0","showcodes=N","cols=1;rows=1") -> 20.6539 | M23: =[1]!wss($A23:$A23,"hks_fa_debttoassets","rptDate="&($B23-1)&"1231","WssConvert=0","showcodes=N","cols=1;rows=1") -> 64.098 | P23: 331.83458 | Q23: 362.23828 | R23: 372.7186 | S23: 19.54696 | T23: 11.49578 | U23: 6.94559 | V23: 14.5005 | W23: 12.9663 | X23: 12.2333
... A30: 1276.HK | B30: =IFERROR(YEAR(VLOOKUP($A30,'01_ipo_master'!$A:$C,3,FALSE)),YEAR(VLOOKUP("0"&$A30,'01_ipo_master'!$A:$C,3,FALSE))) -> 2025 | C30: =[1]!wss($A30:$A30,"hks_stm_is","item=83","rptDate="&($B30-3)&"1231","rptType=1","currencyType=Cur=CNY","WssConvert=0","WssDivide=8","showcodes=N","cols=1;rows=1") -> 212.75271 | D30: =[1]!wss($A30:$A30,"hks_stm_is","item=83","rptDate="&($B30-2)&"1231","rptType=1","currencyType=Cur=CNY","WssConvert=0","WssDivide=8","showcodes=N","cols=1;rows=1") -> 228.19785 | E30: =[1]!wss($A30:$A30,"hks_stm_is","item=83","rptDate="&($B30-1)&"1231","rptType=1","currencyType=Cur=CNY","WssConvert=0","WssDivide=8","showcodes=N","cols=1;rows=1") -> 279.84605 | F30: =[1]!wss($A30:$A30,"hks_stm_is","item=61","rptDate="&($B30-3)&"1231","rptType=1","currencyType=Cur=CNY","WssConvert=0","WssDivide=8","showcodes=N","cols=1;rows=1") -> 39.06374 | G30: =[1]!wss($A30:$A30,"hks_stm_is","item=61","rptDate="&($B30-2)&"1231","rptType=1","currencyType=Cur=CNY","WssConvert=0","WssDivide=8","showcodes=N","cols=1;rows=1") -> 43.02436 | H30: =[1]!wss($A30:$A30,"hks_stm_is","item=61","rptDate="&($B30-1)&"1231","rptType=1","currencyType=Cur=CNY","WssConvert=0","WssDivide=8","showcodes=N","cols=1;rows=1") -> 63.36527 | I30: =[1]!wss($A30:$A30,"hks_fa_grossprofitmargin","rptDate="&($B30-3)&"1231","WssConvert=0","showcodes=N","cols=1;rows=1") -> 83.6118 | J30: =[1]!wss($A30:$A30,"hks_fa_grossprofitmargin","rptDate="&($B30-2)&"1231","WssConvert=0","showcodes=N","cols=1;rows=1") -> 84.5518 | K30: =[1]!wss($A30:$A30,"hks_fa_grossprofitmargin","rptDate="&($B30-1)&"1231","WssConvert=0","showcodes=N","cols=1;rows=1") -> 86.249 | L30: =[1]!wss($A30:$A30,"hks_fa_roe","rptDate="&($B30-1)&"1231","WssConvert=0","showcodes=N","cols=1;rows=1") -> 14.7386 | M30: =[1]!wss($A30:$A30,"hks_fa_debttoassets","rptDate="&($B30-1)&"1231","WssConvert=0","showcodes=N","cols=1;rows=1") -> 8.0689 | P30: 228.19785 | Q30: 279.84605 | R30: 316.29416 | S30: 43.02436 | T30: 63.36527 | U30: 77.11055 | V30: 84.5518 | W30: 86.249 | X30: 86.207
A31: 6623.HK | B31: =IFERROR(YEAR(VLOOKUP($A31,'01_ipo_master'!$A:$C,3,FALSE)),YEAR(VLOOKUP("0"&$A31,'01_ipo_master'!$A:$C,3,FALSE))) -> 2023 | C31: =[1]!wss($A31:$A31,"hks_stm_is","item=83","rptDate="&($B31-3)&"1231","rptType=1","currencyType=Cur=CNY","WssConvert=0","WssDivide=8","showcodes=N","cols=1;rows=1") -> 461.30045 | D31: =[1]!wss($A31:$A31,"hks_stm_is","item=83","rptDate="&($B31-2)&"1231","rptType=1","currencyType=Cur=CNY","WssConvert=0","WssDivide=8","showcodes=N","cols=1;rows=1") -> 542.26808 | E31: =[1]!wss($A31:$A31,"hks_stm_is","item=83","rptDate="&($B31-1)&"1231","rptType=1","currencyType=Cur=CNY","WssConvert=0","WssDivide=8","showcodes=N","cols=1;rows=1") -> 403.26489 | F31: =[1]!wss($A31:$A31,"hks_stm_is","item=61","rptDate="&($B31-3)&"1231","rptType=1","currencyType=Cur=CNY","WssConvert=0","WssDivide=8","showcodes=N","cols=1;rows=1") -> 123.54114 | G31: =[1]!wss($A31:$A31,"hks_stm_is","item=61","rptDate="&($B31-2)&"1231","rptType=1","currencyType=Cur=CNY","WssConvert=0","WssDivide=8","showcodes=N","cols=1;rows=1") -> 168.0438 | H31: =[1]!wss($A31:$A31,"hks_stm_is","item=61","rptDate="&($B31-1)&"1231","rptType=1","currencyType=Cur=CNY","WssConvert=0","WssDivide=8","showcodes=N","cols=1;rows=1") -> 86.99369 | I31: =[1]!wss($A31:$A31,"hks_fa_grossprofitmargin","rptDate="&($B31-3)&"1231","WssConvert=0","showcodes=N","cols=1;rows=1") | J31: =[1]!wss($A31:$A31,"hks_fa_grossprofitmargin","rptDate="&($B31-2)&"1231","WssConvert=0","showcodes=N","cols=1;rows=1") | K31: =[1]!wss($A31:$A31,"hks_fa_grossprofitmargin","rptDate="&($B31-1)&"1231","WssConvert=0","showcodes=N","cols=1;rows=1") | L31: =[1]!wss($A31:$A31,"hks_fa_roe","rptDate="&($B31-1)&"1231","WssConvert=0","showcodes=N","cols=1;rows=1") -> 9.3419 | M31: =[1]!wss($A31:$A31,"hks_fa_debttoassets","rptDate="&($B31-1)&"1231","WssConvert=0","showcodes=N","cols=1;rows=1") -> 72.8609 | P31: 211.49451 | Q31: 118.16373 | R31: 13.70955 | S31: 8.86865 | T31: -38.7062 | U31: -20.97678
A32: 2245.HK | B32: =IFERROR(YEAR(VLOOKUP($A32,'01_ipo_master'!$A:$C,3,FALSE)),YEAR(VLOOKUP("0"&$A32,'01_ipo_master'!$A:$C,3,FALSE))) -> 2022 | C32: =[1]!wss($A32:$A32,"hks_stm_is","item=83","rptDate="&($B32-3)&"1231","rptType=1","currencyType=Cur=CNY","WssConvert=0","WssDivide=8","showcodes=N","cols=1;rows=1") -> 93.50441 | D32: =[1]!wss($A32:$A32,"hks_stm_is","item=83","rptDate="&($B32-2)&"1231","rptType=1","currencyType=Cur=CNY","WssConvert=0","WssDivide=8","showcodes=N","cols=1;rows=1") -> 77.55174 | E32: =[1]!wss($A32:$A32,"hks_stm_is","item=83","rptDate="&($B32-1)&"1231","rptType=1","currencyType=Cur=CNY","WssConvert=0","WssDivide=8","showcodes=N","cols=1;rows=1") -> 124.49318 | F32: =[1]!wss($A32:$A32,"hks_stm_is","item=61","rptDate="&($B32-3)&"1231","rptType=1","currencyType=Cur=CNY","WssConvert=0","WssDivide=8","showcodes=N","cols=1;rows=1") -> 5.65584 | G32: =[1]!wss($A32:$A32,"hks_stm_is","item=61","rptDate="&($B32-2)&"1231","rptType=1","currencyType=Cur=CNY","WssConvert=0","WssDivide=8","showcodes=N","cols=1;rows=1") -> 5.20156 | H32: =[1]!wss($A32:$A32,"hks_stm_is","item=61","rptDate="&($B32-1)&"1231","rptType=1","currencyType=Cur=CNY","WssConvert=0","WssDivide=8","showcodes=N","cols=1;rows=1") -> 10.99508 | I32: =[1]!wss($A32:$A32,"hks_fa_grossprofitmargin","rptDate="&($B32-3)&"1231","WssConvert=0","showcodes=N","cols=1;rows=1") -> 10.8918 | J32: =[1]!wss($A32:$A32,"hks_fa_grossprofitmargin","rptDate="&($B32-2)&"1231","WssConvert=0","showcodes=N","cols=1;rows=1") -> 12.2842 | K32: =[1]!wss($A32:$A32,"hks_fa_grossprofitmargin","rptDate="&($B32-1)&"1231","WssConvert=0","showcodes=N","cols=1;rows=1") -> 12.1768 | L32: =[1]!wss($A32:$A32,"hks_fa_roe","rptDate="&($B32-1)&"1231","WssConvert=0","showcodes=N","cols=1;rows=1") -> 48.5606 | M32: =[1]!wss($A32:$A32,"hks_fa_debttoassets","rptDate="&($B32-1)&"1231","WssConvert=0","showcodes=N","cols=1;rows=1") -> 57.874 | P32: 210.59316 | Q32: 292.32958 | R32: 402.39786 | S32: 10.51365 | T32: 17.7315 | U32: 28.57421 | V32: 16.0592 | W32: 18.3097 | X32: 19.1729
A33: 0501.HK | B33: =IFERROR(YEAR(VLOOKUP($A33,'01_ipo_master'!$A:$C,3,FALSE)),YEAR(VLOOKUP("0"&$A33,'01_ipo_master'!$A:$C,3,FALSE))) -> 2026 | C33: =[1]!wss($A33:$A33,"hks_stm_is","item=83","rptDate="&($B33-3)&"1231","rptType=1","currencyType=Cur=CNY","WssConvert=0","WssDivide=8","showcodes=N","cols=1;rows=1") -> 209.84259 | D33: =[1]!wss($A33:$A33,"hks_stm_is","item=83","rptDate="&($B33-2)&"1231","rptType=1","currencyType=Cur=CNY","WssConvert=0","WssDivide=8","showcodes=N","cols=1;rows=1") -> 257.06819 | E33: =[1]!wss($A33:$A33,"hks_stm_is","item=83","rptDate="&($B33-1)&"1231","rptType=1","currencyType=Cur=CNY","WssConvert=0","WssDivide=8","showcodes=N","cols=1;rows=1") -> 288.54806 | F33: =[1]!wss($A33:$A33,"hks_stm_is","item=61","rptDate="&($B33-3)&"1231","rptType=1","currencyType=Cur=CNY","WssConvert=0","WssDivide=8","showcodes=N","cols=1;rows=1") -> 5.55751 | G33: =[1]!wss($A33:$A33,"hks_stm_is","item=61","rptDate="&($B33-2)&"1231","rptType=1","currencyType=Cur=CNY","WssConvert=0","WssDivide=8","showcodes=N","cols=1;rows=1") -> 33.17582 | H33: =[1]!wss($A33:$A33,"hks_stm_is","item=61","rptDate="&($B33-1)&"1231","rptType=1","currencyType=Cur=CNY","WssConvert=0","WssDivide=8","showcodes=N","cols=1;rows=1") -> 40.454165 | I33: =[1]!wss($A33:$A33,"hks_fa_grossprofitmargin","rptDate="&($B33-3)&"1231","WssConvert=0","showcodes=N","cols=1;rows=1") -> 19.9364 | J33: =[1]!wss($A33:$A33,"hks_fa_grossprofitmargin","rptDate="&($B33-2)&"1231","WssConvert=0","showcodes=N","cols=1;rows=1") -> 28.1606 | K33: =[1]!wss($A33:$A33,"hks_fa_grossprofitmargin","rptDate="&($B33-1)&"1231","WssConvert=0","showcodes=N","cols=1;rows=1") -> 30.6349 | L33: =[1]!wss($A33:$A33,"hks_fa_roe","rptDate="&($B33-1)&"1231","WssConvert=0","showcodes=N","cols=1;rows=1") -> 15.4484 | M33: =[1]!wss($A33:$A33,"hks_fa_debttoassets","rptDate="&($B33-1)&"1231","WssConvert=0","showcodes=N","cols=1;rows=1") -> 35.4277 | P33: 209.84259 | Q33: 257.06819 | R33: 288.54806 | S33: 5.55751 | T33: 33.17582 | U33: 40.454165 | V33: 19.9364 | W33: 28.1606 | X33: 30.6349
A34: 2097.HK | B34: =IFERROR(YEAR(VLOOKUP($A34,'01_ipo_master'!$A:$C,3,FALSE)),YEAR(VLOOKUP("0"&$A34,'01_ipo_master'!$A:$C,3,FALSE))) -> 2025 | C34: =[1]!wss($A34:$A34,"hks_stm_is","item=83","rptDate="&($B34-3)&"1231","rptType=1","currencyType=Cur=CNY","WssConvert=0","WssDivide=8","showcodes=N","cols=1;rows=1") -> 135.75577 | D34: =[1]!wss($A34:$A34,"hks_stm_is","item=83","rptDate="&($B34-2)&"1231","rptType=1","currencyType=Cur=CNY","WssConvert=0","WssDivide=8","showcodes=N","cols=1;rows=1") -> 203.02465 | E34: =[1]!wss($A34:$A34,"hks_stm_is","item=83","rptDate="&($B34-1)&"1231","rptType=1","currencyType=Cur=CNY","WssConvert=0","WssDivide=8","showcodes=N","cols=1;rows=1") -> 248.28874 | F34: =[1]!wss($A34:$A34,"hks_stm_is","item=61","rptDate="&($B34-3)&"1231","rptType=1","currencyType=Cur=CNY","WssConvert=0","WssDivide=8","showcodes=N","cols=1;rows=1") -> 19.96715 | G34: =[1]!wss($A34:$A34,"hks_stm_is","item=61","rptDate="&($B34-2)&"1231","rptType=1","currencyType=Cur=CNY","WssConvert=0","WssDivide=8","showcodes=N","cols=1;rows=1") -> 31.37341 | H34: =[1]!wss($A34:$A34,"hks_stm_is","item=61","rptDate="&($B34-1)&"1231","rptType=1","currencyType=Cur=CNY","WssConvert=0","WssDivide=8","showcodes=N","cols=1;rows=1") -> 44.36504 | I34: =[1]!wss($A34:$A34,"hks_fa_grossprofitmargin","rptDate="&($B34-3)&"1231","WssConvert=0","showcodes=N","cols=1;rows=1") -> 28.3365 | J34: =[1]!wss($A34:$A34,"hks_fa_grossprofitmargin","rptDate="&($B34-2)&"1231","WssConvert=0","showcodes=N","cols=1;rows=1") -> 29.548 | K34: =[1]!wss($A34:$A34,"hks_fa_grossprofitmargin","rptDate="&($B34-1)&"1231","WssConvert=0","showcodes=N","cols=1;rows=1") -> 32.463 | L34: =[1]!wss($A34:$A34,"hks_fa_roe","rptDate="&($B34-1)&"1231","WssConvert=0","showcodes=N","cols=1;rows=1") -> 34.8473 | M34: =[1]!wss($A34:$A34,"hks_fa_debttoassets","rptDate="&($B34-1)&"1231","WssConvert=0","showcodes=N","cols=1;rows=1") -> 23.8711 | P34: 203.02465 | Q34: 248.28874 | R34: 335.59923 | S34: 31.37341 | T34: 44.36504 | U34: 58.86704 | V34: 29.548 | W34: 32.463 | X34: 31.1436
A35: 2585.HK | B35: =IFERROR(YEAR(VLOOKUP($A35,'01_ipo_master'!$A:$C,3,FALSE)),YEAR(VLOOKUP("0"&$A35,'01_ipo_master'!$A:$C,3,FALSE))) -> 2024 | C35: =[1]!wss($A35:$A35,"hks_stm_is","item=83","rptDate="&($B35-3)&"1231","rptType=1","currencyType=Cur=CNY","WssConvert=0","WssDivide=8","showcodes=N","cols=1;rows=1") -> 168.71 | D35: =[1]!wss($A35:$A35,"hks_stm_is","item=83","rptDate="&($B35-2)&"1231","rptType=1","currencyType=Cur=CNY","WssConvert=0","WssDivide=8","showcodes=N","cols=1;rows=1") -> 157.24215 | E35: =[1]!wss($A35:$A35,"hks_stm_is","item=83","rptDate="&($B35-1)&"1231","rptType=1","currencyType=Cur=CNY","WssConvert=0","WssDivide=8","showcodes=N","cols=1;rows=1") -> 202.08599 | F35: =[1]!wss($A35:$A35,"hks_stm_is","item=61","rptDate="&($B35-3)&"1231","rptType=1","currencyType=Cur=CNY","WssConvert=0","WssDivide=8","showcodes=N","cols=1;rows=1") -> 2.20618 | G35: =[1]!wss($A35:$A35,"hks_stm_is","item=61","rptDate="&($B35-2)&"1231","rptType=1","currencyType=Cur=CNY","WssConvert=0","WssDivide=8","showcodes=N","cols=1;rows=1") -> 1.80825 | H35: =[1]!wss($A35:$A35,"hks_stm_is","item=61","rptDate="&($B35-1)&"1231","rptType=1","currencyType=Cur=CNY","WssConvert=0","WssDivide=8","showcodes=N","cols=1;rows=1") -> 2.30375 | I35: =[1]!wss($A35:$A35,"hks_fa_grossprofitmargin","rptDate="&($B35-3)&"1231","WssConvert=0","showcodes=N","cols=1;rows=1") -> 3.1797 | J35: =[1]!wss($A35:$A35,"hks_fa_grossprofitmargin","rptDate="&($B35-2)&"1231","WssConvert=0","showcodes=N","cols=1;rows=1") -> 4.8285 | K35: =[1]!wss($A35:$A35,"hks_fa_grossprofitmargin","rptDate="&($B35-1)&"1231","WssConvert=0","showcodes=N","cols=1;rows=1") -> 5.3317 | L35: =[1]!wss($A35:$A35,"hks_fa_roe","rptDate="&($B35-1)&"1231","WssConvert=0","showcodes=N","cols=1;rows=1") -> 12.8045 | M35: =[1]!wss($A35:$A35,"hks_fa_debttoassets","rptDate="&($B35-1)&"1231","WssConvert=0","showcodes=N","cols=1;rows=1") -> 52.1785 | P35: 202.08599 | Q35: 197.12885 | R35: 207.09567 | S35: 2.30375 | T35: 1.89361 | U35: 0.96521 | V35: 5.3317 | W35: 6.7512 | X35: 7.6246
A36: 1828.HK | B36: =IFERROR(YEAR(VLOOKUP($A36,'01_ipo_master'!$A:$C,3,FALSE)),YEAR(VLOOKUP("0"&$A36,'01_ipo_master'!$A:$C,3,FALSE))) -> 2025 | C36: =[1]!wss($A36:$A36,"hks_stm_is","item=83","rptDate="&($B36-3)&"1231","rptType=1","currencyType=Cur=CNY","WssConvert=0","WssDivide=8","showcodes=N","cols=1;rows=1") -> 138.03837 | D36: =[1]!wss($A36:$A36,"hks_stm_is","item=83","rptDate="&($B36-2)&"1231","rptType=1","currencyType=Cur=CNY","WssConvert=0","WssDivide=8","showcodes=N","cols=1;rows=1") -> 199.94462 | E36: =[1]!wss($A36:$A36,"hks_stm_is","item=83","rptDate="&($B36-1)&"1231","rptType=1","currencyType=Cur=CNY","WssConvert=0","WssDivide=8","showcodes=N","cols=1;rows=1") -> 278.04731 | F36: =[1]!wss($A36:$A36,"hks_stm_is","item=61","rptDate="&($B36-3)&"1231","rptType=1","currencyType=Cur=CNY","WssConvert=0","WssDivide=8","showcodes=N","cols=1;rows=1") -> -15.252474 | G36: =[1]!wss($A36:$A36,"hks_stm_is","item=61","rptDate="&($B36-2)&"1231","rptType=1","currencyType=Cur=CNY","WssConvert=0","WssDivide=8","showcodes=N","cols=1;rows=1") -> -50.712132 | H36: =[1]!wss($A36:$A36,"hks_stm_is","item=61","rptDate="&($B36-1)&"1231","rptType=1","currencyType=Cur=CNY","WssConvert=0","WssDivide=8","showcodes=N","cols=1;rows=1") -> 1.725216 | I36: =[1]!wss($A36:$A36,"hks_fa_grossprofitmargin","rptDate="&($B36-3)&"1231","WssConvert=0","showcodes=N","cols=1;rows=1") | J36: =[1]!wss($A36:$A36,"hks_fa_grossprofitmargin","rptDate="&($B36-2)&"1231","WssConvert=0","showcodes=N","cols=1;rows=1") | K36: =[1]!wss($A36:$A36,"hks_fa_grossprofitmargin","rptDate="&($B36-1)&"1231","WssConvert=0","showcodes=N","cols=1;rows=1") | L36: =[1]!wss($A36:$A36,"hks_fa_roe","rptDate="&($B36-1)&"1231","WssConvert=0","showcodes=N","cols=1;rows=1") -> 0.3348 | M36: =[1]!wss($A36:$A36,"hks_fa_debttoassets","rptDate="&($B36-1)&"1231","WssConvert=0","showcodes=N","cols=1;rows=1") -> 87.3138 | P36: 199.94462 | Q36: 278.04731 | R36: 336.11722 | S36: -50.712132 | T36: 1.725216 | U36: 11.667808
A37: 2865.HK | B37: =IFERROR(YEAR(VLOOKUP($A37,'01_ipo_master'!$A:$C,3,FALSE)),YEAR(VLOOKUP("0"&$A37,'01_ipo_master'!$A:$C,3,FALSE))) -> 2025 | C37: =[1]!wss($A37:$A37,"hks_stm_is","item=83","rptDate="&($B37-3)&"1231","rptType=1","currencyType=Cur=CNY","WssConvert=0","WssDivide=8","showcodes=N","cols=1;rows=1") -> 110.85713 | D37: =[1]!wss($A37:$A37,"hks_stm_is","item=83","rptDate="&($B37-2)&"1231","rptType=1","currencyType=Cur=CNY","WssConvert=0","WssDivide=8","showcodes=N","cols=1;rows=1") -> 186.10794 | E37: =[1]!wss($A37:$A37,"hks_stm_is","item=83","rptDate="&($B37-1)&"1231","rptType=1","currencyType=Cur=CNY","WssConvert=0","WssDivide=8","showcodes=N","cols=1;rows=1") -> 99.23894 | F37: =[1]!wss($A37:$A37,"hks_stm_is","item=61","rptDate="&($B37-3)&"1231","rptType=1","currencyType=Cur=CNY","WssConvert=0","WssDivide=8","showcodes=N","cols=1;rows=1") -> 7.16945 | G37: =[1]!wss($A37:$A37,"hks_stm_is","item=61","rptDate="&($B37-2)&"1231","rptType=1","currencyType=Cur=CNY","WssConvert=0","WssDivide=8","showcodes=N","cols=1;rows=1") -> 8.15642 | H37: =[1]!wss($A37:$A37,"hks_stm_is","item=61","rptDate="&($B37-1)&"1231","rptType=1","currencyType=Cur=CNY","WssConvert=0","WssDivide=8","showcodes=N","cols=1;rows=1") -> -5.91113 | I37: =[1]!wss($A37:$A37,"hks_fa_grossprofitmargin","rptDate="&($B37-3)&"1231","WssConvert=0","showcodes=N","cols=1;rows=1") -> 10.9631 | J37: =[1]!wss($A37:$A37,"hks_fa_grossprofitmargin","rptDate="&($B37-2)&"1231","WssConvert=0","showcodes=N","cols=1;rows=1") -> 9.1136 | K37: =[1]!wss($A37:$A37,"hks_fa_grossprofitmargin","rptDate="&($B37-1)&"1231","WssConvert=0","showcodes=N","cols=1;rows=1") -> -0.8571 | L37: =[1]!wss($A37:$A37,"hks_fa_roe","rptDate="&($B37-1)&"1231","WssConvert=0","showcodes=N","cols=1;rows=1") -> -13.7528 | M37: =[1]!wss($A37:$A37,"hks_fa_debttoassets","rptDate="&($B37-1)&"1231","WssConvert=0","showcodes=N","cols=1;rows=1") -> 76.3625 | P37: 186.10794 | Q37: 99.23894 | R37: 75.97846 | S37: 8.15642 | T37: -5.91113 | U37: -14.15788 | V37: 9.1136 | W37: -0.8571 | X37: -6.8104
A38: 2768.HK | B38: =IFERROR(YEAR(VLOOKUP($A38,'01_ipo_master'!$A:$C,3,FALSE)),YEAR(VLOOKUP("0"&$A38,'01_ipo_master'!$A:$C,3,FALSE))) -> 2026 | C38: =[1]!wss($A38:$A38,"hks_stm_is","item=83","rptDate="&($B38-3)&"1231","rptType=1","currencyType=Cur=CNY","WssConvert=0","WssDivide=8","showcodes=N","cols=1;rows=1") -> 174.38779 | D38: =[1]!wss($A38:$A38,"hks_stm_is","item=83","rptDate="&($B38-2)&"1231","rptType=1","currencyType=Cur=CNY","WssConvert=0","WssDivide=8","showcodes=N","cols=1;rows=1") -> 191.87511 | E38: =[1]!wss($A38:$A38,"hks_stm_is","item=83","rptDate="&($B38-1)&"1231","rptType=1","currencyType=Cur=CNY","WssConvert=0","WssDivide=8","showcodes=N","cols=1;rows=1") -> 212.51231 | F38: =[1]!wss($A38:$A38,"hks_stm_is","item=61","rptDate="&($B38-3)&"1231","rptType=1","currencyType=Cur=CNY","WssConvert=0","WssDivide=8","showcodes=N","cols=1;rows=1") -> 4.71478 | G38: =[1]!wss($A38:$A38,"hks_stm_is","item=61","rptDate="&($B38-2)&"1231","rptType=1","currencyType=Cur=CNY","WssConvert=0","WssDivide=8","showcodes=N","cols=1;rows=1") -> 6.85232 | H38: =[1]!wss($A38:$A38,"hks_stm_is","item=61","rptDate="&($B38-1)&"1231","rptType=1","currencyType=Cur=CNY","WssConvert=0","WssDivide=8","showcodes=N","cols=1;rows=1") -> 8.51994 | I38: =[1]!wss($A38:$A38,"hks_fa_grossprofitmargin","rptDate="&($B38-3)&"1231","WssConvert=0","showcodes=N","cols=1;rows=1") -> 9.1793 | J38: =[1]!wss($A38:$A38,"hks_fa_grossprofitmargin","rptDate="&($B38-2)&"1231","WssConvert=0","showcodes=N","cols=1;rows=1") -> 8.298 | K38: =[1]!wss($A38:$A38,"hks_fa_grossprofitmargin","rptDate="&($B38-1)&"1231","WssConvert=0","showcodes=N","cols=1;rows=1") -> 10.4012 | L38: =[1]!wss($A38:$A38,"hks_fa_roe","rptDate="&($B38-1)&"1231","WssConvert=0","showcodes=N","cols=1;rows=1") -> 15.9455 | M38: =[1]!wss($A38:$A38,"hks_fa_debttoassets","rptDate="&($B38-1)&"1231","WssConvert=0","showcodes=N","cols=1;rows=1") -> 61.0855 | P38: 174.38779 | Q38: 191.87511 | R38: 212.51231 | S38: 4.71478 | T38: 6.85232 | U38: 8.51994 | V38: 9.1793 | W38: 8.298 | X38: 10.4012
A39: 7618.HK | B39: =IFERROR(YEAR(VLOOKUP($A39,'01_ipo_master'!$A:$C,3,FALSE)),YEAR(VLOOKUP("0"&$A39,'01_ipo_master'!$A:$C,3,FALSE))) -> 2025 | C39: =[1]!wss($A39:$A39,"hks_stm_is","item=83","rptDate="&($B39-3)&"1231","rptType=1","currencyType=Cur=CNY","WssConvert=0","WssDivide=8","showcodes=N","cols=1;rows=1") -> 141.34695 | D39: =[1]!wss($A39:$A39,"hks_stm_is","item=83","rptDate="&($B39-2)&"1231","rptType=1","currencyType=Cur=CNY","WssConvert=0","WssDivide=8","showcodes=N","cols=1;rows=1") -> 173.35883 | E39: =[1]!wss($A39:$A39,"hks_stm_is","item=83","rptDate="&($B39-1)&"1231","rptType=1","currencyType=Cur=CNY","WssConvert=0","WssDivide=8","showcodes=N","cols=1;rows=1") -> 203.97741 | F39: =[1]!wss($A39:$A39,"hks_stm_is","item=61","rptDate="&($B39-3)&"1231","rptType=1","currencyType=Cur=CNY","WssConvert=0","WssDivide=8","showcodes=N","cols=1;rows=1") -> -13.34128 | G39: =[1]!wss($A39:$A39,"hks_stm_is","item=61","rptDate="&($B39-2)&"1231","rptType=1","currencyType=Cur=CNY","WssConvert=0","WssDivide=8","showcodes=N","cols=1;rows=1") -> 0.04799 | H39: =[1]!wss($A39:$A39,"hks_stm_is","item=61","rptDate="&($B39-1)&"1231","rptType=1","currencyType=Cur=CNY","WssConvert=0","WssDivide=8","showcodes=N","cols=1;rows=1") -> 7.61608 | I39: =[1]!wss($A39:$A39,"hks_fa_grossprofitmargin","rptDate="&($B39-3)&"1231","WssConvert=0","showcodes=N","cols=1;rows=1") -> 17.9764 | J39: =[1]!wss($A39:$A39,"hks_fa_grossprofitmargin","rptDate="&($B39-2)&"1231","WssConvert=0","showcodes=N","cols=1;rows=1") -> 16.1438 | K39: =[1]!wss($A39:$A39,"hks_fa_grossprofitmargin","rptDate="&($B39-1)&"1231","WssConvert=0","showcodes=N","cols=1;rows=1") -> 16.2439 | L39: =[1]!wss($A39:$A39,"hks_fa_roe","rptDate="&($B39-1)&"1231","WssConvert=0","showcodes=N","cols=1;rows=1") -> 1054.1214 | M39: =[1]!wss($A39:$A39,"hks_fa_debttoassets","rptDate="&($B39-1)&"1231","WssConvert=0","showcodes=N","cols=1;rows=1") -> 96.6774 | P39: 173.35883 | Q39: 203.97741 | R39: 239.51789 | S39: 0.04799 | T39: 7.61608 | U39: 23.13723 | V39: 16.1438 | W39: 16.2439 | X39: 17.4
A40: 9885.HK | B40: =IFERROR(YEAR(VLOOKUP($A40,'01_ipo_master'!$A:$C,3,FALSE)),YEAR(VLOOKUP("0"&$A40,'01_ipo_master'!$A:$C,3,FALSE))) -> 2023 | C40: =[1]!wss($A40:$A40,"hks_stm_is","item=83","rptDate="&($B40-3)&"1231","rptType=1","currencyType=Cur=CNY","WssConvert=0","WssDivide=8","showcodes=N","cols=1;rows=1") -> 60.64907 | D40: =[1]!wss($A40:$A40,"hks_stm_is","item=83","rptDate="&($B40-2)&"1231","rptType=1","currencyType=Cur=CNY","WssConvert=0","WssDivide=8","showcodes=N","cols=1;rows=1") -> 100.93538 | E40: =[1]!wss($A40:$A40,"hks_stm_is","item=83","rptDate="&($B40-1)&"1231","rptType=1","currencyType=Cur=CNY","WssConvert=0","WssDivide=8","showcodes=N","cols=1;rows=1") -> 142.7481 | F40: =[1]!wss($A40:$A40,"hks_stm_is","item=61","rptDate="&($B40-3)&"1231","rptType=1","currencyType=Cur=CNY","WssConvert=0","WssDivide=8","showcodes=N","cols=1;rows=1") -> -5.71711 | G40: =[1]!wss($A40:$A40,"hks_stm_is","item=61","rptDate="&($B40-2)&"1231","rptType=1","currencyType=Cur=CNY","WssConvert=0","WssDivide=8","showcodes=N","cols=1;rows=1") -> -4.94041 | H40: =[1]!wss($A40:$A40,"hks_stm_is","item=61","rptDate="&($B40-1)&"1231","rptType=1","currencyType=Cur=CNY","WssConvert=0","WssDivide=8","showcodes=N","cols=1;rows=1") -> -14.88688 | I40: =[1]!wss($A40:$A40,"hks_fa_grossprofitmargin","rptDate="&($B40-3)&"1231","WssConvert=0","showcodes=N","cols=1;rows=1") -> 10.0379 | J40: =[1]!wss($A40:$A40,"hks_fa_grossprofitmargin","rptDate="&($B40-2)&"1231","WssConvert=0","showcodes=N","cols=1;rows=1") -> 9.0536 | K40: =[1]!wss($A40:$A40,"hks_fa_grossprofitmargin","rptDate="&($B40-1)&"1231","WssConvert=0","showcodes=N","cols=1;rows=1") -> 10.0507 | L40: =[1]!wss($A40:$A40,"hks_fa_roe","rptDate="&($B40-1)&"1231","WssConvert=0","showcodes=N","cols=1;rows=1") | M40: =[1]!wss($A40:$A40,"hks_fa_debttoassets","rptDate="&($B40-1)&"1231","WssConvert=0","showcodes=N","cols=1;rows=1") -> 206.3516 | P40: 169.72276 | Q40: 179.03608 | R40: 209.6965 | S40: -31.89212 | T40: 0.30013 | U40: 1.52965 | V40: 10.2575 | W40: 10.129 | X40: 11.0015
A41: 9863.HK | B41: =IFERROR(YEAR(VLOOKUP($A41,'01_ipo_master'!$A:$C,3,FALSE)),YEAR(VLOOKUP("0"&$A41,'01_ipo_master'!$A:$C,3,FALSE))) -> 2022 | C41: =[1]!wss($A41:$A41,"hks_stm_is","item=83","rptDate="&($B41-3)&"1231","rptType=1","currencyType=Cur=CNY","WssConvert=0","WssDivide=8","showcodes=N","cols=1;rows=1") -> 1.16963 | D41: =[1]!wss($A41:$A41,"hks_stm_is","item=83","rptDate="&($B41-2)&"1231","rptType=1","currencyType=Cur=CNY","WssConvert=0","WssDivide=8","showcodes=N","cols=1;rows=1") -> 6.31301 | E41: =[1]!wss($A41:$A41,"hks_stm_is","item=83","rptDate="&($B41-1)&"1231","rptType=1","currencyType=Cur=CNY","WssConvert=0","WssDivide=8","showcodes=N","cols=1;rows=1") -> 31.32059 | F41: =[1]!wss($A41:$A41,"hks_stm_is","item=61","rptDate="&($B41-3)&"1231","rptType=1","currencyType=Cur=CNY","WssConvert=0","WssDivide=8","showcodes=N","cols=1;rows=1") -> -9.01131 | G41: =[1]!wss($A41:$A41,"hks_stm_is","item=61","rptDate="&($B41-2)&"1231","rptType=1","currencyType=Cur=CNY","WssConvert=0","WssDivide=8","showcodes=N","cols=1;rows=1") -> -11.00093 | H41: =[1]!wss($A41:$A41,"hks_stm_is","item=61","rptDate="&($B41-1)&"1231","rptType=1","currencyType=Cur=CNY","WssConvert=0","WssDivide=8","showcodes=N","cols=1;rows=1") -> -28.45773 | I41: =[1]!wss($A41:$A41,"hks_fa_grossprofitmargin","rptDate="&($B41-3)&"1231","WssConvert=0","showcodes=N","cols=1;rows=1") -> -95.7277 | J41: =[1]!wss($A41:$A41,"hks_fa_grossprofitmargin","rptDate="&($B41-2)&"1231","WssConvert=0","showcodes=N","cols=1;rows=1") -> -50.6258 | K41: =[1]!wss($A41:$A41,"hks_fa_grossprofitmargin","rptDate="&($B41-1)&"1231","WssConvert=0","showcodes=N","cols=1;rows=1") -> -44.3041 | L41: =[1]!wss($A41:$A41,"hks_fa_roe","rptDate="&($B41-1)&"1231","WssConvert=0","showcodes=N","cols=1;rows=1") -> -85.3687 | M41: =[1]!wss($A41:$A41,"hks_fa_debttoassets","rptDate="&($B41-1)&"1231","WssConvert=0","showcodes=N","cols=1;rows=1") -> 42.2805 | P41: 167.46689 | Q41: 321.64184 | R41: 647.3186 | S41: -42.16274 | T41: -28.20796 | U41: 5.38392 | V41: 0.4805 | W41: 8.3771 | X41: 14.5399
A42: 0470.HK | B42: =IFERROR(YEAR(VLOOKUP($A42,'01_ipo_master'!$A:$C,3,FALSE)),YEAR(VLOOKUP("0"&$A42,'01_ipo_master'!$A:$C,3,FALSE))) -> 2026 | C42: =[1]!wss($A42:$A42,"hks_stm_is","item=83","rptDate="&($B42-3)&"1231","rptType=1","currencyType=Cur=CNY","WssConvert=0","WssDivide=8","showcodes=N","cols=1;rows=1") -> 164.83341 | D42: =[1]!wss($A42:$A42,"hks_stm_is","item=83","rptDate="&($B42-2)&"1231","rptType=1","currencyType=Cur=CNY","WssConvert=0","WssDivide=8","showcodes=N","cols=1;rows=1") -> 117.7335 | E42: =[1]!wss($A42:$A42,"hks_stm_is","item=83","rptDate="&($B42-1)&"1231","rptType=1","currencyType=Cur=CNY","WssConvert=0","WssDivide=8","showcodes=N","cols=1;rows=1") -> 143.58016 | F42: =[1]!wss($A42:$A42,"hks_stm_is","item=61","rptDate="&($B42-3)&"1231","rptType=1","currencyType=Cur=CNY","WssConvert=0","WssDivide=8","showcodes=N","cols=1;rows=1") -> 17.74566 | G42: =[1]!wss($A42:$A42,"hks_stm_is","item=61","rptDate="&($B42-2)&"1231","rptType=1","currencyType=Cur=CNY","WssConvert=0","WssDivide=8","showcodes=N","cols=1;rows=1") -> 2.861 | H42: =[1]!wss($A42:$A42,"hks_stm_is","item=61","rptDate="&($B42-1)&"1231","rptType=1","currencyType=Cur=CNY","WssConvert=0","WssDivide=8","showcodes=N","cols=1;rows=1") -> 15.63778 | I42: =[1]!wss($A42:$A42,"hks_fa_grossprofitmargin","rptDate="&($B42-3)&"1231","WssConvert=0","showcodes=N","cols=1;rows=1") -> 32.7212 | J42: =[1]!wss($A42:$A42,"hks_fa_grossprofitmargin","rptDate="&($B42-2)&"1231","WssConvert=0","showcodes=N","cols=1;rows=1") -> 30.0471 | K42: =[1]!wss($A42:$A42,"hks_fa_grossprofitmargin","rptDate="&($B42-1)&"1231","WssConvert=0","showcodes=N","cols=1;rows=1") -> 30.6969 | L42: =[1]!wss($A42:$A42,"hks_fa_roe","rptDate="&($B42-1)&"1231","WssConvert=0","showcodes=N","cols=1;rows=1") -> 12.643 | M42: =[1]!wss($A42:$A42,"hks_fa_debttoassets","rptDate="&($B42-1)&"1231","WssConvert=0","showcodes=N","cols=1;rows=1") -> 66.3428 | P42: 164.83341 | Q42: 117.7335 | R42: 143.58016 | S42: 17.74566 | T42: 2.861 | U42: 15.63778 | V42: 32.7212 | W42: 30.0471 | X42: 30.6969
A43: 2419.HK | B43: =IFERROR(YEAR(VLOOKUP($A43,'01_ipo_master'!$A:$C,3,FALSE)),YEAR(VLOOKUP("0"&$A43,'01_ipo_master'!$A:$C,3,FALSE))) -> 2023 | C43: =[1]!wss($A43:$A43,"hks_stm_is","item=83","rptDate="&($B43-3)&"1231","rptType=1","currencyType=Cur=CNY","WssConvert=0","WssDivide=8","showcodes=N","cols=1;rows=1") -> 81.45349 | D43: =[1]!wss($A43:$A43,"hks_stm_is","item=83","rptDate="&($B43-2)&"1231","rptType=1","currencyType=Cur=CNY","WssConvert=0","WssDivide=8","showcodes=N","cols=1;rows=1") -> 99.01566 | E43: =[1]!wss($A43:$A43,"hks_stm_is","item=83","rptDate="&($B43-1)&"1231","rptType=1","currencyType=Cur=CNY","WssConvert=0","WssDivide=8","showcodes=N","cols=1;rows=1") -> 150.37027 | F43: =[1]!wss($A43:$A43,"hks_stm_is","item=61","rptDate="&($B43-3)&"1231","rptType=1","currencyType=Cur=CNY","WssConvert=0","WssDivide=8","showcodes=N","cols=1;rows=1") -> 34.88173 | G43: =[1]!wss($A43:$A43,"hks_stm_is","item=61","rptDate="&($B43-2)&"1231","rptType=1","currencyType=Cur=CNY","WssConvert=0","WssDivide=8","showcodes=N","cols=1;rows=1") -> -29.97303 | H43: =[1]!wss($A43:$A43,"hks_stm_is","item=61","rptDate="&($B43-1)&"1231","rptType=1","currencyType=Cur=CNY","WssConvert=0","WssDivide=8","showcodes=N","cols=1;rows=1") -> 9.92866 | I43: =[1]!wss($A43:$A43,"hks_fa_grossprofitmargin","rptDate="&($B43-3)&"1231","WssConvert=0","showcodes=N","cols=1;rows=1") -> 38.8429 | J43: =[1]!wss($A43:$A43,"hks_fa_grossprofitmargin","rptDate="&($B43-2)&"1231","WssConvert=0","showcodes=N","cols=1;rows=1") -> 7.717 | K43: =[1]!wss($A43:$A43,"hks_fa_grossprofitmargin","rptDate="&($B43-1)&"1231","WssConvert=0","showcodes=N","cols=1;rows=1") -> 13.7539 | L43: =[1]!wss($A43:$A43,"hks_fa_roe","rptDate="&($B43-1)&"1231","WssConvert=0","showcodes=N","cols=1;rows=1") -> 22.2055 | M43: =[1]!wss($A43:$A43,"hks_fa_debttoassets","rptDate="&($B43-1)&"1231","WssConvert=0","showcodes=N","cols=1;rows=1") -> 73.7633 | P43: 161.55412 | Q43: 224.63038 | R43: 231.59024 | S43: -17.75126 | T43: 41.01559 | U43: 14.332494 | V43: 0.7408 | W43: 21.6591 | X43: 13.7421
A44: 2259.HK | B44: =IFERROR(YEAR(VLOOKUP($A44,'01_ipo_master'!$A:$C,3,FALSE)),YEAR(VLOOKUP("0"&$A44,'01_ipo_master'!$A:$C,3,FALSE))) -> 2025 | C44: =[1]!wss($A44:$A44,"hks_stm_is","item=83","rptDate="&($B44-3)&"1231","rptType=1","currencyType=Cur=CNY","WssConvert=0","WssDivide=8","showcodes=N","cols=1;rows=1") -> 126.6151 | D44: =[1]!wss($A44:$A44,"hks_stm_is","item=83","rptDate="&($B44-2)&"1231","rptType=1","currencyType=Cur=CNY","WssConvert=0","WssDivide=8","showcodes=N","cols=1;rows=1") -> 160.23653 | E44: =[1]!wss($A44:$A44,"hks_stm_is","item=83","rptDate="&($B44-1)&"1231","rptType=1","currencyType=Cur=CNY","WssConvert=0","WssDivide=8","showcodes=N","cols=1;rows=1") -> 214.92849 | F44: =[1]!wss($A44:$A44,"hks_stm_is","item=61","rptDate="&($B44-3)&"1231","rptType=1","currencyType=Cur=CNY","WssConvert=0","WssDivide=8","showcodes=N","cols=1;rows=1") -> 12.792577 | G44: =[1]!wss($A44:$A44,"hks_stm_is","item=61","rptDate="&($B44-2)&"1231","rptType=1","currencyType=Cur=CNY","WssConvert=0","WssDivide=8","showcodes=N","cols=1;rows=1") -> 16.317337 | H44: =[1]!wss($A44:$A44,"hks_stm_is","item=61","rptDate="&($B44-1)&"1231","rptType=1","currencyType=Cur=CNY","WssConvert=0","WssDivide=8","showcodes=N","cols=1;rows=1") -> 34.602873 | I44: =[1]!wss($A44:$A44,"hks_fa_grossprofitmargin","rptDate="&($B44-3)&"1231","WssConvert=0","showcodes=N","cols=1;rows=1") -> 34.1287 | J44: =[1]!wss($A44:$A44,"hks_fa_grossprofitmargin","rptDate="&($B44-2)&"1231","WssConvert=0","showcodes=N","cols=1;rows=1") -> 26.1972 | K44: =[1]!wss($A44:$A44,"hks_fa_grossprofitmargin","rptDate="&($B44-1)&"1231","WssConvert=0","showcodes=N","cols=1;rows=1") -> 37.9381 | L44: =[1]!wss($A44:$A44,"hks_fa_roe","rptDate="&($B44-1)&"1231","WssConvert=0","showcodes=N","cols=1;rows=1") -> 22.1923 | M44: =[1]!wss($A44:$A44,"hks_fa_debttoassets","rptDate="&($B44-1)&"1231","WssConvert=0","showcodes=N","cols=1;rows=1") -> 46.2848 | P44: 160.23653 | Q44: 214.92849 | R44: 378.39404 | S44: 16.317337 | T44: 34.602873 | U44: 112.57017 | V44: 26.1972 | W44: 37.9381 | X44: 52.6965
A45: 3660.HK | B45: =IFERROR(YEAR(VLOOKUP($A45,'01_ipo_master'!$A:$C,3,FALSE)),YEAR(VLOOKUP("0"&$A45,'01_ipo_master'!$A:$C,3,FALSE))) -> 2022 | C45: =[1]!wss($A45:$A45,"hks_stm_is","item=83","rptDate="&($B45-3)&"1231","rptType=1","currencyType=Cur=CNY","WssConvert=0","WssDivide=8","showcodes=N","cols=1;rows=1") -> 86.91149 | D45: =[1]!wss($A45:$A45,"hks_stm_is","item=83","rptDate="&($B45-2)&"1231","rptType=1","currencyType=Cur=CNY","WssConvert=0","WssDivide=8","showcodes=N","cols=1;rows=1") -> 129.42422 | E45: =[1]!wss($A45:$A45,"hks_stm_is","item=83","rptDate="&($B45-1)&"1231","rptType=1","currencyType=Cur=CNY","WssConvert=0","WssDivide=8","showcodes=N","cols=1;rows=1") -> 157.96482 | F45: =[1]!wss($A45:$A45,"hks_stm_is","item=61","rptDate="&($B45-3)&"1231","rptType=1","currencyType=Cur=CNY","WssConvert=0","WssDivide=8","showcodes=N","cols=1;rows=1") -> 25.01595 | G45: =[1]!wss($A45:$A45,"hks_stm_is","item=61","rptDate="&($B45-2)&"1231","rptType=1","currencyType=Cur=CNY","WssConvert=0","WssDivide=8","showcodes=N","cols=1;rows=1") -> 34.96606 | H45: =[1]!wss($A45:$A45,"hks_stm_is","item=61","rptDate="&($B45-1)&"1231","rptType=1","currencyType=Cur=CNY","WssConvert=0","WssDivide=8","showcodes=N","cols=1;rows=1") -> 57.81725 | I45: =[1]!wss($A45:$A45,"hks_fa_grossprofitmargin","rptDate="&($B45-3)&"1231","WssConvert=0","showcodes=N","cols=1;rows=1") | J45: =[1]!wss($A45:$A45,"hks_fa_grossprofitmargin","rptDate="&($B45-2)&"1231","WssConvert=0","showcodes=N","cols=1;rows=1") | K45: =[1]!wss($A45:$A45,"hks_fa_grossprofitmargin","rptDate="&($B45-1)&"1231","WssConvert=0","showcodes=N","cols=1;rows=1") | L45: =[1]!wss($A45:$A45,"hks_fa_roe","rptDate="&($B45-1)&"1231","WssConvert=0","showcodes=N","cols=1;rows=1") -> 46.8451 | M45: =[1]!wss($A45:$A45,"hks_fa_debttoassets","rptDate="&($B45-1)&"1231","WssConvert=0","showcodes=N","cols=1;rows=1") -> 54.5841 | P45: 143.56288 | Q45: 146.29348 | R45: 158.58643 | S45: 42.85336 | T45: 62.64314 | U45: 59.89691
A46: 2648.HK | B46: =IFERROR(YEAR(VLOOKUP($A46,'01_ipo_master'!$A:$C,3,FALSE)),YEAR(VLOOKUP("0"&$A46,'01_ipo_master'!$A:$C,3,FALSE))) -> 2025 | C46: =[1]!wss($A46:$A46,"hks_stm_is","item=83","rptDate="&($B46-3)&"1231","rptType=1","currencyType=Cur=CNY","WssConvert=0","WssDivide=8","showcodes=N","cols=1;rows=1") -> 121.05618 | D46: =[1]!wss($A46:$A46,"hks_stm_is","item=83","rptDate="&($B46-2)&"1231","rptType=1","currencyType=Cur=CNY","WssConvert=0","WssDivide=8","showcodes=N","cols=1;rows=1") -> 139.64878 | E46: =[1]!wss($A46:$A46,"hks_stm_is","item=83","rptDate="&($B46-1)&"1231","rptType=1","currencyType=Cur=CNY","WssConvert=0","WssDivide=8","showcodes=N","cols=1;rows=1") -> 150.29588 | F46: =[1]!wss($A46:$A46,"hks_stm_is","item=61","rptDate="&($B46-3)&"1231","rptType=1","currencyType=Cur=CNY","WssConvert=0","WssDivide=8","showcodes=N","cols=1;rows=1") -> 11.0103 | G46: =[1]!wss($A46:$A46,"hks_stm_is","item=61","rptDate="&($B46-2)&"1231","rptType=1","currencyType=Cur=CNY","WssConvert=0","WssDivide=8","showcodes=N","cols=1;rows=1") -> 14.78067 | H46: =[1]!wss($A46:$A46,"hks_stm_is","item=61","rptDate="&($B46-1)&"1231","rptType=1","currencyType=Cur=CNY","WssConvert=0","WssDivide=8","showcodes=N","cols=1;rows=1") -> 14.84831 | I46: =[1]!wss($A46:$A46,"hks_fa_grossprofitmargin","rptDate="&($B46-3)&"1231","WssConvert=0","showcodes=N","cols=1;rows=1") -> 21.1516 | J46: =[1]!wss($A46:$A46,"hks_fa_grossprofitmargin","rptDate="&($B46-2)&"1231","WssConvert=0","showcodes=N","cols=1;rows=1") -> 22.6078 | K46: =[1]!wss($A46:$A46,"hks_fa_grossprofitmargin","rptDate="&($B46-1)&"1231","WssConvert=0","showcodes=N","cols=1;rows=1") -> 22.6771 | L46: =[1]!wss($A46:$A46,"hks_fa_roe","rptDate="&($B46-1)&"1231","WssConvert=0","showcodes=N","cols=1;rows=1") -> 11.6091 | M46: =[1]!wss($A46:$A46,"hks_fa_debttoassets","rptDate="&($B46-1)&"1231","WssConvert=0","showcodes=N","cols=1;rows=1") -> 23.6244 | P46: 139.64878 | Q46: 150.29588 | R46: 161.92613 | S46: 14.78067 | T46: 14.84831 | U46: 13.592371 | V46: 22.6078 | W46: 22.6771 | X46: 21.601
A47: 2788.HK | B47: =IFERROR(YEAR(VLOOKUP($A47,'01_ipo_master'!$A:$C,3,FALSE)),YEAR(VLOOKUP("0"&$A47,'01_ipo_master'!$A:$C,3,FALSE))) -> 2025 | C47: =[1]!wss($A47:$A47,"hks_stm_is","item=83","rptDate="&($B47-3)&"1231","rptType=1","currencyType=Cur=CNY","WssConvert=0","WssDivide=8","showcodes=N","cols=1;rows=1") -> 134.89726 | D47: =[1]!wss($A47:$A47,"hks_stm_is","item=83","rptDate="&($B47-2)&"1231","rptType=1","currencyType=Cur=CNY","WssConvert=0","WssDivide=8","showcodes=N","cols=1;rows=1") -> 138.14657 | E47: =[1]!wss($A47:$A47,"hks_stm_is","item=83","rptDate="&($B47-1)&"1231","rptType=1","currencyType=Cur=CNY","WssConvert=0","WssDivide=8","showcodes=N","cols=1;rows=1") -> 151.63182 | F47: =[1]!wss($A47:$A47,"hks_stm_is","item=61","rptDate="&($B47-3)&"1231","rptType=1","currencyType=Cur=CNY","WssConvert=0","WssDivide=8","showcodes=N","cols=1;rows=1") -> 8.81286 | G47: =[1]!wss($A47:$A47,"hks_stm_is","item=61","rptDate="&($B47-2)&"1231","rptType=1","currencyType=Cur=CNY","WssConvert=0","WssDivide=8","showcodes=N","cols=1;rows=1") -> 10.03572 | H47: =[1]!wss($A47:$A47,"hks_stm_is","item=61","rptDate="&($B47-1)&"1231","rptType=1","currencyType=Cur=CNY","WssConvert=0","WssDivide=8","showcodes=N","cols=1;rows=1") -> 20.56227 | I47: =[1]!wss($A47:$A47,"hks_fa_grossprofitmargin","rptDate="&($B47-3)&"1231","WssConvert=0","showcodes=N","cols=1;rows=1") -> 15.1311 | J47: =[1]!wss($A47:$A47,"hks_fa_grossprofitmargin","rptDate="&($B47-2)&"1231","WssConvert=0","showcodes=N","cols=1;rows=1") -> 16.9117 | K47: =[1]!wss($A47:$A47,"hks_fa_grossprofitmargin","rptDate="&($B47-1)&"1231","WssConvert=0","showcodes=N","cols=1;rows=1") -> 28.2029 | L47: =[1]!wss($A47:$A47,"hks_fa_roe","rptDate="&($B47-1)&"1231","WssConvert=0","showcodes=N","cols=1;rows=1") -> 97.7975 | M47: =[1]!wss($A47:$A47,"hks_fa_debttoassets","rptDate="&($B47-1)&"1231","WssConvert=0","showcodes=N","cols=1;rows=1") -> 87.3019 | P47: 138.14657 | Q47: 151.63182 | R47: 186.80567 | S47: 10.03572 | T47: 20.56227 | U47: 27.30811 | V47: 16.9117 | W47: 28.2029 | X47: 24.7563
A48: 0666.HK | B48: =IFERROR(YEAR(VLOOKUP($A48,'01_ipo_master'!$A:$C,3,FALSE)),YEAR(VLOOKUP("0"&$A48,'01_ipo_master'!$A:$C,3,FALSE))) -> 2023 | C48: =[1]!wss($A48:$A48,"hks_stm_is","item=83","rptDate="&($B48-3)&"1231","rptType=1","currencyType=Cur=CNY","WssConvert=0","WssDivide=8","showcodes=N","cols=1;rows=1") -> 9.06986 | D48: =[1]!wss($A48:$A48,"hks_stm_is","item=83","rptDate="&($B48-2)&"1231","rptType=1","currencyType=Cur=CNY","WssConvert=0","WssDivide=8","showcodes=N","cols=1;rows=1") -> 21.09144 | E48: =[1]!wss($A48:$A48,"hks_stm_is","item=83","rptDate="&($B48-1)&"1231","rptType=1","currencyType=Cur=CNY","WssConvert=0","WssDivide=8","showcodes=N","cols=1;rows=1") -> 146.47778 | F48: =[1]!wss($A48:$A48,"hks_stm_is","item=61","rptDate="&($B48-3)&"1231","rptType=1","currencyType=Cur=CNY","WssConvert=0","WssDivide=8","showcodes=N","cols=1;rows=1") -> -0.40843 | G48: =[1]!wss($A48:$A48,"hks_stm_is","item=61","rptDate="&($B48-2)&"1231","rptType=1","currencyType=Cur=CNY","WssConvert=0","WssDivide=8","showcodes=N","cols=1;rows=1") -> -7.17227 | H48: =[1]!wss($A48:$A48,"hks_stm_is","item=61","rptDate="&($B48-1)&"1231","rptType=1","currencyType=Cur=CNY","WssConvert=0","WssDivide=8","showcodes=N","cols=1;rows=1") -> -3.54121 | I48: =[1]!wss($A48:$A48,"hks_fa_grossprofitmargin","rptDate="&($B48-3)&"1231","WssConvert=0","showcodes=N","cols=1;rows=1") -> 12.2491 | J48: =[1]!wss($A48:$A48,"hks_fa_grossprofitmargin","rptDate="&($B48-2)&"1231","WssConvert=0","showcodes=N","cols=1;rows=1") -> -15.4034 | K48: =[1]!wss($A48:$A48,"hks_fa_grossprofitmargin","rptDate="&($B48-1)&"1231","WssConvert=0","showcodes=N","cols=1;rows=1") -> 7.4297 | L48: =[1]!wss($A48:$A48,"hks_fa_roe","rptDate="&($B48-1)&"1231","WssConvert=0","showcodes=N","cols=1;rows=1") -> -5.5427 | M48: =[1]!wss($A48:$A48,"hks_fa_debttoassets","rptDate="&($B48-1)&"1231","WssConvert=0","showcodes=N","cols=1;rows=1") -> 56.6908 | P48: 137.48914 | Q48: 177.95914 | R48: 243.33984 | S48: -14.71802 | T48: -11.63089 | U48: 6.22992 | V48: 2.1336 | W48: 4.141 | X48: 11.1821
A49: 9690.HK | B49: =IFERROR(YEAR(VLOOKUP($A49,'01_ipo_master'!$A:$C,3,FALSE)),YEAR(VLOOKUP("0"&$A49,'01_ipo_master'!$A:$C,3,FALSE))) -> 2023 | C49: =[1]!wss($A49:$A49,"hks_stm_is","item=83","rptDate="&($B49-3)&"1231","rptType=1","currencyType=Cur=CNY","WssConvert=0","WssDivide=8","showcodes=N","cols=1;rows=1") -> 87.53316 | D49: =[1]!wss($A49:$A49,"hks_stm_is","item=83","rptDate="&($B49-2)&"1231","rptType=1","currencyType=Cur=CNY","WssConvert=0","WssDivide=8","showcodes=N","cols=1;rows=1") -> 117.24263 | E49: =[1]!wss($A49:$A49,"hks_stm_is","item=83","rptDate="&($B49-1)&"1231","rptType=1","currencyType=Cur=CNY","WssConvert=0","WssDivide=8","showcodes=N","cols=1;rows=1") -> 115.46851 | F49: =[1]!wss($A49:$A49,"hks_stm_is","item=61","rptDate="&($B49-3)&"1231","rptType=1","currencyType=Cur=CNY","WssConvert=0","WssDivide=8","showcodes=N","cols=1;rows=1") -> -39.28209 | G49: =[1]!wss($A49:$A49,"hks_stm_is","item=61","rptDate="&($B49-2)&"1231","rptType=1","currencyType=Cur=CNY","WssConvert=0","WssDivide=8","showcodes=N","cols=1;rows=1") -> -58.40577 | H49: =[1]!wss($A49:$A49,"hks_stm_is","item=61","rptDate="&($B49-1)&"1231","rptType=1","currencyType=Cur=CNY","WssConvert=0","WssDivide=8","showcodes=N","cols=1;rows=1") -> -21.36173 | I49: =[1]!wss($A49:$A49,"hks_fa_grossprofitmargin","rptDate="&($B49-3)&"1231","WssConvert=0","showcodes=N","cols=1;rows=1") -> 12.3384 | J49: =[1]!wss($A49:$A49,"hks_fa_grossprofitmargin","rptDate="&($B49-2)&"1231","WssConvert=0","showcodes=N","cols=1;rows=1") -> 15.9524 | K49: =[1]!wss($A49:$A49,"hks_fa_grossprofitmargin","rptDate="&($B49-1)&"1231","WssConvert=0","showcodes=N","cols=1;rows=1") -> 19.6606 | L49: =[1]!wss($A49:$A49,"hks_fa_roe","rptDate="&($B49-1)&"1231","WssConvert=0","showcodes=N","cols=1;rows=1") | M49: =[1]!wss($A49:$A49,"hks_fa_debttoassets","rptDate="&($B49-1)&"1231","WssConvert=0","showcodes=N","cols=1;rows=1") -> 310.2986 | P49: 136.01085 | Q49: 147.58694 | R49: 164.61611 | S49: 67.02935 | T49: 4.83794 | U49: 4.20394 | V49: 24.6992 | W49: 25.3815 | X49: 24.1017
A50: 2460.HK | B50: =IFERROR(YEAR(VLOOKUP($A50,'01_ipo_master'!$A:$C,3,FALSE)),YEAR(VLOOKUP("0"&$A50,'01_ipo_master'!$A:$C,3,FALSE))) -> 2024 | C50: =[1]!wss($A50:$A50,"hks_stm_is","item=83","rptDate="&($B50-3)&"1231","rptType=1","currencyType=Cur=CNY","WssConvert=0","WssDivide=8","showcodes=N","cols=1;rows=1") -> 113.39881 | D50: =[1]!wss($A50:$A50,"hks_stm_is","item=83","rptDate="&($B50-2)&"1231","rptType=1","currencyType=Cur=CNY","WssConvert=0","WssDivide=8","showcodes=N","cols=1;rows=1") -> 126.22776 | E50: =[1]!wss($A50:$A50,"hks_stm_is","item=83","rptDate="&($B50-1)&"1231","rptType=1","currencyType=Cur=CNY","WssConvert=0","WssDivide=8","showcodes=N","cols=1;rows=1") -> 135.14728 | F50: =[1]!wss($A50:$A50,"hks_stm_is","item=61","rptDate="&($B50-3)&"1231","rptType=1","currencyType=Cur=CNY","WssConvert=0","WssDivide=8","showcodes=N","cols=1;rows=1") -> 8.58141 | G50: =[1]!wss($A50:$A50,"hks_stm_is","item=61","rptDate="&($B50-2)&"1231","rptType=1","currencyType=Cur=CNY","WssConvert=0","WssDivide=8","showcodes=N","cols=1;rows=1") -> 9.89808 | H50: =[1]!wss($A50:$A50,"hks_stm_is","item=61","rptDate="&($B50-1)&"1231","rptType=1","currencyType=Cur=CNY","WssConvert=0","WssDivide=8","showcodes=N","cols=1;rows=1") -> 13.29341 | I50: =[1]!wss($A50:$A50,"hks_fa_grossprofitmargin","rptDate="&($B50-3)&"1231","WssConvert=0","showcodes=N","cols=1;rows=1") -> 43.8397 | J50: =[1]!wss($A50:$A50,"hks_fa_grossprofitmargin","rptDate="&($B50-2)&"1231","WssConvert=0","showcodes=N","cols=1;rows=1") -> 41.6636 | K50: =[1]!wss($A50:$A50,"hks_fa_grossprofitmargin","rptDate="&($B50-1)&"1231","WssConvert=0","showcodes=N","cols=1;rows=1") -> 44.6566 | L50: =[1]!wss($A50:$A50,"hks_fa_roe","rptDate="&($B50-1)&"1231","WssConvert=0","showcodes=N","cols=1;rows=1") -> 21.309 | M50: =[1]!wss($A50:$A50,"hks_fa_debttoassets","rptDate="&($B50-1)&"1231","WssConvert=0","showcodes=N","cols=1;rows=1") -> 43.294 | P50: 135.14728 | Q50: 135.21246 | R50: 110.02111 | S50: 13.29341 | T50: 16.36694 | U50: 9.85341 | V50: 44.6566 | W50: 47.3127 | X50: 45.6762
A51: 7489.HK | B51: =IFERROR(YEAR(VLOOKUP($A51,'01_ipo_master'!$A:$C,3,FALSE)),YEAR(VLOOKUP("0"&$A51,'01_ipo_master'!$A:$C,3,FALSE))) -> 2026 | C51: =[1]!wss($A51:$A51,"hks_stm_is","item=83","rptDate="&($B51-3)&"1231","rptType=1","currencyType=Cur=CNY","WssConvert=0","WssDivide=8","showcodes=N","cols=1;rows=1") -> 127.4938 | D51: =[1]!wss($A51:$A51,"hks_stm_is","item=83","rptDate="&($B51-2)&"1231","rptType=1","currencyType=Cur=CNY","WssConvert=0","WssDivide=8","showcodes=N","cols=1;rows=1") -> 193.60642 | E51: =[1]!wss($A51:$A51,"hks_stm_is","item=83","rptDate="&($B51-1)&"1231","rptType=1","currencyType=Cur=CNY","WssConvert=0","WssDivide=8","showcodes=N","cols=1;rows=1") -> 348.64815 | F51: =[1]!wss($A51:$A51,"hks_stm_is","item=61","rptDate="&($B51-3)&"1231","rptType=1","currencyType=Cur=CNY","WssConvert=0","WssDivide=8","showcodes=N","cols=1;rows=1") -> -14.95531 | G51: =[1]!wss($A51:$A51,"hks_stm_is","item=61","rptDate="&($B51-2)&"1231","rptType=1","currencyType=Cur=CNY","WssConvert=0","WssDivide=8","showcodes=N","cols=1;rows=1") -> -0.90459 | H51: =[1]!wss($A51:$A51,"hks_stm_is","item=61","rptDate="&($B51-1)&"1231","rptType=1","currencyType=Cur=CNY","WssConvert=0","WssDivide=8","showcodes=N","cols=1;rows=1") -> 10.17378 | I51: =[1]!wss($A51:$A51,"hks_fa_grossprofitmargin","rptDate="&($B51-3)&"1231","WssConvert=0","showcodes=N","cols=1;rows=1") -> 13.9061 | J51: =[1]!wss($A51:$A51,"hks_fa_grossprofitmargin","rptDate="&($B51-2)&"1231","WssConvert=0","showcodes=N","cols=1;rows=1") -> 20.9741 | K51: =[1]!wss($A51:$A51,"hks_fa_grossprofitmargin","rptDate="&($B51-1)&"1231","WssConvert=0","showcodes=N","cols=1;rows=1") -> 20.9032 | L51: =[1]!wss($A51:$A51,"hks_fa_roe","rptDate="&($B51-1)&"1231","WssConvert=0","showcodes=N","cols=1;rows=1") -> 14.6986 | M51: =[1]!wss($A51:$A51,"hks_fa_debttoassets","rptDate="&($B51-1)&"1231","WssConvert=0","showcodes=N","cols=1;rows=1") -> 73.5195 | P51: 127.4938 | Q51: 193.60642 | R51: 348.64815 | S51: -14.95531 | T51: -0.90459 | U51: 10.17378 | V51: 13.9061 | W51: 20.9741 | X51: 20.9032
A52: 9896.HK | B52: =IFERROR(YEAR(VLOOKUP($A52,'01_ipo_master'!$A:$C,3,FALSE)),YEAR(VLOOKUP("0"&$A52,'01_ipo_master'!$A:$C,3,FALSE))) -> 2022 | C52: =[1]!wss($A52:$A52,"hks_stm_is","item=83","rptDate="&($B52-3)&"1231","rptType=1","currencyType=Cur=CNY","WssConvert=0","WssDivide=8","showcodes=N","cols=1;rows=1") -> 93.94911 | D52: =[1]!wss($A52:$A52,"hks_stm_is","item=83","rptDate="&($B52-2)&"1231","rptType=1","currencyType=Cur=CNY","WssConvert=0","WssDivide=8","showcodes=N","cols=1;rows=1") -> 89.78986 | E52: =[1]!wss($A52:$A52,"hks_stm_is","item=83","rptDate="&($B52-1)&"1231","rptType=1","currencyType=Cur=CNY","WssConvert=0","WssDivide=8","showcodes=N","cols=1;rows=1") -> 90.71659 | F52: =[1]!wss($A52:$A52,"hks_stm_is","item=61","rptDate="&($B52-3)&"1231","rptType=1","currencyType=Cur=CNY","WssConvert=0","WssDivide=8","showcodes=N","cols=1;rows=1") -> -2.90647 | G52: =[1]!wss($A52:$A52,"hks_stm_is","item=61","rptDate="&($B52-2)&"1231","rptType=1","currencyType=Cur=CNY","WssConvert=0","WssDivide=8","showcodes=N","cols=1;rows=1") -> -2.62267 | H52: =[1]!wss($A52:$A52,"hks_stm_is","item=61","rptDate="&($B52-1)&"1231","rptType=1","currencyType=Cur=CNY","WssConvert=0","WssDivide=8","showcodes=N","cols=1;rows=1") -> -14.1501 | I52: =[1]!wss($A52:$A52,"hks_fa_grossprofitmargin","rptDate="&($B52-3)&"1231","WssConvert=0","showcodes=N","cols=1;rows=1") -> 26.727 | J52: =[1]!wss($A52:$A52,"hks_fa_grossprofitmargin","rptDate="&($B52-2)&"1231","WssConvert=0","showcodes=N","cols=1;rows=1") -> 30.4321 | K52: =[1]!wss($A52:$A52,"hks_fa_grossprofitmargin","rptDate="&($B52-1)&"1231","WssConvert=0","showcodes=N","cols=1;rows=1") -> 26.7943 | L52: =[1]!wss($A52:$A52,"hks_fa_roe","rptDate="&($B52-1)&"1231","WssConvert=0","showcodes=N","cols=1;rows=1") -> -44.7622 | M52: =[1]!wss($A52:$A52,"hks_fa_debttoassets","rptDate="&($B52-1)&"1231","WssConvert=0","showcodes=N","cols=1;rows=1") -> 37.8595 | P52: 114.73208 | Q52: 169.94025 | R52: 214.43827 | S52: 17.68926 | T52: 26.1756 | U52: 12.05045 | V52: 38.7255 | W52: 44.9397 | X52: 44.9925
